Workbook

Sheet Catalog
A1: ID | B1: UPC2 | C1: ISRC | D1: Tracks, Albums, Content | E1: Artist Name | F1: Release Date | G1: LABEL | H1: LABEL % | I1: Unique Artist Name | J1: Artist 1 | K1: Artist 1 % | L1: Artist 2 | M1: Artist 2 % | N1: Artist 3 | O1: Artist 3 % | P1: Artist 4 | Q1: Artist 4 % | R1: Artist 5 | S1: Artist 5 % | T1: Artist 6 | U1: Artist 6 % | V1: Artist 7 | W1: Artist 7 % | X1: Artist 8 | Y1: Artist 8 % | Z1: Artist 9 | AA1: Artist 9%
A2: 3617054108995FR-S18-22-65715 | B2: 3617054108995 | C2: FR-S18-22-65715 | D2: 44902 | E2: Los Dos Carnales | G2: AfinArte | H2: =100%-SUM(CatalogTable[[#This Row],[Artist 1 %]],CatalogTable[[#This Row],[Artist 2 %]],CatalogTable[[#This Row],[Artist 3 %]],CatalogTable[[#This Row],[Artist 4 %]],CatalogTable[[#This Row],[Artist 5 %]],CatalogTable[[#This Row],[Artist 6 %]],CatalogTable[[#This Row],[Artist 7 %]],CatalogTable[[#This Row],[Artist 8 %]],CatalogTable[[#This Row],[Artist 9%]]) -> 0.9 | I2: =IF(ISBLANK(E2),"",INDEX(UniqueArtist!B:B, MATCH(E2,UniqueArtist!A:A, 0))) -> Los Dos Carnales | J2: =IFERROR(TRIM(LEFT(I2, IFERROR(FIND(",", I2)-1, LEN(I2)))), "") -> Los Dos Carnales | K2: 0.1 | L2: =IFERROR(TRIM(MID(I2, FIND(",", I2) + 1, IFERROR(FIND(",", I2, FIND(",", I2) + 1) - FIND(",", I2) - 1, LEN(I2)))), "") | N2: =IFERROR(TRIM(MID(I2, FIND(",", I2, FIND(",", I2) + 1) + 1, IFERROR(FIND(",", I2, FIND(",", I2, FIND(",", I2) + 1) + 1) - FIND(",", I2, FIND(",", I2) + 1) - 1, LEN(I2)))), "") | P2: =IFERROR(TRIM(MID(I2, FIND(",", I2, FIND(",", I2, FIND(",", I2) + 1) + 1) + 1, IFERROR(FIND(",", I2, FIND(",", I2, FIND(",", I2, FIND(",", I2) + 1) + 1) + 1) - FIND(",", I2, FIND(",", I2, FIND(",", I2) + 1) + 1) - 1, LEN(I2)))), "") | R2: =IFERROR(TRIM(MID(I2, FIND(",", I2, FIND(",", I2, FIND(",", I2, FIND(",", I2) + 1) + 1) + 1) + 1, IFERROR(FIND(",", I2, FIND(",", I2, FIND(",", I2, FIND(",", I2, FIND(",", I2) + 1) + 1) + 1) + 1) - FIND(",", I2, FIND(",", I2, FIND(",", I2, FIND(",", I2) + 1) + 1) + 1) - 1, LEN(I2)))), "") | T2: =IFERROR(TRIM(MID(I2, FIND(",", I2, FIND(",", I2, FIND(",", I2, FIND(",", I2, FIND(",", I2, FIND(",", I2) + 1) + 1) + 1) + 1) + 1) + 1, IFERROR(FIND(",", I2, FIND(",", I2, FIND(",", I2, FIND(",", I2, FIND(",", I2, FIND(",", I2) + 1) + 1) + 1) + 1) + 1) - FIND(",", I2, FIND(",", I2, FIND(",", I2, FIND(",", I2, FIND(",", I2) + 1) + 1) + 1) + 1) - 1, LEN(I2)))), "") | V2: =IFERROR(TRIM(MID(I2, FIND(",", I2, FIND(",", I2, FIND(",", I2, FIND(",", I2, FIND(",", I2, FIND(",", I2, FIND(",", I2) + 1) + 1) + 1) + 1) + 1) + 1) + 1, IFERROR(FIND(",", I2, FIND(",", I2, FIND(",", I2, FIND(",", I2, FIND(",", I2, FIND(",", I2, FIND(",", I2) + 1) + 1) + 1) + 1) + 1) + 1) - FIND(",", I2, FIND(",", I2, FIND(",", I2, FIND(",", I2, FIND(",", I2, FIND(",", I2) + 1) + 1) + 1) + 1) + 1) - 1, LEN(I2)))), "") | X2: =IFERROR(TRIM(MID(I2, FIND(",", I2, FIND(",", I2, FIND(",", I2, FIND(",", I2, FIND(",", I2, FIND(",", I2, FIND(",", I2, FIND(",", I2) + 1) + 1) + 1) + 1) + 1) + 1) + 1) + 1, IFERROR(FIND(",", I2, FIND(",", I2, FIND(",", I2, FIND(",", I2, FIND(",", I2, FIND(",", I2, FIND(",", I2, FIND(",", I2) + 1) + 1) + 1) + 1) + 1) + 1) + 1) - FIND(",", I2, FIND(",", I2, FIND(",", I2, FIND(",", I2, FIND(",", I2, FIND(",", I2, FIND(",", I2) + 1) + 1) + 1) + 1) + 1) + 1) - 1, LEN(I2)))), "") | Z2: =IFERROR(TRIM(MID(I2, FIND(",", I2, FIND(",", I2, FIND(",", I2, FIND(",", I2, FIND(",", I2, FIND(",", I2, FIND(",", I2, FIND(",", I2, FIND(",", I2) + 1) + 1) + 1) + 1) + 1) + 1) + 1) + 1) + 1, IFERROR(FIND(",", I2, FIND(",", I2, FIND(",", I2, FIND(",", I2, FIND(",", I2, FIND(",", I2, FIND(",", I2, FIND(",", I2, FIND(",", I2) + 1) + 1) + 1) + 1) + 1) + 1) + 1) + 1) - FIND(",", I2, FIND(",", I2, FIND(",", I2, FIND(",", I2, FIND(",", I2, FIND(",", I2, FIND(",", I2, FIND(",", I2) + 1) + 1) + 1) + 1) + 1) + 1) + 1) - 1, LEN(I2)))), "")
A3: 3617050147738FR-X99-22-26351 | B3: 3617050147738 | C3: FR-X99-22-26351 | D3: ¡Azzzzzucar! #ElFantasma | E3: El Fantasma | G3: AfinArte | H3: =100%-SUM(CatalogTable[[#This Row],[Artist 1 %]],CatalogTable[[#This Row],[Artist 2 %]],CatalogTable[[#This Row],[Artist 3 %]],CatalogTable[[#This Row],[Artist 4 %]],CatalogTable[[#This Row],[Artist 5 %]],CatalogTable[[#This Row],[Artist 6 %]],CatalogTable[[#This Row],[Artist 7 %]],CatalogTable[[#This Row],[Artist 8 %]],CatalogTable[[#This Row],[Artist 9%]]) -> 0.65 | I3: =IF(ISBLANK(E3),"",INDEX(UniqueArtist!B:B, MATCH(E3,UniqueArtist!A:A, 0))) -> El Fantasma | J3: =IFERROR(TRIM(LEFT(I3, IFERROR(FIND(",", I3)-1, LEN(I3)))), "") -> El Fantasma | K3: 0.35 | L3: =IFERROR(TRIM(MID(I3, FIND(",", I3) + 1, IFERROR(FIND(",", I3, FIND(",", I3) + 1) - FIND(",", I3) - 1, LEN(I3)))), "") | N3: =IFERROR(TRIM(MID(I3, FIND(",", I3, FIND(",", I3) + 1) + 1, IFERROR(FIND(",", I3, FIND(",", I3, FIND(",", I3) + 1) + 1) - FIND(",", I3, FIND(",", I3) + 1) - 1, LEN(I3)))), "") | P3: =IFERROR(TRIM(MID(I3, FIND(",", I3, FIND(",", I3, FIND(",", I3) + 1) + 1) + 1, IFERROR(FIND(",", I3, FIND(",", I3, FIND(",", I3, FIND(",", I3) + 1) + 1) + 1) - FIND(",", I3, FIND(",", I3, FIND(",", I3) + 1) + 1) - 1, LEN(I3)))), "") | R3: =IFERROR(TRIM(MID(I3, FIND(",", I3, FIND(",", I3, FIND(",", I3, FIND(",", I3) + 1) + 1) + 1) + 1, IFERROR(FIND(",", I3, FIND(",", I3, FIND(",", I3, FIND(",", I3, FIND(",", I3) + 1) + 1) + 1) + 1) - FIND(",", I3, FIND(",", I3, FIND(",", I3, FIND(",", I3) + 1) + 1) + 1) - 1, LEN(I3)))), "") | T3: =IFERROR(TRIM(MID(I3, FIND(",", I3, FIND(",", I3, FIND(",", I3, FIND(",", I3, FIND(",", I3, FIND(",", I3) + 1) + 1) + 1) + 1) + 1) + 1, IFERROR(FIND(",", I3, FIND(",", I3, FIND(",", I3, FIND(",", I3, FIND(",", I3, FIND(",", I3) + 1) + 1) + 1) + 1) + 1) - FIND(",", I3, FIND(",", I3, FIND(",", I3, FIND(",", I3, FIND(",", I3) + 1) + 1) + 1) + 1) - 1, LEN(I3)))), "") | V3: =IFERROR(TRIM(MID(I3, FIND(",", I3, FIND(",", I3, FIND(",", I3, FIND(",", I3, FIND(",", I3, FIND(",", I3, FIND(",", I3) + 1) + 1) + 1) + 1) + 1) + 1) + 1, IFERROR(FIND(",", I3, FIND(",", I3, FIND(",", I3, FIND(",", I3, FIND(",", I3, FIND(",", I3, FIND(",", I3) + 1) + 1) + 1) + 1) + 1) + 1) - FIND(",", I3, FIND(",", I3, FIND(",", I3, FIND(",", I3, FIND(",", I3, FIND(",", I3) + 1) + 1) + 1) + 1) + 1) - 1, LEN(I3)))), "") | X3: =IFERROR(TRIM(MID(I3, FIND(",", I3, FIND(",", I3, FIND(",", I3, FIND(",", I3, FIND(",", I3, FIND(",", I3, FIND(",", I3, FIND(",", I3) + 1) + 1) + 1) + 1) + 1) + 1) + 1) + 1, IFERROR(FIND(",", I3, FIND(",", I3, FIND(",", I3, FIND(",", I3, FIND(",", I3, FIND(",", I3, FIND(",", I3, FIND(",", I3) + 1) + 1) + 1) + 1) + 1) + 1) + 1) - FIND(",", I3, FIND(",", I3, FIND(",", I3, FIND(",", I3, FIND(",", I3, FIND(",", I3, FIND(",", I3) + 1) + 1) + 1) + 1) + 1) + 1) - 1, LEN(I3)))), "") | Z3: =IFERROR(TRIM(MID(I3, FIND(",", I3, FIND(",", I3, FIND(",", I3, FIND(",", I3, FIND(",", I3, FIND(",", I3, FIND(",", I3, FIND(",", I3, FIND(",", I3) + 1) + 1) + 1) + 1) + 1) + 1) + 1) + 1) + 1, IFERROR(FIND(",", I3, FIND(",", I3, FIND(",", I3, FIND(",", I3, FIND(",", I3, FIND(",", I3, FIND(",", I3, FIND(",", I3, FIND(",", I3) + 1) + 1) + 1) + 1) + 1) + 1) + 1) + 1) - FIND(",", I3, FIND(",", I3, FIND(",", I3, FIND(",", I3, FIND(",", I3, FIND(",", I3, FIND(",", I3, FIND(",", I3) + 1) + 1) + 1) + 1) + 1) + 1) + 1) - 1, LEN(I3)))), "")
A4: 3617223765318FR-X99-23-93640 | B4: 3617223765318 | C4: FR-X99-23-93640 | D4: ¡Esperen al final! 😎😂 #ElParrandero #JrSalazar #Shorts #ShorteVideo #Fun #newrelease | E4: AfinArte Music | G4: AfinArte | H4: =100%-SUM(CatalogTable[[#This Row],[Artist 1 %]],CatalogTable[[#This Row],[Artist 2 %]],CatalogTable[[#This Row],[Artist 3 %]],CatalogTable[[#This Row],[Artist 4 %]],CatalogTable[[#This Row],[Artist 5 %]],CatalogTable[[#This Row],[Artist 6 %]],CatalogTable[[#This Row],[Artist 7 %]],CatalogTable[[#This Row],[Artist 8 %]],CatalogTable[[#This Row],[Artist 9%]]) -> 0 | I4: =IF(ISBLANK(E4),"",INDEX(UniqueArtist!B:B, MATCH(E4,UniqueArtist!A:A, 0))) -> AfinArte Music | J4: =IFERROR(TRIM(LEFT(I4, IFERROR(FIND(",", I4)-1, LEN(I4)))), "") -> AfinArte Music | K4: 1 | L4: =IFERROR(TRIM(MID(I4, FIND(",", I4) + 1, IFERROR(FIND(",", I4, FIND(",", I4) + 1) - FIND(",", I4) - 1, LEN(I4)))), "") | N4: =IFERROR(TRIM(MID(I4, FIND(",", I4, FIND(",", I4) + 1) + 1, IFERROR(FIND(",", I4, FIND(",", I4, FIND(",", I4) + 1) + 1) - FIND(",", I4, FIND(",", I4) + 1) - 1, LEN(I4)))), "") | P4: =IFERROR(TRIM(MID(I4, FIND(",", I4, FIND(",", I4, FIND(",", I4) + 1) + 1) + 1, IFERROR(FIND(",", I4, FIND(",", I4, FIND(",", I4, FIND(",", I4) + 1) + 1) + 1) - FIND(",", I4, FIND(",", I4, FIND(",", I4) + 1) + 1) - 1, LEN(I4)))), "") | R4: =IFERROR(TRIM(MID(I4, FIND(",", I4, FIND(",", I4, FIND(",", I4, FIND(",", I4) + 1) + 1) + 1) + 1, IFERROR(FIND(",", I4, FIND(",", I4, FIND(",", I4, FIND(",", I4, FIND(",", I4) + 1) + 1) + 1) + 1) - FIND(",", I4, FIND(",", I4, FIND(",", I4, FIND(",", I4) + 1) + 1) + 1) - 1, LEN(I4)))), "") | T4: =IFERROR(TRIM(MID(I4, FIND(",", I4, FIND(",", I4, FIND(",", I4, FIND(",", I4, FIND(",", I4, FIND(",", I4) + 1) + 1) + 1) + 1) + 1) + 1, IFERROR(FIND(",", I4, FIND(",", I4, FIND(",", I4, FIND(",", I4, FIND(",", I4, FIND(",", I4) + 1) + 1) + 1) + 1) + 1) - FIND(",", I4, FIND(",", I4, FIND(",", I4, FIND(",", I4, FIND(",", I4) + 1) + 1) + 1) + 1) - 1, LEN(I4)))), "") | V4: =IFERROR(TRIM(MID(I4, FIND(",", I4, FIND(",", I4, FIND(",", I4, FIND(",", I4, FIND(",", I4, FIND(",", I4, FIND(",", I4) + 1) + 1) + 1) + 1) + 1) + 1) + 1, IFERROR(FIND(",", I4, FIND(",", I4, FIND(",", I4, FIND(",", I4, FIND(",", I4, FIND(",", I4, FIND(",", I4) + 1) + 1) + 1) + 1) + 1) + 1) - FIND(",", I4, FIND(",", I4, FIND(",", I4, FIND(",", I4, FIND(",", I4, FIND(",", I4) + 1) + 1) + 1) + 1) + 1) - 1, LEN(I4)))), "") | X4: =IFERROR(TRIM(MID(I4, FIND(",", I4, FIND(",", I4, FIND(",", I4, FIND(",", I4, FIND(",", I4, FIND(",", I4, FIND(",", I4, FIND(",", I4) + 1) + 1) + 1) + 1) + 1) + 1) + 1) + 1, IFERROR(FIND(",", I4, FIND(",", I4, FIND(",", I4, FIND(",", I4, FIND(",", I4, FIND(",", I4, FIND(",", I4, FIND(",", I4) + 1) + 1) + 1) + 1) + 1) + 1) + 1) - FIND(",", I4, FIND(",", I4, FIND(",", I4, FIND(",", I4, FIND(",", I4, FIND(",", I4, FIND(",", I4) + 1) + 1) + 1) + 1) + 1) + 1) - 1, LEN(I4)))), "") | Z4: =IFERROR(TRIM(MID(I4, FIND(",", I4, FIND(",", I4, FIND(",", I4, FIND(",", I4, FIND(",", I4, FIND(",", I4, FIND(",", I4, FIND(",", I4, FIND(",", I4) + 1) + 1) + 1) + 1) + 1) + 1) + 1) + 1) + 1, IFERROR(FIND(",", I4, FIND(",", I4, FIND(",", I4, FIND(",", I4, FIND(",", I4, FIND(",", I4, FIND(",", I4, FIND(",", I4, FIND(",", I4) + 1) + 1) + 1) + 1) + 1) + 1) + 1) + 1) - FIND(",", I4, FIND(",", I4, FIND(",", I4, FIND(",", I4, FIND(",", I4, FIND(",", I4, FIND(",", I4, FIND(",", I4) + 1) + 1) + 1) + 1) + 1) + 1) + 1) - 1, LEN(I4)))), "")
A5: 3617055399231FR-W24-23-13929 | B5: 3617055399231 | C5: FR-W24-23-13929 | D5: ¡Estamos de vuelta!~~~~~~ #FantasmaClassics #2daTemporada #AfinArteMusic #ElFantasma | E5: El Fantasma | G5: AfinArte | H5: =100%-SUM(CatalogTable[[#This Row],[Artist 1 %]],CatalogTable[[#This Row],[Artist 2 %]],CatalogTable[[#This Row],[Artist 3 %]],CatalogTable[[#This Row],[Artist 4 %]],CatalogTable[[#This Row],[Artist 5 %]],CatalogTable[[#This Row],[Artist 6 %]],CatalogTable[[#This Row],[Artist 7 %]],CatalogTable[[#This Row],[Artist 8 %]],CatalogTable[[#This Row],[Artist 9%]]) -> 0.65 | I5: =IF(ISBLANK(E5),"",INDEX(UniqueArtist!B:B, MATCH(E5,UniqueArtist!A:A, 0))) -> El Fantasma | J5: =IFERROR(TRIM(LEFT(I5, IFERROR(FIND(",", I5)-1, LEN(I5)))), "") -> El Fantasma | K5: 0.35 | L5: =IFERROR(TRIM(MID(I5, FIND(",", I5) + 1, IFERROR(FIND(",", I5, FIND(",", I5) + 1) - FIND(",", I5) - 1, LEN(I5)))), "") | N5: =IFERROR(TRIM(MID(I5, FIND(",", I5, FIND(",", I5) + 1) + 1, IFERROR(FIND(",", I5, FIND(",", I5, FIND(",", I5) + 1) + 1) - FIND(",", I5, FIND(",", I5) + 1) - 1, LEN(I5)))), "") | P5: =IFERROR(TRIM(MID(I5, FIND(",", I5, FIND(",", I5, FIND(",", I5) + 1) + 1) + 1, IFERROR(FIND(",", I5, FIND(",", I5, FIND(",", I5, FIND(",", I5) + 1) + 1) + 1) - FIND(",", I5, FIND(",", I5, FIND(",", I5) + 1) + 1) - 1, LEN(I5)))), "") | R5: =IFERROR(TRIM(MID(I5, FIND(",", I5, FIND(",", I5, FIND(",", I5, FIND(",", I5) + 1) + 1) + 1) + 1, IFERROR(FIND(",", I5, FIND(",", I5, FIND(",", I5, FIND(",", I5, FIND(",", I5) + 1) + 1) + 1) + 1) - FIND(",", I5, FIND(",", I5, FIND(",", I5, FIND(",", I5) + 1) + 1) + 1) - 1, LEN(I5)))), "") | T5: =IFERROR(TRIM(MID(I5, FIND(",", I5, FIND(",", I5, FIND(",", I5, FIND(",", I5, FIND(",", I5, FIND(",", I5) + 1) + 1) + 1) + 1) + 1) + 1, IFERROR(FIND(",", I5, FIND(",", I5, FIND(",", I5, FIND(",", I5, FIND(",", I5, FIND(",", I5) + 1) + 1) + 1) + 1) + 1) - FIND(",", I5, FIND(",", I5, FIND(",", I5, FIND(",", I5, FIND(",", I5) + 1) + 1) + 1) + 1) - 1, LEN(I5)))), "") | V5: =IFERROR(TRIM(MID(I5, FIND(",", I5, FIND(",", I5, FIND(",", I5, FIND(",", I5, FIND(",", I5, FIND(",", I5, FIND(",", I5) + 1) + 1) + 1) + 1) + 1) + 1) + 1, IFERROR(FIND(",", I5, FIND(",", I5, FIND(",", I5, FIND(",", I5, FIND(",", I5, FIND(",", I5, FIND(",", I5) + 1) + 1) + 1) + 1) + 1) + 1) - FIND(",", I5, FIND(",", I5, FIND(",", I5, FIND(",", I5, FIND(",", I5, FIND(",", I5) + 1) + 1) + 1) + 1) + 1) - 1, LEN(I5)))), "") | X5: =IFERROR(TRIM(MID(I5, FIND(",", I5, FIND(",", I5, FIND(",", I5, FIND(",", I5, FIND(",", I5, FIND(",", I5, FIND(",", I5, FIND(",", I5) + 1) + 1) + 1) + 1) + 1) + 1) + 1) + 1, IFERROR(FIND(",", I5, FIND(",", I5, FIND(",", I5, FIND(",", I5, FIND(",", I5, FIND(",", I5, FIND(",", I5, FIND(",", I5) + 1) + 1) + 1) + 1) + 1) + 1) + 1) - FIND(",", I5, FIND(",", I5, FIND(",", I5, FIND(",", I5, FIND(",", I5, FIND(",", I5, FIND(",", I5) + 1) + 1) + 1) + 1) + 1) + 1) - 1, LEN(I5)))), "") | Z5: =IFERROR(TRIM(MID(I5, FIND(",", I5, FIND(",", I5, FIND(",", I5, FIND(",", I5, FIND(",", I5, FIND(",", I5, FIND(",", I5, FIND(",", I5, FIND(",", I5) + 1) + 1) + 1) + 1) + 1) + 1) + 1) + 1) + 1, IFERROR(FIND(",", I5, FIND(",", I5, FIND(",", I5, FIND(",", I5, FIND(",", I5, FIND(",", I5, FIND(",", I5, FIND(",", I5, FIND(",", I5) + 1) + 1) + 1) + 1) + 1) + 1) + 1) + 1) - FIND(",", I5, FIND(",", I5, FIND(",", I5, FIND(",", I5, FIND(",", I5, FIND(",", I5, FIND(",", I5, FIND(",", I5) + 1) + 1) + 1) + 1) + 1) + 1) + 1) - 1, LEN(I5)))), "")
A6: 3616842123998DG-A0D-21-15652 | B6: 3616842123998 | C6: DG-A0D-21-15652 | D6: ¡Este si es un buen taco señores! #elfantasma #afinartemusic #mexicanfood | E6: El Fantasma | G6: AfinArte | H6: =100%-SUM(CatalogTable[[#This Row],[Artist 1 %]],CatalogTable[[#This Row],[Artist 2 %]],CatalogTable[[#This Row],[Artist 3 %]],CatalogTable[[#This Row],[Artist 4 %]],CatalogTable[[#This Row],[Artist 5 %]],CatalogTable[[#This Row],[Artist 6 %]],CatalogTable[[#This Row],[Artist 7 %]],CatalogTable[[#This Row],[Artist 8 %]],CatalogTable[[#This Row],[Artist 9%]]) -> 0.65 | I6: =IF(ISBLANK(E6),"",INDEX(UniqueArtist!B:B, MATCH(E6,UniqueArtist!A:A, 0))) -> El Fantasma | J6: =IFERROR(TRIM(LEFT(I6, IFERROR(FIND(",", I6)-1, LEN(I6)))), "") -> El Fantasma | K6: 0.35 | L6: =IFERROR(TRIM(MID(I6, FIND(",", I6) + 1, IFERROR(FIND(",", I6, FIND(",", I6) + 1) - FIND(",", I6) - 1, LEN(I6)))), "") | N6: =IFERROR(TRIM(MID(I6, FIND(",", I6, FIND(",", I6) + 1) + 1, IFERROR(FIND(",", I6, FIND(",", I6, FIND(",", I6) + 1) + 1) - FIND(",", I6, FIND(",", I6) + 1) - 1, LEN(I6)))), "") | P6: =IFERROR(TRIM(MID(I6, FIND(",", I6, FIND(",", I6, FIND(",", I6) + 1) + 1) + 1, IFERROR(FIND(",", I6, FIND(",", I6, FIND(",", I6, FIND(",", I6) + 1) + 1) + 1) - FIND(",", I6, FIND(",", I6, FIND(",", I6) + 1) + 1) - 1, LEN(I6)))), "") | R6: =IFERROR(TRIM(MID(I6, FIND(",", I6, FIND(",", I6, FIND(",", I6, FIND(",", I6) + 1) + 1) + 1) + 1, IFERROR(FIND(",", I6, FIND(",", I6, FIND(",", I6, FIND(",", I6, FIND(",", I6) + 1) + 1) + 1) + 1) - FIND(",", I6, FIND(",", I6, FIND(",", I6, FIND(",", I6) + 1) + 1) + 1) - 1, LEN(I6)))), "") | T6: =IFERROR(TRIM(MID(I6, FIND(",", I6, FIND(",", I6, FIND(",", I6, FIND(",", I6, FIND(",", I6, FIND(",", I6) + 1) + 1) + 1) + 1) + 1) + 1, IFERROR(FIND(",", I6, FIND(",", I6, FIND(",", I6, FIND(",", I6, FIND(",", I6, FIND(",", I6) + 1) + 1) + 1) + 1) + 1) - FIND(",", I6, FIND(",", I6, FIND(",", I6, FIND(",", I6, FIND(",", I6) + 1) + 1) + 1) + 1) - 1, LEN(I6)))), "") | V6: =IFERROR(TRIM(MID(I6, FIND(",", I6, FIND(",", I6, FIND(",", I6, FIND(",", I6, FIND(",", I6, FIND(",", I6, FIND(",", I6) + 1) + 1) + 1) + 1) + 1) + 1) + 1, IFERROR(FIND(",", I6, FIND(",", I6, FIND(",", I6, FIND(",", I6, FIND(",", I6, FIND(",", I6, FIND(",", I6) + 1) + 1) + 1) + 1) + 1) + 1) - FIND(",", I6, FIND(",", I6, FIND(",", I6, FIND(",", I6, FIND(",", I6, FIND(",", I6) + 1) + 1) + 1) + 1) + 1) - 1, LEN(I6)))), "") | X6: =IFERROR(TRIM(MID(I6, FIND(",", I6, FIND(",", I6, FIND(",", I6, FIND(",", I6, FIND(",", I6, FIND(",", I6, FIND(",", I6, FIND(",", I6) + 1) + 1) + 1) + 1) + 1) + 1) + 1) + 1, IFERROR(FIND(",", I6, FIND(",", I6, FIND(",", I6, FIND(",", I6, FIND(",", I6, FIND(",", I6, FIND(",", I6, FIND(",", I6) + 1) + 1) + 1) + 1) + 1) + 1) + 1) - FIND(",", I6, FIND(",", I6, FIND(",", I6, FIND(",", I6, FIND(",", I6, FIND(",", I6, FIND(",", I6) + 1) + 1) + 1) + 1) + 1) + 1) - 1, LEN(I6)))), "") | Z6: =IFERROR(TRIM(MID(I6, FIND(",", I6, FIND(",", I6, FIND(",", I6, FIND(",", I6, FIND(",", I6, FIND(",", I6, FIND(",", I6, FIND(",", I6, FIND(",", I6) + 1) + 1) + 1) + 1) + 1) + 1) + 1) + 1) + 1, IFERROR(FIND(",", I6, FIND(",", I6, FIND(",", I6, FIND(",", I6, FIND(",", I6, FIND(",", I6, FIND(",", I6, FIND(",", I6, FIND(",", I6) + 1) + 1) + 1) + 1) + 1) + 1) + 1) + 1) - FIND(",", I6, FIND(",", I6, FIND(",", I6, FIND(",", I6, FIND(",", I6, FIND(",", I6, FIND(",", I6, FIND(",", I6) + 1) + 1) + 1) + 1) + 1) + 1) + 1) - 1, LEN(I6)))), "")
A7: 3616842202228DG-A0D-21-20565 | B7: 3616842202228 | C7: DG-A0D-21-20565 | D7: ¡Gracias por todo! #republicadominicana #ElFantasma #afinartemusic | E7: El Fantasma | G7: AfinArte | H7: =100%-SUM(CatalogTable[[#This Row],[Artist 1 %]],CatalogTable[[#This Row],[Artist 2 %]],CatalogTable[[#This Row],[Artist 3 %]],CatalogTable[[#This Row],[Artist 4 %]],CatalogTable[[#This Row],[Artist 5 %]],CatalogTable[[#This Row],[Artist 6 %]],CatalogTable[[#This Row],[Artist 7 %]],CatalogTable[[#This Row],[Artist 8 %]],CatalogTable[[#This Row],[Artist 9%]]) -> 0.65 | I7: =IF(ISBLANK(E7),"",INDEX(UniqueArtist!B:B, MATCH(E7,UniqueArtist!A:A, 0))) -> El Fantasma | J7: =IFERROR(TRIM(LEFT(I7, IFERROR(FIND(",", I7)-1, LEN(I7)))), "") -> El Fantasma | K7: 0.35 | L7: =IFERROR(TRIM(MID(I7, FIND(",", I7) + 1, IFERROR(FIND(",", I7, FIND(",", I7) + 1) - FIND(",", I7) - 1, LEN(I7)))), "") | N7: =IFERROR(TRIM(MID(I7, FIND(",", I7, FIND(",", I7) + 1) + 1, IFERROR(FIND(",", I7, FIND(",", I7, FIND(",", I7) + 1) + 1) - FIND(",", I7, FIND(",", I7) + 1) - 1, LEN(I7)))), "") | P7: =IFERROR(TRIM(MID(I7, FIND(",", I7, FIND(",", I7, FIND(",", I7) + 1) + 1) + 1, IFERROR(FIND(",", I7, FIND(",", I7, FIND(",", I7, FIND(",", I7) + 1) + 1) + 1) - FIND(",", I7, FIND(",", I7, FIND(",", I7) + 1) + 1) - 1, LEN(I7)))), "") | R7: =IFERROR(TRIM(MID(I7, FIND(",", I7, FIND(",", I7, FIND(",", I7, FIND(",", I7) + 1) + 1) + 1) + 1, IFERROR(FIND(",", I7, FIND(",", I7, FIND(",", I7, FIND(",", I7, FIND(",", I7) + 1) + 1) + 1) + 1) - FIND(",", I7, FIND(",", I7, FIND(",", I7, FIND(",", I7) + 1) + 1) + 1) - 1, LEN(I7)))), "") | T7: =IFERROR(TRIM(MID(I7, FIND(",", I7, FIND(",", I7, FIND(",", I7, FIND(",", I7, FIND(",", I7, FIND(",", I7) + 1) + 1) + 1) + 1) + 1) + 1, IFERROR(FIND(",", I7, FIND(",", I7, FIND(",", I7, FIND(",", I7, FIND(",", I7, FIND(",", I7) + 1) + 1) + 1) + 1) + 1) - FIND(",", I7, FIND(",", I7, FIND(",", I7, FIND(",", I7, FIND(",", I7) + 1) + 1) + 1) + 1) - 1, LEN(I7)))), "") | V7: =IFERROR(TRIM(MID(I7, FIND(",", I7, FIND(",", I7, FIND(",", I7, FIND(",", I7, FIND(",", I7, FIND(",", I7, FIND(",", I7) + 1) + 1) + 1) + 1) + 1) + 1) + 1, IFERROR(FIND(",", I7, FIND(",", I7, FIND(",", I7, FIND(",", I7, FIND(",", I7, FIND(",", I7, FIND(",", I7) + 1) + 1) + 1) + 1) + 1) + 1) - FIND(",", I7, FIND(",", I7, FIND(",", I7, FIND(",", I7, FIND(",", I7, FIND(",", I7) + 1) + 1) + 1) + 1) + 1) - 1, LEN(I7)))), "") | X7: =IFERROR(TRIM(MID(I7, FIND(",", I7, FIND(",", I7, FIND(",", I7, FIND(",", I7, FIND(",", I7, FIND(",", I7, FIND(",", I7, FIND(",", I7) + 1) + 1) + 1) + 1) + 1) + 1) + 1) + 1, IFERROR(FIND(",", I7, FIND(",", I7, FIND(",", I7, FIND(",", I7, FIND(",", I7, FIND(",", I7, FIND(",", I7, FIND(",", I7) + 1) + 1) + 1) + 1) + 1) + 1) + 1) - FIND(",", I7, FIND(",", I7, FIND(",", I7, FIND(",", I7, FIND(",", I7, FIND(",", I7, FIND(",", I7) + 1) + 1) + 1) + 1) + 1) + 1) - 1, LEN(I7)))), "") | Z7: =IFERROR(TRIM(MID(I7, FIND(",", I7, FIND(",", I7, FIND(",", I7, FIND(",", I7, FIND(",", I7, FIND(",", I7, FIND(",", I7, FIND(",", I7, FIND(",", I7) + 1) + 1) + 1) + 1) + 1) + 1) + 1) + 1) + 1, IFERROR(FIND(",", I7, FIND(",", I7, FIND(",", I7, FIND(",", I7, FIND(",", I7, FIND(",", I7, FIND(",", I7, FIND(",", I7, FIND(",", I7) + 1) + 1) + 1) + 1) + 1) + 1) + 1) + 1) - FIND(",", I7, FIND(",", I7, FIND(",", I7, FIND(",", I7, FIND(",", I7, FIND(",", I7, FIND(",", I7, FIND(",", I7) + 1) + 1) + 1) + 1) + 1) + 1) + 1) - 1, LEN(I7)))), "")
A8: 3616842171241DG-A0D-21-18366 | B8: 3616842171241 | C8: DG-A0D-21-18366 | D8: ¡hay que celebrar no importa el motivo! ¿ustedes que piensan mi gente? #losdoscarnales #AfinArte | E8: Los Dos Carnales | G8: AfinArte | H8: =100%-SUM(CatalogTable[[#This Row],[Artist 1 %]],CatalogTable[[#This Row],[Artist 2 %]],CatalogTable[[#This Row],[Artist 3 %]],CatalogTable[[#This Row],[Artist 4 %]],CatalogTable[[#This Row],[Artist 5 %]],CatalogTable[[#This Row],[Artist 6 %]],CatalogTable[[#This Row],[Artist 7 %]],CatalogTable[[#This Row],[Artist 8 %]],CatalogTable[[#This Row],[Artist 9%]]) -> 0.9 | I8: =IF(ISBLANK(E8),"",INDEX(UniqueArtist!B:B, MATCH(E8,UniqueArtist!A:A, 0))) -> Los Dos Carnales | J8: =IFERROR(TRIM(LEFT(I8, IFERROR(FIND(",", I8)-1, LEN(I8)))), "") -> Los Dos Carnales | K8: 0.1 | L8: =IFERROR(TRIM(MID(I8, FIND(",", I8) + 1, IFERROR(FIND(",", I8, FIND(",", I8) + 1) - FIND(",", I8) - 1, LEN(I8)))), "") | N8: =IFERROR(TRIM(MID(I8, FIND(",", I8, FIND(",", I8) + 1) + 1, IFERROR(FIND(",", I8, FIND(",", I8, FIND(",", I8) + 1) + 1) - FIND(",", I8, FIND(",", I8) + 1) - 1, LEN(I8)))), "") | P8: =IFERROR(TRIM(MID(I8, FIND(",", I8, FIND(",", I8, FIND(",", I8) + 1) + 1) + 1, IFERROR(FIND(",", I8, FIND(",", I8, FIND(",", I8, FIND(",", I8) + 1) + 1) + 1) - FIND(",", I8, FIND(",", I8, FIND(",", I8) + 1) + 1) - 1, LEN(I8)))), "") | R8: =IFERROR(TRIM(MID(I8, FIND(",", I8, FIND(",", I8, FIND(",", I8, FIND(",", I8) + 1) + 1) + 1) + 1, IFERROR(FIND(",", I8, FIND(",", I8, FIND(",", I8, FIND(",", I8, FIND(",", I8) + 1) + 1) + 1) + 1) - FIND(",", I8, FIND(",", I8, FIND(",", I8, FIND(",", I8) + 1) + 1) + 1) - 1, LEN(I8)))), "") | T8: =IFERROR(TRIM(MID(I8, FIND(",", I8, FIND(",", I8, FIND(",", I8, FIND(",", I8, FIND(",", I8, FIND(",", I8) + 1) + 1) + 1) + 1) + 1) + 1, IFERROR(FIND(",", I8, FIND(",", I8, FIND(",", I8, FIND(",", I8, FIND(",", I8, FIND(",", I8) + 1) + 1) + 1) + 1) + 1) - FIND(",", I8, FIND(",", I8, FIND(",", I8, FIND(",", I8, FIND(",", I8) + 1) + 1) + 1) + 1) - 1, LEN(I8)))), "") | V8: =IFERROR(TRIM(MID(I8, FIND(",", I8, FIND(",", I8, FIND(",", I8, FIND(",", I8, FIND(",", I8, FIND(",", I8, FIND(",", I8) + 1) + 1) + 1) + 1) + 1) + 1) + 1, IFERROR(FIND(",", I8, FIND(",", I8, FIND(",", I8, FIND(",", I8, FIND(",", I8, FIND(",", I8, FIND(",", I8) + 1) + 1) + 1) + 1) + 1) + 1) - FIND(",", I8, FIND(",", I8, FIND(",", I8, FIND(",", I8, FIND(",", I8, FIND(",", I8) + 1) + 1) + 1) + 1) + 1) - 1, LEN(I8)))), "") | X8: =IFERROR(TRIM(MID(I8, FIND(",", I8, FIND(",", I8, FIND(",", I8, FIND(",", I8, FIND(",", I8, FIND(",", I8, FIND(",", I8, FIND(",", I8) + 1) + 1) + 1) + 1) + 1) + 1) + 1) + 1, IFERROR(FIND(",", I8, FIND(",", I8, FIND(",", I8, FIND(",", I8, FIND(",", I8, FIND(",", I8, FIND(",", I8, FIND(",", I8) + 1) + 1) + 1) + 1) + 1) + 1) + 1) - FIND(",", I8, FIND(",", I8, FIND(",", I8, FIND(",", I8, FIND(",", I8, FIND(",", I8, FIND(",", I8) + 1) + 1) + 1) + 1) + 1) + 1) - 1, LEN(I8)))), "") | Z8: =IFERROR(TRIM(MID(I8, FIND(",", I8, FIND(",", I8, FIND(",", I8, FIND(",", I8, FIND(",", I8, FIND(",", I8, FIND(",", I8, FIND(",", I8, FIND(",", I8) + 1) + 1) + 1) + 1) + 1) + 1) + 1) + 1) + 1, IFERROR(FIND(",", I8, FIND(",", I8, FIND(",", I8, FIND(",", I8, FIND(",", I8, FIND(",", I8, FIND(",", I8, FIND(",", I8, FIND(",", I8) + 1) + 1) + 1) + 1) + 1) + 1) + 1) + 1) - FIND(",", I8, FIND(",", I8, FIND(",", I8, FIND(",", I8, FIND(",", I8, FIND(",", I8, FIND(",", I8, FIND(",", I8) + 1) + 1) + 1) + 1) + 1) + 1) + 1) - 1, LEN(I8)))), "")
A9: 3617053324594FR-S18-22-43262 | B9: 3617053324594 | C9: FR-S18-22-43262 | D9: ¡Like ???????? para Parte ✌???? mi gente! #Tureando #EstadosUnidos #LosDosCarnales #AfinArteMusic | E9: Los Dos Carnales | G9: AfinArte | H9: =100%-SUM(CatalogTable[[#This Row],[Artist 1 %]],CatalogTable[[#This Row],[Artist 2 %]],CatalogTable[[#This Row],[Artist 3 %]],CatalogTable[[#This Row],[Artist 4 %]],CatalogTable[[#This Row],[Artist 5 %]],CatalogTable[[#This Row],[Artist 6 %]],CatalogTable[[#This Row],[Artist 7 %]],CatalogTable[[#This Row],[Artist 8 %]],CatalogTable[[#This Row],[Artist 9%]]) -> 0.9 | I9: =IF(ISBLANK(E9),"",INDEX(UniqueArtist!B:B, MATCH(E9,UniqueArtist!A:A, 0))) -> Los Dos Carnales | J9: =IFERROR(TRIM(LEFT(I9, IFERROR(FIND(",", I9)-1, LEN(I9)))), "") -> Los Dos Carnales | K9: 0.1 | L9: =IFERROR(TRIM(MID(I9, FIND(",", I9) + 1, IFERROR(FIND(",", I9, FIND(",", I9) + 1) - FIND(",", I9) - 1, LEN(I9)))), "") | N9: =IFERROR(TRIM(MID(I9, FIND(",", I9, FIND(",", I9) + 1) + 1, IFERROR(FIND(",", I9, FIND(",", I9, FIND(",", I9) + 1) + 1) - FIND(",", I9, FIND(",", I9) + 1) - 1, LEN(I9)))), "") | P9: =IFERROR(TRIM(MID(I9, FIND(",", I9, FIND(",", I9, FIND(",", I9) + 1) + 1) + 1, IFERROR(FIND(",", I9, FIND(",", I9, FIND(",", I9, FIND(",", I9) + 1) + 1) + 1) - FIND(",", I9, FIND(",", I9, FIND(",", I9) + 1) + 1) - 1, LEN(I9)))), "") | R9: =IFERROR(TRIM(MID(I9, FIND(",", I9, FIND(",", I9, FIND(",", I9, FIND(",", I9) + 1) + 1) + 1) + 1, IFERROR(FIND(",", I9, FIND(",", I9, FIND(",", I9, FIND(",", I9, FIND(",", I9) + 1) + 1) + 1) + 1) - FIND(",", I9, FIND(",", I9, FIND(",", I9, FIND(",", I9) + 1) + 1) + 1) - 1, LEN(I9)))), "") | T9: =IFERROR(TRIM(MID(I9, FIND(",", I9, FIND(",", I9, FIND(",", I9, FIND(",", I9, FIND(",", I9, FIND(",", I9) + 1) + 1) + 1) + 1) + 1) + 1, IFERROR(FIND(",", I9, FIND(",", I9, FIND(",", I9, FIND(",", I9, FIND(",", I9, FIND(",", I9) + 1) + 1) + 1) + 1) + 1) - FIND(",", I9, FIND(",", I9, FIND(",", I9, FIND(",", I9, FIND(",", I9) + 1) + 1) + 1) + 1) - 1, LEN(I9)))), "") | V9: =IFERROR(TRIM(MID(I9, FIND(",", I9, FIND(",", I9, FIND(",", I9, FIND(",", I9, FIND(",", I9, FIND(",", I9, FIND(",", I9) + 1) + 1) + 1) + 1) + 1) + 1) + 1, IFERROR(FIND(",", I9, FIND(",", I9, FIND(",", I9, FIND(",", I9, FIND(",", I9, FIND(",", I9, FIND(",", I9) + 1) + 1) + 1) + 1) + 1) + 1) - FIND(",", I9, FIND(",", I9, FIND(",", I9, FIND(",", I9, FIND(",", I9, FIND(",", I9) + 1) + 1) + 1) + 1) + 1) - 1, LEN(I9)))), "") | X9: =IFERROR(TRIM(MID(I9, FIND(",", I9, FIND(",", I9, FIND(",", I9, FIND(",", I9, FIND(",", I9, FIND(",", I9, FIND(",", I9, FIND(",", I9) + 1) + 1) + 1) + 1) + 1) + 1) + 1) + 1, IFERROR(FIND(",", I9, FIND(",", I9, FIND(",", I9, FIND(",", I9, FIND(",", I9, FIND(",", I9, FIND(",", I9, FIND(",", I9) + 1) + 1) + 1) + 1) + 1) + 1) + 1) - FIND(",", I9, FIND(",", I9, FIND(",", I9, FIND(",", I9, FIND(",", I9, FIND(",", I9, FIND(",", I9) + 1) + 1) + 1) + 1) + 1) + 1) - 1, LEN(I9)))), "") | Z9: =IFERROR(TRIM(MID(I9, FIND(",", I9, FIND(",", I9, FIND(",", I9, FIND(",", I9, FIND(",", I9, FIND(",", I9, FIND(",", I9, FIND(",", I9, FIND(",", I9) + 1) + 1) + 1) + 1) + 1) + 1) + 1) + 1) + 1, IFERROR(FIND(",", I9, FIND(",", I9, FIND(",", I9, FIND(",", I9, FIND(",", I9, FIND(",", I9, FIND(",", I9, FIND(",", I9, FIND(",", I9) + 1) + 1) + 1) + 1) + 1) + 1) + 1) + 1) - FIND(",", I9, FIND(",", I9, FIND(",", I9, FIND(",", I9, FIND(",", I9, FIND(",", I9, FIND(",", I9, FIND(",", I9) + 1) + 1) + 1) + 1) + 1) + 1) + 1) - 1, LEN(I9)))), "")
A10: 3617052285391FR-S18-22-03373 | B10: 3617052285391 | C10: FR-S18-22-03373 | D10: ¡Los Quiero #Tijuana! @Adriana Ríos #AfinArteMusic #FeriaDeTijuana | E10: Adriana Ríos | G10: AfinArte | H10: =100%-SUM(CatalogTable[[#This Row],[Artist 1 %]],CatalogTable[[#This Row],[Artist 2 %]],CatalogTable[[#This Row],[Artist 3 %]],CatalogTable[[#This Row],[Artist 4 %]],CatalogTable[[#This Row],[Artist 5 %]],CatalogTable[[#This Row],[Artist 6 %]],CatalogTable[[#This Row],[Artist 7 %]],CatalogTable[[#This Row],[Artist 8 %]],CatalogTable[[#This Row],[Artist 9%]]) -> 0.9 | I10: =IF(ISBLANK(E10),"",INDEX(UniqueArtist!B:B, MATCH(E10,UniqueArtist!A:A, 0))) -> Adriana Rios | J10: =IFERROR(TRIM(LEFT(I10, IFERROR(FIND(",", I10)-1, LEN(I10)))), "") -> Adriana Rios | K10: 0.1 | L10: =IFERROR(TRIM(MID(I10, FIND(",", I10) + 1, IFERROR(FIND(",", I10, FIND(",", I10) + 1) - FIND(",", I10) - 1, LEN(I10)))), "") | N10: =IFERROR(TRIM(MID(I10, FIND(",", I10, FIND(",", I10) + 1) + 1, IFERROR(FIND(",", I10, FIND(",", I10, FIND(",", I10) + 1) + 1) - FIND(",", I10, FIND(",", I10) + 1) - 1, LEN(I10)))), "") | P10: =IFERROR(TRIM(MID(I10, FIND(",", I10, FIND(",", I10, FIND(",", I10) + 1) + 1) + 1, IFERROR(FIND(",", I10, FIND(",", I10, FIND(",", I10, FIND(",", I10) + 1) + 1) + 1) - FIND(",", I10, FIND(",", I10, FIND(",", I10) + 1) + 1) - 1, LEN(I10)))), "") | R10: =IFERROR(TRIM(MID(I10, FIND(",", I10, FIND(",", I10, FIND(",", I10, FIND(",", I10) + 1) + 1) + 1) + 1, IFERROR(FIND(",", I10, FIND(",", I10, FIND(",", I10, FIND(",", I10, FIND(",", I10) + 1) + 1) + 1) + 1) - FIND(",", I10, FIND(",", I10, FIND(",", I10, FIND(",", I10) + 1) + 1) + 1) - 1, LEN(I10)))), "") | T10: =IFERROR(TRIM(MID(I10, FIND(",", I10, FIND(",", I10, FIND(",", I10, FIND(",", I10, FIND(",", I10, FIND(",", I10) + 1) + 1) + 1) + 1) + 1) + 1, IFERROR(FIND(",", I10, FIND(",", I10, FIND(",", I10, FIND(",", I10, FIND(",", I10, FIND(",", I10) + 1) + 1) + 1) + 1) + 1) - FIND(",", I10, FIND(",", I10, FIND(",", I10, FIND(",", I10, FIND(",", I10) + 1) + 1) + 1) + 1) - 1, LEN(I10)))), "") | V10: =IFERROR(TRIM(MID(I10, FIND(",", I10, FIND(",", I10, FIND(",", I10, FIND(",", I10, FIND(",", I10, FIND(",", I10, FIND(",", I10) + 1) + 1) + 1) + 1) + 1) + 1) + 1, IFERROR(FIND(",", I10, FIND(",", I10, FIND(",", I10, FIND(",", I10, FIND(",", I10, FIND(",", I10, FIND(",", I10) + 1) + 1) + 1) + 1) + 1) + 1) - FIND(",", I10, FIND(",", I10, FIND(",", I10, FIND(",", I10, FIND(",", I10, FIND(",", I10) + 1) + 1) + 1) + 1) + 1) - 1, LEN(I10)))), "") | X10: =IFERROR(TRIM(MID(I10, FIND(",", I10, FIND(",", I10, FIND(",", I10, FIND(",", I10, FIND(",", I10, FIND(",", I10, FIND(",", I10, FIND(",", I10) + 1) + 1) + 1) + 1) + 1) + 1) + 1) + 1, IFERROR(FIND(",", I10, FIND(",", I10, FIND(",", I10, FIND(",", I10, FIND(",", I10, FIND(",", I10, FIND(",", I10, FIND(",", I10) + 1) + 1) + 1) + 1) + 1) + 1) + 1) - FIND(",", I10, FIND(",", I10, FIND(",", I10, FIND(",", I10, FIND(",", I10, FIND(",", I10, FIND(",", I10) + 1) + 1) + 1) + 1) + 1) + 1) - 1, LEN(I10)))), "") | Z10: =IFERROR(TRIM(MID(I10, FIND(",", I10, FIND(",", I10, FIND(",", I10, FIND(",", I10, FIND(",", I10, FIND(",", I10, FIND(",", I10, FIND(",", I10, FIND(",", I10) + 1) + 1) + 1) + 1) + 1) + 1) + 1) + 1) + 1, IFERROR(FIND(",", I10, FIND(",", I10, FIND(",", I10, FIND(",", I10, FIND(",", I10, FIND(",", I10, FIND(",", I10, FIND(",", I10, FIND(",", I10) + 1) + 1) + 1) + 1) + 1) + 1) + 1) + 1) - FIND(",", I10, FIND(",", I10, FIND(",", I10, FIND(",", I10, FIND(",", I10, FIND(",", I10, FIND(",", I10, FIND(",", I10) + 1) + 1) + 1) + 1) + 1) + 1) + 1) - 1, LEN(I10)))), "")
A11: 3617057125401FR-W24-23-75325 | B11: 3617057125401 | C11: FR-W24-23-75325 | D11: ¡No! El Dinero a mi no me cambio ???????? #ElFantasma #ElSelectivo #Shorts #ShortsVideo #AfinArte | E11: El Fantasma | G11: AfinArte | H11: =100%-SUM(CatalogTable[[#This Row],[Artist 1 %]],CatalogTable[[#This Row],[Artist 2 %]],CatalogTable[[#This Row],[Artist 3 %]],CatalogTable[[#This Row],[Artist 4 %]],CatalogTable[[#This Row],[Artist 5 %]],CatalogTable[[#This Row],[Artist 6 %]],CatalogTable[[#This Row],[Artist 7 %]],CatalogTable[[#This Row],[Artist 8 %]],CatalogTable[[#This Row],[Artist 9%]]) -> 0.65 | I11: =IF(ISBLANK(E11),"",INDEX(UniqueArtist!B:B, MATCH(E11,UniqueArtist!A:A, 0))) -> El Fantasma | J11: =IFERROR(TRIM(LEFT(I11, IFERROR(FIND(",", I11)-1, LEN(I11)))), "") -> El Fantasma | K11: 0.35 | L11: =IFERROR(TRIM(MID(I11, FIND(",", I11) + 1, IFERROR(FIND(",", I11, FIND(",", I11) + 1) - FIND(",", I11) - 1, LEN(I11)))), "") | N11: =IFERROR(TRIM(MID(I11, FIND(",", I11, FIND(",", I11) + 1) + 1, IFERROR(FIND(",", I11, FIND(",", I11, FIND(",", I11) + 1) + 1) - FIND(",", I11, FIND(",", I11) + 1) - 1, LEN(I11)))), "") | P11: =IFERROR(TRIM(MID(I11, FIND(",", I11, FIND(",", I11, FIND(",", I11) + 1) + 1) + 1, IFERROR(FIND(",", I11, FIND(",", I11, FIND(",", I11, FIND(",", I11) + 1) + 1) + 1) - FIND(",", I11, FIND(",", I11, FIND(",", I11) + 1) + 1) - 1, LEN(I11)))), "") | R11: =IFERROR(TRIM(MID(I11, FIND(",", I11, FIND(",", I11, FIND(",", I11, FIND(",", I11) + 1) + 1) + 1) + 1, IFERROR(FIND(",", I11, FIND(",", I11, FIND(",", I11, FIND(",", I11, FIND(",", I11) + 1) + 1) + 1) + 1) - FIND(",", I11, FIND(",", I11, FIND(",", I11, FIND(",", I11) + 1) + 1) + 1) - 1, LEN(I11)))), "") | T11: =IFERROR(TRIM(MID(I11, FIND(",", I11, FIND(",", I11, FIND(",", I11, FIND(",", I11, FIND(",", I11, FIND(",", I11) + 1) + 1) + 1) + 1) + 1) + 1, IFERROR(FIND(",", I11, FIND(",", I11, FIND(",", I11, FIND(",", I11, FIND(",", I11, FIND(",", I11) + 1) + 1) + 1) + 1) + 1) - FIND(",", I11, FIND(",", I11, FIND(",", I11, FIND(",", I11, FIND(",", I11) + 1) + 1) + 1) + 1) - 1, LEN(I11)))), "") | V11: =IFERROR(TRIM(MID(I11, FIND(",", I11, FIND(",", I11, FIND(",", I11, FIND(",", I11, FIND(",", I11, FIND(",", I11, FIND(",", I11) + 1) + 1) + 1) + 1) + 1) + 1) + 1, IFERROR(FIND(",", I11, FIND(",", I11, FIND(",", I11, FIND(",", I11, FIND(",", I11, FIND(",", I11, FIND(",", I11) + 1) + 1) + 1) + 1) + 1) + 1) - FIND(",", I11, FIND(",", I11, FIND(",", I11, FIND(",", I11, FIND(",", I11, FIND(",", I11) + 1) + 1) + 1) + 1) + 1) - 1, LEN(I11)))), "") | X11: =IFERROR(TRIM(MID(I11, FIND(",", I11, FIND(",", I11, FIND(",", I11, FIND(",", I11, FIND(",", I11, FIND(",", I11, FIND(",", I11, FIND(",", I11) + 1) + 1) + 1) + 1) + 1) + 1) + 1) + 1, IFERROR(FIND(",", I11, FIND(",", I11, FIND(",", I11, FIND(",", I11, FIND(",", I11, FIND(",", I11, FIND(",", I11, FIND(",", I11) + 1) + 1) + 1) + 1) + 1) + 1) + 1) - FIND(",", I11, FIND(",", I11, FIND(",", I11, FIND(",", I11, FIND(",", I11, FIND(",", I11, FIND(",", I11) + 1) + 1) + 1) + 1) + 1) + 1) - 1, LEN(I11)))), "") | Z11: =IFERROR(TRIM(MID(I11, FIND(",", I11, FIND(",", I11, FIND(",", I11, FIND(",", I11, FIND(",", I11, FIND(",", I11, FIND(",", I11, FIND(",", I11, FIND(",", I11) + 1) + 1) + 1) + 1) + 1) + 1) + 1) + 1) + 1, IFERROR(FIND(",", I11, FIND(",", I11, FIND(",", I11, FIND(",", I11, FIND(",", I11, FIND(",", I11, FIND(",", I11, FIND(",", I11, FIND(",", I11) + 1) + 1) + 1) + 1) + 1) + 1) + 1) + 1) - FIND(",", I11, FIND(",", I11, FIND(",", I11, FIND(",", I11, FIND(",", I11, FIND(",", I11, FIND(",", I11, FIND(",", I11) + 1) + 1) + 1) + 1) + 1) + 1) + 1) - 1, LEN(I11)))), "")
A12: 3617052596404FR-S18-22-14503 | B12: 3617052596404 | C12: FR-S18-22-14503 | D12: ¡Nos encontramos a #SpiderMan y #ElChapulinColorado en NY! @AfinArte Music #LosDosCarnales #NYC | E12: Los Dos Carnales | G12: AfinArte | H12: =100%-SUM(CatalogTable[[#This Row],[Artist 1 %]],CatalogTable[[#This Row],[Artist 2 %]],CatalogTable[[#This Row],[Artist 3 %]],CatalogTable[[#This Row],[Artist 4 %]],CatalogTable[[#This Row],[Artist 5 %]],CatalogTable[[#This Row],[Artist 6 %]],CatalogTable[[#This Row],[Artist 7 %]],CatalogTable[[#This Row],[Artist 8 %]],CatalogTable[[#This Row],[Artist 9%]]) -> 0.9 | I12: =IF(ISBLANK(E12),"",INDEX(UniqueArtist!B:B, MATCH(E12,UniqueArtist!A:A, 0))) -> Los Dos Carnales | J12: =IFERROR(TRIM(LEFT(I12, IFERROR(FIND(",", I12)-1, LEN(I12)))), "") -> Los Dos Carnales | K12: 0.1 | L12: =IFERROR(TRIM(MID(I12, FIND(",", I12) + 1, IFERROR(FIND(",", I12, FIND(",", I12) + 1) - FIND(",", I12) - 1, LEN(I12)))), "") | N12: =IFERROR(TRIM(MID(I12, FIND(",", I12, FIND(",", I12) + 1) + 1, IFERROR(FIND(",", I12, FIND(",", I12, FIND(",", I12) + 1) + 1) - FIND(",", I12, FIND(",", I12) + 1) - 1, LEN(I12)))), "") | P12: =IFERROR(TRIM(MID(I12, FIND(",", I12, FIND(",", I12, FIND(",", I12) + 1) + 1) + 1, IFERROR(FIND(",", I12, FIND(",", I12, FIND(",", I12, FIND(",", I12) + 1) + 1) + 1) - FIND(",", I12, FIND(",", I12, FIND(",", I12) + 1) + 1) - 1, LEN(I12)))), "") | R12: =IFERROR(TRIM(MID(I12, FIND(",", I12, FIND(",", I12, FIND(",", I12, FIND(",", I12) + 1) + 1) + 1) + 1, IFERROR(FIND(",", I12, FIND(",", I12, FIND(",", I12, FIND(",", I12, FIND(",", I12) + 1) + 1) + 1) + 1) - FIND(",", I12, FIND(",", I12, FIND(",", I12, FIND(",", I12) + 1) + 1) + 1) - 1, LEN(I12)))), "") | T12: =IFERROR(TRIM(MID(I12, FIND(",", I12, FIND(",", I12, FIND(",", I12, FIND(",", I12, FIND(",", I12, FIND(",", I12) + 1) + 1) + 1) + 1) + 1) + 1, IFERROR(FIND(",", I12, FIND(",", I12, FIND(",", I12, FIND(",", I12, FIND(",", I12, FIND(",", I12) + 1) + 1) + 1) + 1) + 1) - FIND(",", I12, FIND(",", I12, FIND(",", I12, FIND(",", I12, FIND(",", I12) + 1) + 1) + 1) + 1) - 1, LEN(I12)))), "") | V12: =IFERROR(TRIM(MID(I12, FIND(",", I12, FIND(",", I12, FIND(",", I12, FIND(",", I12, FIND(",", I12, FIND(",", I12, FIND(",", I12) + 1) + 1) + 1) + 1) + 1) + 1) + 1, IFERROR(FIND(",", I12, FIND(",", I12, FIND(",", I12, FIND(",", I12, FIND(",", I12, FIND(",", I12, FIND(",", I12) + 1) + 1) + 1) + 1) + 1) + 1) - FIND(",", I12, FIND(",", I12, FIND(",", I12, FIND(",", I12, FIND(",", I12, FIND(",", I12) + 1) + 1) + 1) + 1) + 1) - 1, LEN(I12)))), "") | X12: =IFERROR(TRIM(MID(I12, FIND(",", I12, FIND(",", I12, FIND(",", I12, FIND(",", I12, FIND(",", I12, FIND(",", I12, FIND(",", I12, FIND(",", I12) + 1) + 1) + 1) + 1) + 1) + 1) + 1) + 1, IFERROR(FIND(",", I12, FIND(",", I12, FIND(",", I12, FIND(",", I12, FIND(",", I12, FIND(",", I12, FIND(",", I12, FIND(",", I12) + 1) + 1) + 1) + 1) + 1) + 1) + 1) - FIND(",", I12, FIND(",", I12, FIND(",", I12, FIND(",", I12, FIND(",", I12, FIND(",", I12, FIND(",", I12) + 1) + 1) + 1) + 1) + 1) + 1) - 1, LEN(I12)))), "") | Z12: =IFERROR(TRIM(MID(I12, FIND(",", I12, FIND(",", I12, FIND(",", I12, FIND(",", I12, FIND(",", I12, FIND(",", I12, FIND(",", I12, FIND(",", I12, FIND(",", I12) + 1) + 1) + 1) + 1) + 1) + 1) + 1) + 1) + 1, IFERROR(FIND(",", I12, FIND(",", I12, FIND(",", I12, FIND(",", I12, FIND(",", I12, FIND(",", I12, FIND(",", I12, FIND(",", I12, FIND(",", I12) + 1) + 1) + 1) + 1) + 1) + 1) + 1) + 1) - FIND(",", I12, FIND(",", I12, FIND(",", I12, FIND(",", I12, FIND(",", I12, FIND(",", I12, FIND(",", I12, FIND(",", I12) + 1) + 1) + 1) + 1) + 1) + 1) + 1) - 1, LEN(I12)))), "")
A13: 3617381804102DG-A0J-23-90371 | B13: 3617381804102 | C13: DG-A0J-23-90371 | D13: ¡Quedan 2 señores!😮 #VozDeMando #Phoenix #Shorts #Navidad | E13: Voz De Mando | G13: AfinArte | H13: =100%-SUM(CatalogTable[[#This Row],[Artist 1 %]],CatalogTable[[#This Row],[Artist 2 %]],CatalogTable[[#This Row],[Artist 3 %]],CatalogTable[[#This Row],[Artist 4 %]],CatalogTable[[#This Row],[Artist 5 %]],CatalogTable[[#This Row],[Artist 6 %]],CatalogTable[[#This Row],[Artist 7 %]],CatalogTable[[#This Row],[Artist 8 %]],CatalogTable[[#This Row],[Artist 9%]]) -> 0 | I13: =IF(ISBLANK(E13),"",INDEX(UniqueArtist!B:B, MATCH(E13,UniqueArtist!A:A, 0))) -> Voz de Mando | J13: =IFERROR(TRIM(LEFT(I13, IFERROR(FIND(",", I13)-1, LEN(I13)))), "") -> Voz de Mando | K13: 1 | L13: =IFERROR(TRIM(MID(I13, FIND(",", I13) + 1, IFERROR(FIND(",", I13, FIND(",", I13) + 1) - FIND(",", I13) - 1, LEN(I13)))), "") | N13: =IFERROR(TRIM(MID(I13, FIND(",", I13, FIND(",", I13) + 1) + 1, IFERROR(FIND(",", I13, FIND(",", I13, FIND(",", I13) + 1) + 1) - FIND(",", I13, FIND(",", I13) + 1) - 1, LEN(I13)))), "") | P13: =IFERROR(TRIM(MID(I13, FIND(",", I13, FIND(",", I13, FIND(",", I13) + 1) + 1) + 1, IFERROR(FIND(",", I13, FIND(",", I13, FIND(",", I13, FIND(",", I13) + 1) + 1) + 1) - FIND(",", I13, FIND(",", I13, FIND(",", I13) + 1) + 1) - 1, LEN(I13)))), "") | R13: =IFERROR(TRIM(MID(I13, FIND(",", I13, FIND(",", I13, FIND(",", I13, FIND(",", I13) + 1) + 1) + 1) + 1, IFERROR(FIND(",", I13, FIND(",", I13, FIND(",", I13, FIND(",", I13, FIND(",", I13) + 1) + 1) + 1) + 1) - FIND(",", I13, FIND(",", I13, FIND(",", I13, FIND(",", I13) + 1) + 1) + 1) - 1, LEN(I13)))), "") | T13: =IFERROR(TRIM(MID(I13, FIND(",", I13, FIND(",", I13, FIND(",", I13, FIND(",", I13, FIND(",", I13, FIND(",", I13) + 1) + 1) + 1) + 1) + 1) + 1, IFERROR(FIND(",", I13, FIND(",", I13, FIND(",", I13, FIND(",", I13, FIND(",", I13, FIND(",", I13) + 1) + 1) + 1) + 1) + 1) - FIND(",", I13, FIND(",", I13, FIND(",", I13, FIND(",", I13, FIND(",", I13) + 1) + 1) + 1) + 1) - 1, LEN(I13)))), "") | V13: =IFERROR(TRIM(MID(I13, FIND(",", I13, FIND(",", I13, FIND(",", I13, FIND(",", I13, FIND(",", I13, FIND(",", I13, FIND(",", I13) + 1) + 1) + 1) + 1) + 1) + 1) + 1, IFERROR(FIND(",", I13, FIND(",", I13, FIND(",", I13, FIND(",", I13, FIND(",", I13, FIND(",", I13, FIND(",", I13) + 1) + 1) + 1) + 1) + 1) + 1) - FIND(",", I13, FIND(",", I13, FIND(",", I13, FIND(",", I13, FIND(",", I13, FIND(",", I13) + 1) + 1) + 1) + 1) + 1) - 1, LEN(I13)))), "") | X13: =IFERROR(TRIM(MID(I13, FIND(",", I13, FIND(",", I13, FIND(",", I13, FIND(",", I13, FIND(",", I13, FIND(",", I13, FIND(",", I13, FIND(",", I13) + 1) + 1) + 1) + 1) + 1) + 1) + 1) + 1, IFERROR(FIND(",", I13, FIND(",", I13, FIND(",", I13, FIND(",", I13, FIND(",", I13, FIND(",", I13, FIND(",", I13, FIND(",", I13) + 1) + 1) + 1) + 1) + 1) + 1) + 1) - FIND(",", I13, FIND(",", I13, FIND(",", I13, FIND(",", I13, FIND(",", I13, FIND(",", I13, FIND(",", I13) + 1) + 1) + 1) + 1) + 1) + 1) - 1, LEN(I13)))), "") | Z13: =IFERROR(TRIM(MID(I13, FIND(",", I13, FIND(",", I13, FIND(",", I13, FIND(",", I13, FIND(",", I13, FIND(",", I13, FIND(",", I13, FIND(",", I13, FIND(",", I13) + 1) + 1) + 1) + 1) + 1) + 1) + 1) + 1) + 1, IFERROR(FIND(",", I13, FIND(",", I13, FIND(",", I13, FIND(",", I13, FIND(",", I13, FIND(",", I13, FIND(",", I13, FIND(",", I13, FIND(",", I13) + 1) + 1) + 1) + 1) + 1) + 1) + 1) + 1) - FIND(",", I13, FIND(",", I13, FIND(",", I13, FIND(",", I13, FIND(",", I13, FIND(",", I13, FIND(",", I13, FIND(",", I13) + 1) + 1) + 1) + 1) + 1) + 1) + 1) - 1, LEN(I13)))), "")
A14: 3617058135164FR-W77-23-07901 | B14: 3617058135164 | C14: FR-W77-23-07901 | D14: ¡TE REGALAMOS UN TRAJE! ~~~~~~#Shorts #shortsvideo #ElFantasma | E14: El Fantasma | G14: AfinArte | H14: =100%-SUM(CatalogTable[[#This Row],[Artist 1 %]],CatalogTable[[#This Row],[Artist 2 %]],CatalogTable[[#This Row],[Artist 3 %]],CatalogTable[[#This Row],[Artist 4 %]],CatalogTable[[#This Row],[Artist 5 %]],CatalogTable[[#This Row],[Artist 6 %]],CatalogTable[[#This Row],[Artist 7 %]],CatalogTable[[#This Row],[Artist 8 %]],CatalogTable[[#This Row],[Artist 9%]]) -> 0.65 | I14: =IF(ISBLANK(E14),"",INDEX(UniqueArtist!B:B, MATCH(E14,UniqueArtist!A:A, 0))) -> El Fantasma | J14: =IFERROR(TRIM(LEFT(I14, IFERROR(FIND(",", I14)-1, LEN(I14)))), "") -> El Fantasma | K14: 0.35 | L14: =IFERROR(TRIM(MID(I14, FIND(",", I14) + 1, IFERROR(FIND(",", I14, FIND(",", I14) + 1) - FIND(",", I14) - 1, LEN(I14)))), "") | N14: =IFERROR(TRIM(MID(I14, FIND(",", I14, FIND(",", I14) + 1) + 1, IFERROR(FIND(",", I14, FIND(",", I14, FIND(",", I14) + 1) + 1) - FIND(",", I14, FIND(",", I14) + 1) - 1, LEN(I14)))), "") | P14: =IFERROR(TRIM(MID(I14, FIND(",", I14, FIND(",", I14, FIND(",", I14) + 1) + 1) + 1, IFERROR(FIND(",", I14, FIND(",", I14, FIND(",", I14, FIND(",", I14) + 1) + 1) + 1) - FIND(",", I14, FIND(",", I14, FIND(",", I14) + 1) + 1) - 1, LEN(I14)))), "") | R14: =IFERROR(TRIM(MID(I14, FIND(",", I14, FIND(",", I14, FIND(",", I14, FIND(",", I14) + 1) + 1) + 1) + 1, IFERROR(FIND(",", I14, FIND(",", I14, FIND(",", I14, FIND(",", I14, FIND(",", I14) + 1) + 1) + 1) + 1) - FIND(",", I14, FIND(",", I14, FIND(",", I14, FIND(",", I14) + 1) + 1) + 1) - 1, LEN(I14)))), "") | T14: =IFERROR(TRIM(MID(I14, FIND(",", I14, FIND(",", I14, FIND(",", I14, FIND(",", I14, FIND(",", I14, FIND(",", I14) + 1) + 1) + 1) + 1) + 1) + 1, IFERROR(FIND(",", I14, FIND(",", I14, FIND(",", I14, FIND(",", I14, FIND(",", I14, FIND(",", I14) + 1) + 1) + 1) + 1) + 1) - FIND(",", I14, FIND(",", I14, FIND(",", I14, FIND(",", I14, FIND(",", I14) + 1) + 1) + 1) + 1) - 1, LEN(I14)))), "") | V14: =IFERROR(TRIM(MID(I14, FIND(",", I14, FIND(",", I14, FIND(",", I14, FIND(",", I14, FIND(",", I14, FIND(",", I14, FIND(",", I14) + 1) + 1) + 1) + 1) + 1) + 1) + 1, IFERROR(FIND(",", I14, FIND(",", I14, FIND(",", I14, FIND(",", I14, FIND(",", I14, FIND(",", I14, FIND(",", I14) + 1) + 1) + 1) + 1) + 1) + 1) - FIND(",", I14, FIND(",", I14, FIND(",", I14, FIND(",", I14, FIND(",", I14, FIND(",", I14) + 1) + 1) + 1) + 1) + 1) - 1, LEN(I14)))), "") | X14: =IFERROR(TRIM(MID(I14, FIND(",", I14, FIND(",", I14, FIND(",", I14, FIND(",", I14, FIND(",", I14, FIND(",", I14, FIND(",", I14, FIND(",", I14) + 1) + 1) + 1) + 1) + 1) + 1) + 1) + 1, IFERROR(FIND(",", I14, FIND(",", I14, FIND(",", I14, FIND(",", I14, FIND(",", I14, FIND(",", I14, FIND(",", I14, FIND(",", I14) + 1) + 1) + 1) + 1) + 1) + 1) + 1) - FIND(",", I14, FIND(",", I14, FIND(",", I14, FIND(",", I14, FIND(",", I14, FIND(",", I14, FIND(",", I14) + 1) + 1) + 1) + 1) + 1) + 1) - 1, LEN(I14)))), "") | Z14: =IFERROR(TRIM(MID(I14, FIND(",", I14, FIND(",", I14, FIND(",", I14, FIND(",", I14, FIND(",", I14, FIND(",", I14, FIND(",", I14, FIND(",", I14, FIND(",", I14) + 1) + 1) + 1) + 1) + 1) + 1) + 1) + 1) + 1, IFERROR(FIND(",", I14, FIND(",", I14, FIND(",", I14, FIND(",", I14, FIND(",", I14, FIND(",", I14, FIND(",", I14, FIND(",", I14, FIND(",", I14) + 1) + 1) + 1) + 1) + 1) + 1) + 1) + 1) - FIND(",", I14, FIND(",", I14, FIND(",", I14, FIND(",", I14, FIND(",", I14, FIND(",", I14, FIND(",", I14, FIND(",", I14) + 1) + 1) + 1) + 1) + 1) + 1) + 1) - 1, LEN(I14)))), "")
... A87: 3616841324990DG-A0C-21-88467 | B87: 3616841324990 | C87: DG-A0C-21-88467 | D87: ¿y los 15mil dólares? a lucir el tobillo raza | E87: El Fantasma | G87: AfinArte | H87: =100%-SUM(CatalogTable[[#This Row],[Artist 1 %]],CatalogTable[[#This Row],[Artist 2 %]],CatalogTable[[#This Row],[Artist 3 %]],CatalogTable[[#This Row],[Artist 4 %]],CatalogTable[[#This Row],[Artist 5 %]],CatalogTable[[#This Row],[Artist 6 %]],CatalogTable[[#This Row],[Artist 7 %]],CatalogTable[[#This Row],[Artist 8 %]],CatalogTable[[#This Row],[Artist 9%]]) -> 0.65 | I87: =IF(ISBLANK(E87),"",INDEX(UniqueArtist!B:B, MATCH(E87,UniqueArtist!A:A, 0))) -> El Fantasma | J87: =IFERROR(TRIM(LEFT(I87, IFERROR(FIND(",", I87)-1, LEN(I87)))), "") -> El Fantasma | K87: 0.35 | L87: =IFERROR(TRIM(MID(I87, FIND(",", I87) + 1, IFERROR(FIND(",", I87, FIND(",", I87) + 1) - FIND(",", I87) - 1, LEN(I87)))), "") | N87: =IFERROR(TRIM(MID(I87, FIND(",", I87, FIND(",", I87) + 1) + 1, IFERROR(FIND(",", I87, FIND(",", I87, FIND(",", I87) + 1) + 1) - FIND(",", I87, FIND(",", I87) + 1) - 1, LEN(I87)))), "") | P87: =IFERROR(TRIM(MID(I87, FIND(",", I87, FIND(",", I87, FIND(",", I87) + 1) + 1) + 1, IFERROR(FIND(",", I87, FIND(",", I87, FIND(",", I87, FIND(",", I87) + 1) + 1) + 1) - FIND(",", I87, FIND(",", I87, FIND(",", I87) + 1) + 1) - 1, LEN(I87)))), "") | R87: =IFERROR(TRIM(MID(I87, FIND(",", I87, FIND(",", I87, FIND(",", I87, FIND(",", I87) + 1) + 1) + 1) + 1, IFERROR(FIND(",", I87, FIND(",", I87, FIND(",", I87, FIND(",", I87, FIND(",", I87) + 1) + 1) + 1) + 1) - FIND(",", I87, FIND(",", I87, FIND(",", I87, FIND(",", I87) + 1) + 1) + 1) - 1, LEN(I87)))), "") | T87: =IFERROR(TRIM(MID(I87, FIND(",", I87, FIND(",", I87, FIND(",", I87, FIND(",", I87, FIND(",", I87, FIND(",", I87) + 1) + 1) + 1) + 1) + 1) + 1, IFERROR(FIND(",", I87, FIND(",", I87, FIND(",", I87, FIND(",", I87, FIND(",", I87, FIND(",", I87) + 1) + 1) + 1) + 1) + 1) - FIND(",", I87, FIND(",", I87, FIND(",", I87, FIND(",", I87, FIND(",", I87) + 1) + 1) + 1) + 1) - 1, LEN(I87)))), "") | V87: =IFERROR(TRIM(MID(I87, FIND(",", I87, FIND(",", I87, FIND(",", I87, FIND(",", I87, FIND(",", I87, FIND(",", I87, FIND(",", I87) + 1) + 1) + 1) + 1) + 1) + 1) + 1, IFERROR(FIND(",", I87, FIND(",", I87, FIND(",", I87, FIND(",", I87, FIND(",", I87, FIND(",", I87, FIND(",", I87) + 1) + 1) + 1) + 1) + 1) + 1) - FIND(",", I87, FIND(",", I87, FIND(",", I87, FIND(",", I87, FIND(",", I87, FIND(",", I87) + 1) + 1) + 1) + 1) + 1) - 1, LEN(I87)))), "") | X87: =IFERROR(TRIM(MID(I87, FIND(",", I87, FIND(",", I87, FIND(",", I87, FIND(",", I87, FIND(",", I87, FIND(",", I87, FIND(",", I87, FIND(",", I87) + 1) + 1) + 1) + 1) + 1) + 1) + 1) + 1, IFERROR(FIND(",", I87, FIND(",", I87, FIND(",", I87, FIND(",", I87, FIND(",", I87, FIND(",", I87, FIND(",", I87, FIND(",", I87) + 1) + 1) + 1) + 1) + 1) + 1) + 1) - FIND(",", I87, FIND(",", I87, FIND(",", I87, FIND(",", I87, FIND(",", I87, FIND(",", I87, FIND(",", I87) + 1) + 1) + 1) + 1) + 1) + 1) - 1, LEN(I87)))), "") | Z87: =IFERROR(TRIM(MID(I87, FIND(",", I87, FIND(",", I87, FIND(",", I87, FIND(",", I87, FIND(",", I87, FIND(",", I87, FIND(",", I87, FIND(",", I87, FIND(",", I87) + 1) + 1) + 1) + 1) + 1) + 1) + 1) + 1) + 1, IFERROR(FIND(",", I87, FIND(",", I87, FIND(",", I87, FIND(",", I87, FIND(",", I87, FIND(",", I87, FIND(",", I87, FIND(",", I87, FIND(",", I87) + 1) + 1) + 1) + 1) + 1) + 1) + 1) + 1) - FIND(",", I87, FIND(",", I87, FIND(",", I87, FIND(",", I87, FIND(",", I87, FIND(",", I87, FIND(",", I87, FIND(",", I87) + 1) + 1) + 1) + 1) + 1) + 1) + 1) - 1, LEN(I87)))), "")
A88: 3617380035866DG-A0J-23-29504 | B88: 3617380035866 | C88: DG-A0J-23-29504 | D88: ¿Ya escogiste tu Drink Team? Ya está disponible #LaBohemia #AfinArteMusic ? #Shorts | E88: El Fantasma, Voz De Mando | G88: AfinArte | H88: =100%-SUM(CatalogTable[[#This Row],[Artist 1 %]],CatalogTable[[#This Row],[Artist 2 %]],CatalogTable[[#This Row],[Artist 3 %]],CatalogTable[[#This Row],[Artist 4 %]],CatalogTable[[#This Row],[Artist 5 %]],CatalogTable[[#This Row],[Artist 6 %]],CatalogTable[[#This Row],[Artist 7 %]],CatalogTable[[#This Row],[Artist 8 %]],CatalogTable[[#This Row],[Artist 9%]]) -> 0.325 | I88: =IF(ISBLANK(E88),"",INDEX(UniqueArtist!B:B, MATCH(E88,UniqueArtist!A:A, 0))) -> El Fantasma, Voz de Mando | J88: =IFERROR(TRIM(LEFT(I88, IFERROR(FIND(",", I88)-1, LEN(I88)))), "") -> El Fantasma | K88: 0.175 | L88: =IFERROR(TRIM(MID(I88, FIND(",", I88) + 1, IFERROR(FIND(",", I88, FIND(",", I88) + 1) - FIND(",", I88) - 1, LEN(I88)))), "") -> Voz de Mando | M88: 0.5 | N88: =IFERROR(TRIM(MID(I88, FIND(",", I88, FIND(",", I88) + 1) + 1, IFERROR(FIND(",", I88, FIND(",", I88, FIND(",", I88) + 1) + 1) - FIND(",", I88, FIND(",", I88) + 1) - 1, LEN(I88)))), "") | P88: =IFERROR(TRIM(MID(I88, FIND(",", I88, FIND(",", I88, FIND(",", I88) + 1) + 1) + 1, IFERROR(FIND(",", I88, FIND(",", I88, FIND(",", I88, FIND(",", I88) + 1) + 1) + 1) - FIND(",", I88, FIND(",", I88, FIND(",", I88) + 1) + 1) - 1, LEN(I88)))), "") | R88: =IFERROR(TRIM(MID(I88, FIND(",", I88, FIND(",", I88, FIND(",", I88, FIND(",", I88) + 1) + 1) + 1) + 1, IFERROR(FIND(",", I88, FIND(",", I88, FIND(",", I88, FIND(",", I88, FIND(",", I88) + 1) + 1) + 1) + 1) - FIND(",", I88, FIND(",", I88, FIND(",", I88, FIND(",", I88) + 1) + 1) + 1) - 1, LEN(I88)))), "") | T88: =IFERROR(TRIM(MID(I88, FIND(",", I88, FIND(",", I88, FIND(",", I88, FIND(",", I88, FIND(",", I88, FIND(",", I88) + 1) + 1) + 1) + 1) + 1) + 1, IFERROR(FIND(",", I88, FIND(",", I88, FIND(",", I88, FIND(",", I88, FIND(",", I88, FIND(",", I88) + 1) + 1) + 1) + 1) + 1) - FIND(",", I88, FIND(",", I88, FIND(",", I88, FIND(",", I88, FIND(",", I88) + 1) + 1) + 1) + 1) - 1, LEN(I88)))), "") | V88: =IFERROR(TRIM(MID(I88, FIND(",", I88, FIND(",", I88, FIND(",", I88, FIND(",", I88, FIND(",", I88, FIND(",", I88, FIND(",", I88) + 1) + 1) + 1) + 1) + 1) + 1) + 1, IFERROR(FIND(",", I88, FIND(",", I88, FIND(",", I88, FIND(",", I88, FIND(",", I88, FIND(",", I88, FIND(",", I88) + 1) + 1) + 1) + 1) + 1) + 1) - FIND(",", I88, FIND(",", I88, FIND(",", I88, FIND(",", I88, FIND(",", I88, FIND(",", I88) + 1) + 1) + 1) + 1) + 1) - 1, LEN(I88)))), "") | X88: =IFERROR(TRIM(MID(I88, FIND(",", I88, FIND(",", I88, FIND(",", I88, FIND(",", I88, FIND(",", I88, FIND(",", I88, FIND(",", I88, FIND(",", I88) + 1) + 1) + 1) + 1) + 1) + 1) + 1) + 1, IFERROR(FIND(",", I88, FIND(",", I88, FIND(",", I88, FIND(",", I88, FIND(",", I88, FIND(",", I88, FIND(",", I88, FIND(",", I88) + 1) + 1) + 1) + 1) + 1) + 1) + 1) - FIND(",", I88, FIND(",", I88, FIND(",", I88, FIND(",", I88, FIND(",", I88, FIND(",", I88, FIND(",", I88) + 1) + 1) + 1) + 1) + 1) + 1) - 1, LEN(I88)))), "") | Z88: =IFERROR(TRIM(MID(I88, FIND(",", I88, FIND(",", I88, FIND(",", I88, FIND(",", I88, FIND(",", I88, FIND(",", I88, FIND(",", I88, FIND(",", I88, FIND(",", I88) + 1) + 1) + 1) + 1) + 1) + 1) + 1) + 1) + 1, IFERROR(FIND(",", I88, FIND(",", I88, FIND(",", I88, FIND(",", I88, FIND(",", I88, FIND(",", I88, FIND(",", I88, FIND(",", I88, FIND(",", I88) + 1) + 1) + 1) + 1) + 1) + 1) + 1) + 1) - FIND(",", I88, FIND(",", I88, FIND(",", I88, FIND(",", I88, FIND(",", I88, FIND(",", I88, FIND(",", I88, FIND(",", I88) + 1) + 1) + 1) + 1) + 1) + 1) + 1) - 1, LEN(I88)))), "")
A89: 3617053158724FR-S18-22-34525 | B89: 3617053158724 | C89: FR-S18-22-34525 | D89: ¿Ya están listos chavalones? #LaEnseñanzaDeLosViejos duetazo junto a @Pepe Aguilar #AfinArteMusic | E89: El Fantasma | G89: AfinArte | H89: =100%-SUM(CatalogTable[[#This Row],[Artist 1 %]],CatalogTable[[#This Row],[Artist 2 %]],CatalogTable[[#This Row],[Artist 3 %]],CatalogTable[[#This Row],[Artist 4 %]],CatalogTable[[#This Row],[Artist 5 %]],CatalogTable[[#This Row],[Artist 6 %]],CatalogTable[[#This Row],[Artist 7 %]],CatalogTable[[#This Row],[Artist 8 %]],CatalogTable[[#This Row],[Artist 9%]]) -> 0.65 | I89: =IF(ISBLANK(E89),"",INDEX(UniqueArtist!B:B, MATCH(E89,UniqueArtist!A:A, 0))) -> El Fantasma | J89: =IFERROR(TRIM(LEFT(I89, IFERROR(FIND(",", I89)-1, LEN(I89)))), "") -> El Fantasma | K89: 0.35 | L89: =IFERROR(TRIM(MID(I89, FIND(",", I89) + 1, IFERROR(FIND(",", I89, FIND(",", I89) + 1) - FIND(",", I89) - 1, LEN(I89)))), "") | N89: =IFERROR(TRIM(MID(I89, FIND(",", I89, FIND(",", I89) + 1) + 1, IFERROR(FIND(",", I89, FIND(",", I89, FIND(",", I89) + 1) + 1) - FIND(",", I89, FIND(",", I89) + 1) - 1, LEN(I89)))), "") | P89: =IFERROR(TRIM(MID(I89, FIND(",", I89, FIND(",", I89, FIND(",", I89) + 1) + 1) + 1, IFERROR(FIND(",", I89, FIND(",", I89, FIND(",", I89, FIND(",", I89) + 1) + 1) + 1) - FIND(",", I89, FIND(",", I89, FIND(",", I89) + 1) + 1) - 1, LEN(I89)))), "") | R89: =IFERROR(TRIM(MID(I89, FIND(",", I89, FIND(",", I89, FIND(",", I89, FIND(",", I89) + 1) + 1) + 1) + 1, IFERROR(FIND(",", I89, FIND(",", I89, FIND(",", I89, FIND(",", I89, FIND(",", I89) + 1) + 1) + 1) + 1) - FIND(",", I89, FIND(",", I89, FIND(",", I89, FIND(",", I89) + 1) + 1) + 1) - 1, LEN(I89)))), "") | T89: =IFERROR(TRIM(MID(I89, FIND(",", I89, FIND(",", I89, FIND(",", I89, FIND(",", I89, FIND(",", I89, FIND(",", I89) + 1) + 1) + 1) + 1) + 1) + 1, IFERROR(FIND(",", I89, FIND(",", I89, FIND(",", I89, FIND(",", I89, FIND(",", I89, FIND(",", I89) + 1) + 1) + 1) + 1) + 1) - FIND(",", I89, FIND(",", I89, FIND(",", I89, FIND(",", I89, FIND(",", I89) + 1) + 1) + 1) + 1) - 1, LEN(I89)))), "") | V89: =IFERROR(TRIM(MID(I89, FIND(",", I89, FIND(",", I89, FIND(",", I89, FIND(",", I89, FIND(",", I89, FIND(",", I89, FIND(",", I89) + 1) + 1) + 1) + 1) + 1) + 1) + 1, IFERROR(FIND(",", I89, FIND(",", I89, FIND(",", I89, FIND(",", I89, FIND(",", I89, FIND(",", I89, FIND(",", I89) + 1) + 1) + 1) + 1) + 1) + 1) - FIND(",", I89, FIND(",", I89, FIND(",", I89, FIND(",", I89, FIND(",", I89, FIND(",", I89) + 1) + 1) + 1) + 1) + 1) - 1, LEN(I89)))), "") | X89: =IFERROR(TRIM(MID(I89, FIND(",", I89, FIND(",", I89, FIND(",", I89, FIND(",", I89, FIND(",", I89, FIND(",", I89, FIND(",", I89, FIND(",", I89) + 1) + 1) + 1) + 1) + 1) + 1) + 1) + 1, IFERROR(FIND(",", I89, FIND(",", I89, FIND(",", I89, FIND(",", I89, FIND(",", I89, FIND(",", I89, FIND(",", I89, FIND(",", I89) + 1) + 1) + 1) + 1) + 1) + 1) + 1) - FIND(",", I89, FIND(",", I89, FIND(",", I89, FIND(",", I89, FIND(",", I89, FIND(",", I89, FIND(",", I89) + 1) + 1) + 1) + 1) + 1) + 1) - 1, LEN(I89)))), "") | Z89: =IFERROR(TRIM(MID(I89, FIND(",", I89, FIND(",", I89, FIND(",", I89, FIND(",", I89, FIND(",", I89, FIND(",", I89, FIND(",", I89, FIND(",", I89, FIND(",", I89) + 1) + 1) + 1) + 1) + 1) + 1) + 1) + 1) + 1, IFERROR(FIND(",", I89, FIND(",", I89, FIND(",", I89, FIND(",", I89, FIND(",", I89, FIND(",", I89, FIND(",", I89, FIND(",", I89, FIND(",", I89) + 1) + 1) + 1) + 1) + 1) + 1) + 1) + 1) - FIND(",", I89, FIND(",", I89, FIND(",", I89, FIND(",", I89, FIND(",", I89, FIND(",", I89, FIND(",", I89, FIND(",", I89) + 1) + 1) + 1) + 1) + 1) + 1) + 1) - 1, LEN(I89)))), "")
A90: 3617380620314DG-A0J-23-49839 | B90: 3617380620314 | C90: DG-A0J-23-49839 | D90: ¿Ya están listos chavalones? 🔥 24 de Noviembre mbre #QuienTeDioPermiso #Shorts | E90: El Fantasma | G90: AfinArte | H90: =100%-SUM(CatalogTable[[#This Row],[Artist 1 %]],CatalogTable[[#This Row],[Artist 2 %]],CatalogTable[[#This Row],[Artist 3 %]],CatalogTable[[#This Row],[Artist 4 %]],CatalogTable[[#This Row],[Artist 5 %]],CatalogTable[[#This Row],[Artist 6 %]],CatalogTable[[#This Row],[Artist 7 %]],CatalogTable[[#This Row],[Artist 8 %]],CatalogTable[[#This Row],[Artist 9%]]) -> 0.65 | I90: =IF(ISBLANK(E90),"",INDEX(UniqueArtist!B:B, MATCH(E90,UniqueArtist!A:A, 0))) -> El Fantasma | J90: =IFERROR(TRIM(LEFT(I90, IFERROR(FIND(",", I90)-1, LEN(I90)))), "") -> El Fantasma | K90: 0.35 | L90: =IFERROR(TRIM(MID(I90, FIND(",", I90) + 1, IFERROR(FIND(",", I90, FIND(",", I90) + 1) - FIND(",", I90) - 1, LEN(I90)))), "") | N90: =IFERROR(TRIM(MID(I90, FIND(",", I90, FIND(",", I90) + 1) + 1, IFERROR(FIND(",", I90, FIND(",", I90, FIND(",", I90) + 1) + 1) - FIND(",", I90, FIND(",", I90) + 1) - 1, LEN(I90)))), "") | P90: =IFERROR(TRIM(MID(I90, FIND(",", I90, FIND(",", I90, FIND(",", I90) + 1) + 1) + 1, IFERROR(FIND(",", I90, FIND(",", I90, FIND(",", I90, FIND(",", I90) + 1) + 1) + 1) - FIND(",", I90, FIND(",", I90, FIND(",", I90) + 1) + 1) - 1, LEN(I90)))), "") | R90: =IFERROR(TRIM(MID(I90, FIND(",", I90, FIND(",", I90, FIND(",", I90, FIND(",", I90) + 1) + 1) + 1) + 1, IFERROR(FIND(",", I90, FIND(",", I90, FIND(",", I90, FIND(",", I90, FIND(",", I90) + 1) + 1) + 1) + 1) - FIND(",", I90, FIND(",", I90, FIND(",", I90, FIND(",", I90) + 1) + 1) + 1) - 1, LEN(I90)))), "") | T90: =IFERROR(TRIM(MID(I90, FIND(",", I90, FIND(",", I90, FIND(",", I90, FIND(",", I90, FIND(",", I90, FIND(",", I90) + 1) + 1) + 1) + 1) + 1) + 1, IFERROR(FIND(",", I90, FIND(",", I90, FIND(",", I90, FIND(",", I90, FIND(",", I90, FIND(",", I90) + 1) + 1) + 1) + 1) + 1) - FIND(",", I90, FIND(",", I90, FIND(",", I90, FIND(",", I90, FIND(",", I90) + 1) + 1) + 1) + 1) - 1, LEN(I90)))), "") | V90: =IFERROR(TRIM(MID(I90, FIND(",", I90, FIND(",", I90, FIND(",", I90, FIND(",", I90, FIND(",", I90, FIND(",", I90, FIND(",", I90) + 1) + 1) + 1) + 1) + 1) + 1) + 1, IFERROR(FIND(",", I90, FIND(",", I90, FIND(",", I90, FIND(",", I90, FIND(",", I90, FIND(",", I90, FIND(",", I90) + 1) + 1) + 1) + 1) + 1) + 1) - FIND(",", I90, FIND(",", I90, FIND(",", I90, FIND(",", I90, FIND(",", I90, FIND(",", I90) + 1) + 1) + 1) + 1) + 1) - 1, LEN(I90)))), "") | X90: =IFERROR(TRIM(MID(I90, FIND(",", I90, FIND(",", I90, FIND(",", I90, FIND(",", I90, FIND(",", I90, FIND(",", I90, FIND(",", I90, FIND(",", I90) + 1) + 1) + 1) + 1) + 1) + 1) + 1) + 1, IFERROR(FIND(",", I90, FIND(",", I90, FIND(",", I90, FIND(",", I90, FIND(",", I90, FIND(",", I90, FIND(",", I90, FIND(",", I90) + 1) + 1) + 1) + 1) + 1) + 1) + 1) - FIND(",", I90, FIND(",", I90, FIND(",", I90, FIND(",", I90, FIND(",", I90, FIND(",", I90, FIND(",", I90) + 1) + 1) + 1) + 1) + 1) + 1) - 1, LEN(I90)))), "") | Z90: =IFERROR(TRIM(MID(I90, FIND(",", I90, FIND(",", I90, FIND(",", I90, FIND(",", I90, FIND(",", I90, FIND(",", I90, FIND(",", I90, FIND(",", I90, FIND(",", I90) + 1) + 1) + 1) + 1) + 1) + 1) + 1) + 1) + 1, IFERROR(FIND(",", I90, FIND(",", I90, FIND(",", I90, FIND(",", I90, FIND(",", I90, FIND(",", I90, FIND(",", I90, FIND(",", I90, FIND(",", I90) + 1) + 1) + 1) + 1) + 1) + 1) + 1) + 1) - FIND(",", I90, FIND(",", I90, FIND(",", I90, FIND(",", I90, FIND(",", I90, FIND(",", I90, FIND(",", I90, FIND(",", I90) + 1) + 1) + 1) + 1) + 1) + 1) + 1) - 1, LEN(I90)))), "")
A91: 3617380035644DG-A0J-23-29486 | B91: 3617380035644 | C91: DG-A0J-23-29486 | D91: ¿Ya están listos para #LaBohemiaAfinArte ? 🔥 ¡estamos en estreno! #Shorts #YTShorts | E91: AfinArte Music | G91: AfinArte | H91: =100%-SUM(CatalogTable[[#This Row],[Artist 1 %]],CatalogTable[[#This Row],[Artist 2 %]],CatalogTable[[#This Row],[Artist 3 %]],CatalogTable[[#This Row],[Artist 4 %]],CatalogTable[[#This Row],[Artist 5 %]],CatalogTable[[#This Row],[Artist 6 %]],CatalogTable[[#This Row],[Artist 7 %]],CatalogTable[[#This Row],[Artist 8 %]],CatalogTable[[#This Row],[Artist 9%]]) -> 0 | I91: =IF(ISBLANK(E91),"",INDEX(UniqueArtist!B:B, MATCH(E91,UniqueArtist!A:A, 0))) -> AfinArte Music | J91: =IFERROR(TRIM(LEFT(I91, IFERROR(FIND(",", I91)-1, LEN(I91)))), "") -> AfinArte Music | K91: 1 | L91: =IFERROR(TRIM(MID(I91, FIND(",", I91) + 1, IFERROR(FIND(",", I91, FIND(",", I91) + 1) - FIND(",", I91) - 1, LEN(I91)))), "") | N91: =IFERROR(TRIM(MID(I91, FIND(",", I91, FIND(",", I91) + 1) + 1, IFERROR(FIND(",", I91, FIND(",", I91, FIND(",", I91) + 1) + 1) - FIND(",", I91, FIND(",", I91) + 1) - 1, LEN(I91)))), "") | P91: =IFERROR(TRIM(MID(I91, FIND(",", I91, FIND(",", I91, FIND(",", I91) + 1) + 1) + 1, IFERROR(FIND(",", I91, FIND(",", I91, FIND(",", I91, FIND(",", I91) + 1) + 1) + 1) - FIND(",", I91, FIND(",", I91, FIND(",", I91) + 1) + 1) - 1, LEN(I91)))), "") | R91: =IFERROR(TRIM(MID(I91, FIND(",", I91, FIND(",", I91, FIND(",", I91, FIND(",", I91) + 1) + 1) + 1) + 1, IFERROR(FIND(",", I91, FIND(",", I91, FIND(",", I91, FIND(",", I91, FIND(",", I91) + 1) + 1) + 1) + 1) - FIND(",", I91, FIND(",", I91, FIND(",", I91, FIND(",", I91) + 1) + 1) + 1) - 1, LEN(I91)))), "") | T91: =IFERROR(TRIM(MID(I91, FIND(",", I91, FIND(",", I91, FIND(",", I91, FIND(",", I91, FIND(",", I91, FIND(",", I91) + 1) + 1) + 1) + 1) + 1) + 1, IFERROR(FIND(",", I91, FIND(",", I91, FIND(",", I91, FIND(",", I91, FIND(",", I91, FIND(",", I91) + 1) + 1) + 1) + 1) + 1) - FIND(",", I91, FIND(",", I91, FIND(",", I91, FIND(",", I91, FIND(",", I91) + 1) + 1) + 1) + 1) - 1, LEN(I91)))), "") | V91: =IFERROR(TRIM(MID(I91, FIND(",", I91, FIND(",", I91, FIND(",", I91, FIND(",", I91, FIND(",", I91, FIND(",", I91, FIND(",", I91) + 1) + 1) + 1) + 1) + 1) + 1) + 1, IFERROR(FIND(",", I91, FIND(",", I91, FIND(",", I91, FIND(",", I91, FIND(",", I91, FIND(",", I91, FIND(",", I91) + 1) + 1) + 1) + 1) + 1) + 1) - FIND(",", I91, FIND(",", I91, FIND(",", I91, FIND(",", I91, FIND(",", I91, FIND(",", I91) + 1) + 1) + 1) + 1) + 1) - 1, LEN(I91)))), "") | X91: =IFERROR(TRIM(MID(I91, FIND(",", I91, FIND(",", I91, FIND(",", I91, FIND(",", I91, FIND(",", I91, FIND(",", I91, FIND(",", I91, FIND(",", I91) + 1) + 1) + 1) + 1) + 1) + 1) + 1) + 1, IFERROR(FIND(",", I91, FIND(",", I91, FIND(",", I91, FIND(",", I91, FIND(",", I91, FIND(",", I91, FIND(",", I91, FIND(",", I91) + 1) + 1) + 1) + 1) + 1) + 1) + 1) - FIND(",", I91, FIND(",", I91, FIND(",", I91, FIND(",", I91, FIND(",", I91, FIND(",", I91, FIND(",", I91) + 1) + 1) + 1) + 1) + 1) + 1) - 1, LEN(I91)))), "") | Z91: =IFERROR(TRIM(MID(I91, FIND(",", I91, FIND(",", I91, FIND(",", I91, FIND(",", I91, FIND(",", I91, FIND(",", I91, FIND(",", I91, FIND(",", I91, FIND(",", I91) + 1) + 1) + 1) + 1) + 1) + 1) + 1) + 1) + 1, IFERROR(FIND(",", I91, FIND(",", I91, FIND(",", I91, FIND(",", I91, FIND(",", I91, FIND(",", I91, FIND(",", I91, FIND(",", I91, FIND(",", I91) + 1) + 1) + 1) + 1) + 1) + 1) + 1) + 1) - FIND(",", I91, FIND(",", I91, FIND(",", I91, FIND(",", I91, FIND(",", I91, FIND(",", I91, FIND(",", I91, FIND(",", I91) + 1) + 1) + 1) + 1) + 1) + 1) + 1) - 1, LEN(I91)))), "")
A92: 3617229794657DG-A0J-23-24194 | B92: 3617229794657 | C92: DG-A0J-23-24194 | D92: ¿Ya están listos para lo mejor del año?🔥🍻 #BohemiaAfinArte #Shorts #YTShorts | E92: AfinArte Music | G92: AfinArte | H92: =100%-SUM(CatalogTable[[#This Row],[Artist 1 %]],CatalogTable[[#This Row],[Artist 2 %]],CatalogTable[[#This Row],[Artist 3 %]],CatalogTable[[#This Row],[Artist 4 %]],CatalogTable[[#This Row],[Artist 5 %]],CatalogTable[[#This Row],[Artist 6 %]],CatalogTable[[#This Row],[Artist 7 %]],CatalogTable[[#This Row],[Artist 8 %]],CatalogTable[[#This Row],[Artist 9%]]) -> 0 | I92: =IF(ISBLANK(E92),"",INDEX(UniqueArtist!B:B, MATCH(E92,UniqueArtist!A:A, 0))) -> AfinArte Music | J92: =IFERROR(TRIM(LEFT(I92, IFERROR(FIND(",", I92)-1, LEN(I92)))), "") -> AfinArte Music | K92: 1 | L92: =IFERROR(TRIM(MID(I92, FIND(",", I92) + 1, IFERROR(FIND(",", I92, FIND(",", I92) + 1) - FIND(",", I92) - 1, LEN(I92)))), "") | N92: =IFERROR(TRIM(MID(I92, FIND(",", I92, FIND(",", I92) + 1) + 1, IFERROR(FIND(",", I92, FIND(",", I92, FIND(",", I92) + 1) + 1) - FIND(",", I92, FIND(",", I92) + 1) - 1, LEN(I92)))), "") | P92: =IFERROR(TRIM(MID(I92, FIND(",", I92, FIND(",", I92, FIND(",", I92) + 1) + 1) + 1, IFERROR(FIND(",", I92, FIND(",", I92, FIND(",", I92, FIND(",", I92) + 1) + 1) + 1) - FIND(",", I92, FIND(",", I92, FIND(",", I92) + 1) + 1) - 1, LEN(I92)))), "") | R92: =IFERROR(TRIM(MID(I92, FIND(",", I92, FIND(",", I92, FIND(",", I92, FIND(",", I92) + 1) + 1) + 1) + 1, IFERROR(FIND(",", I92, FIND(",", I92, FIND(",", I92, FIND(",", I92, FIND(",", I92) + 1) + 1) + 1) + 1) - FIND(",", I92, FIND(",", I92, FIND(",", I92, FIND(",", I92) + 1) + 1) + 1) - 1, LEN(I92)))), "") | T92: =IFERROR(TRIM(MID(I92, FIND(",", I92, FIND(",", I92, FIND(",", I92, FIND(",", I92, FIND(",", I92, FIND(",", I92) + 1) + 1) + 1) + 1) + 1) + 1, IFERROR(FIND(",", I92, FIND(",", I92, FIND(",", I92, FIND(",", I92, FIND(",", I92, FIND(",", I92) + 1) + 1) + 1) + 1) + 1) - FIND(",", I92, FIND(",", I92, FIND(",", I92, FIND(",", I92, FIND(",", I92) + 1) + 1) + 1) + 1) - 1, LEN(I92)))), "") | V92: =IFERROR(TRIM(MID(I92, FIND(",", I92, FIND(",", I92, FIND(",", I92, FIND(",", I92, FIND(",", I92, FIND(",", I92, FIND(",", I92) + 1) + 1) + 1) + 1) + 1) + 1) + 1, IFERROR(FIND(",", I92, FIND(",", I92, FIND(",", I92, FIND(",", I92, FIND(",", I92, FIND(",", I92, FIND(",", I92) + 1) + 1) + 1) + 1) + 1) + 1) - FIND(",", I92, FIND(",", I92, FIND(",", I92, FIND(",", I92, FIND(",", I92, FIND(",", I92) + 1) + 1) + 1) + 1) + 1) - 1, LEN(I92)))), "") | X92: =IFERROR(TRIM(MID(I92, FIND(",", I92, FIND(",", I92, FIND(",", I92, FIND(",", I92, FIND(",", I92, FIND(",", I92, FIND(",", I92, FIND(",", I92) + 1) + 1) + 1) + 1) + 1) + 1) + 1) + 1, IFERROR(FIND(",", I92, FIND(",", I92, FIND(",", I92, FIND(",", I92, FIND(",", I92, FIND(",", I92, FIND(",", I92, FIND(",", I92) + 1) + 1) + 1) + 1) + 1) + 1) + 1) - FIND(",", I92, FIND(",", I92, FIND(",", I92, FIND(",", I92, FIND(",", I92, FIND(",", I92, FIND(",", I92) + 1) + 1) + 1) + 1) + 1) + 1) - 1, LEN(I92)))), "") | Z92: =IFERROR(TRIM(MID(I92, FIND(",", I92, FIND(",", I92, FIND(",", I92, FIND(",", I92, FIND(",", I92, FIND(",", I92, FIND(",", I92, FIND(",", I92, FIND(",", I92) + 1) + 1) + 1) + 1) + 1) + 1) + 1) + 1) + 1, IFERROR(FIND(",", I92, FIND(",", I92, FIND(",", I92, FIND(",", I92, FIND(",", I92, FIND(",", I92, FIND(",", I92, FIND(",", I92, FIND(",", I92) + 1) + 1) + 1) + 1) + 1) + 1) + 1) + 1) - FIND(",", I92, FIND(",", I92, FIND(",", I92, FIND(",", I92, FIND(",", I92, FIND(",", I92, FIND(",", I92, FIND(",", I92) + 1) + 1) + 1) + 1) + 1) + 1) + 1) - 1, LEN(I92)))), "")
A93: 3617051464490FR-X99-22-72903 | B93: 3617051464490 | C93: FR-X99-22-72903 | D93: ¿Ya fueron a ver el video de #LaSiembra ? Dejen en los comentarios que les pareció ~~~~~~~~~ #AfinAr | E93: Los Dos Carnales | G93: AfinArte | H93: =100%-SUM(CatalogTable[[#This Row],[Artist 1 %]],CatalogTable[[#This Row],[Artist 2 %]],CatalogTable[[#This Row],[Artist 3 %]],CatalogTable[[#This Row],[Artist 4 %]],CatalogTable[[#This Row],[Artist 5 %]],CatalogTable[[#This Row],[Artist 6 %]],CatalogTable[[#This Row],[Artist 7 %]],CatalogTable[[#This Row],[Artist 8 %]],CatalogTable[[#This Row],[Artist 9%]]) -> 0.9 | I93: =IF(ISBLANK(E93),"",INDEX(UniqueArtist!B:B, MATCH(E93,UniqueArtist!A:A, 0))) -> Los Dos Carnales | J93: =IFERROR(TRIM(LEFT(I93, IFERROR(FIND(",", I93)-1, LEN(I93)))), "") -> Los Dos Carnales | K93: 0.1 | L93: =IFERROR(TRIM(MID(I93, FIND(",", I93) + 1, IFERROR(FIND(",", I93, FIND(",", I93) + 1) - FIND(",", I93) - 1, LEN(I93)))), "") | N93: =IFERROR(TRIM(MID(I93, FIND(",", I93, FIND(",", I93) + 1) + 1, IFERROR(FIND(",", I93, FIND(",", I93, FIND(",", I93) + 1) + 1) - FIND(",", I93, FIND(",", I93) + 1) - 1, LEN(I93)))), "") | P93: =IFERROR(TRIM(MID(I93, FIND(",", I93, FIND(",", I93, FIND(",", I93) + 1) + 1) + 1, IFERROR(FIND(",", I93, FIND(",", I93, FIND(",", I93, FIND(",", I93) + 1) + 1) + 1) - FIND(",", I93, FIND(",", I93, FIND(",", I93) + 1) + 1) - 1, LEN(I93)))), "") | R93: =IFERROR(TRIM(MID(I93, FIND(",", I93, FIND(",", I93, FIND(",", I93, FIND(",", I93) + 1) + 1) + 1) + 1, IFERROR(FIND(",", I93, FIND(",", I93, FIND(",", I93, FIND(",", I93, FIND(",", I93) + 1) + 1) + 1) + 1) - FIND(",", I93, FIND(",", I93, FIND(",", I93, FIND(",", I93) + 1) + 1) + 1) - 1, LEN(I93)))), "") | T93: =IFERROR(TRIM(MID(I93, FIND(",", I93, FIND(",", I93, FIND(",", I93, FIND(",", I93, FIND(",", I93, FIND(",", I93) + 1) + 1) + 1) + 1) + 1) + 1, IFERROR(FIND(",", I93, FIND(",", I93, FIND(",", I93, FIND(",", I93, FIND(",", I93, FIND(",", I93) + 1) + 1) + 1) + 1) + 1) - FIND(",", I93, FIND(",", I93, FIND(",", I93, FIND(",", I93, FIND(",", I93) + 1) + 1) + 1) + 1) - 1, LEN(I93)))), "") | V93: =IFERROR(TRIM(MID(I93, FIND(",", I93, FIND(",", I93, FIND(",", I93, FIND(",", I93, FIND(",", I93, FIND(",", I93, FIND(",", I93) + 1) + 1) + 1) + 1) + 1) + 1) + 1, IFERROR(FIND(",", I93, FIND(",", I93, FIND(",", I93, FIND(",", I93, FIND(",", I93, FIND(",", I93, FIND(",", I93) + 1) + 1) + 1) + 1) + 1) + 1) - FIND(",", I93, FIND(",", I93, FIND(",", I93, FIND(",", I93, FIND(",", I93, FIND(",", I93) + 1) + 1) + 1) + 1) + 1) - 1, LEN(I93)))), "") | X93: =IFERROR(TRIM(MID(I93, FIND(",", I93, FIND(",", I93, FIND(",", I93, FIND(",", I93, FIND(",", I93, FIND(",", I93, FIND(",", I93, FIND(",", I93) + 1) + 1) + 1) + 1) + 1) + 1) + 1) + 1, IFERROR(FIND(",", I93, FIND(",", I93, FIND(",", I93, FIND(",", I93, FIND(",", I93, FIND(",", I93, FIND(",", I93, FIND(",", I93) + 1) + 1) + 1) + 1) + 1) + 1) + 1) - FIND(",", I93, FIND(",", I93, FIND(",", I93, FIND(",", I93, FIND(",", I93, FIND(",", I93, FIND(",", I93) + 1) + 1) + 1) + 1) + 1) + 1) - 1, LEN(I93)))), "") | Z93: =IFERROR(TRIM(MID(I93, FIND(",", I93, FIND(",", I93, FIND(",", I93, FIND(",", I93, FIND(",", I93, FIND(",", I93, FIND(",", I93, FIND(",", I93, FIND(",", I93) + 1) + 1) + 1) + 1) + 1) + 1) + 1) + 1) + 1, IFERROR(FIND(",", I93, FIND(",", I93, FIND(",", I93, FIND(",", I93, FIND(",", I93, FIND(",", I93, FIND(",", I93, FIND(",", I93, FIND(",", I93) + 1) + 1) + 1) + 1) + 1) + 1) + 1) + 1) - FIND(",", I93, FIND(",", I93, FIND(",", I93, FIND(",", I93, FIND(",", I93, FIND(",", I93, FIND(",", I93, FIND(",", I93) + 1) + 1) + 1) + 1) + 1) + 1) + 1) - 1, LEN(I93)))), "")
A94: 3616849514515FR-X99-22-06738 | B94: 3616849514515 | C94: FR-X99-22-06738 | D94: ¿Ya Hicieron shorts con el video? | E94: El Fantasma | G94: AfinArte | H94: =100%-SUM(CatalogTable[[#This Row],[Artist 1 %]],CatalogTable[[#This Row],[Artist 2 %]],CatalogTable[[#This Row],[Artist 3 %]],CatalogTable[[#This Row],[Artist 4 %]],CatalogTable[[#This Row],[Artist 5 %]],CatalogTable[[#This Row],[Artist 6 %]],CatalogTable[[#This Row],[Artist 7 %]],CatalogTable[[#This Row],[Artist 8 %]],CatalogTable[[#This Row],[Artist 9%]]) -> 0.65 | I94: =IF(ISBLANK(E94),"",INDEX(UniqueArtist!B:B, MATCH(E94,UniqueArtist!A:A, 0))) -> El Fantasma | J94: =IFERROR(TRIM(LEFT(I94, IFERROR(FIND(",", I94)-1, LEN(I94)))), "") -> El Fantasma | K94: 0.35 | L94: =IFERROR(TRIM(MID(I94, FIND(",", I94) + 1, IFERROR(FIND(",", I94, FIND(",", I94) + 1) - FIND(",", I94) - 1, LEN(I94)))), "") | N94: =IFERROR(TRIM(MID(I94, FIND(",", I94, FIND(",", I94) + 1) + 1, IFERROR(FIND(",", I94, FIND(",", I94, FIND(",", I94) + 1) + 1) - FIND(",", I94, FIND(",", I94) + 1) - 1, LEN(I94)))), "") | P94: =IFERROR(TRIM(MID(I94, FIND(",", I94, FIND(",", I94, FIND(",", I94) + 1) + 1) + 1, IFERROR(FIND(",", I94, FIND(",", I94, FIND(",", I94, FIND(",", I94) + 1) + 1) + 1) - FIND(",", I94, FIND(",", I94, FIND(",", I94) + 1) + 1) - 1, LEN(I94)))), "") | R94: =IFERROR(TRIM(MID(I94, FIND(",", I94, FIND(",", I94, FIND(",", I94, FIND(",", I94) + 1) + 1) + 1) + 1, IFERROR(FIND(",", I94, FIND(",", I94, FIND(",", I94, FIND(",", I94, FIND(",", I94) + 1) + 1) + 1) + 1) - FIND(",", I94, FIND(",", I94, FIND(",", I94, FIND(",", I94) + 1) + 1) + 1) - 1, LEN(I94)))), "") | T94: =IFERROR(TRIM(MID(I94, FIND(",", I94, FIND(",", I94, FIND(",", I94, FIND(",", I94, FIND(",", I94, FIND(",", I94) + 1) + 1) + 1) + 1) + 1) + 1, IFERROR(FIND(",", I94, FIND(",", I94, FIND(",", I94, FIND(",", I94, FIND(",", I94, FIND(",", I94) + 1) + 1) + 1) + 1) + 1) - FIND(",", I94, FIND(",", I94, FIND(",", I94, FIND(",", I94, FIND(",", I94) + 1) + 1) + 1) + 1) - 1, LEN(I94)))), "") | V94: =IFERROR(TRIM(MID(I94, FIND(",", I94, FIND(",", I94, FIND(",", I94, FIND(",", I94, FIND(",", I94, FIND(",", I94, FIND(",", I94) + 1) + 1) + 1) + 1) + 1) + 1) + 1, IFERROR(FIND(",", I94, FIND(",", I94, FIND(",", I94, FIND(",", I94, FIND(",", I94, FIND(",", I94, FIND(",", I94) + 1) + 1) + 1) + 1) + 1) + 1) - FIND(",", I94, FIND(",", I94, FIND(",", I94, FIND(",", I94, FIND(",", I94, FIND(",", I94) + 1) + 1) + 1) + 1) + 1) - 1, LEN(I94)))), "") | X94: =IFERROR(TRIM(MID(I94, FIND(",", I94, FIND(",", I94, FIND(",", I94, FIND(",", I94, FIND(",", I94, FIND(",", I94, FIND(",", I94, FIND(",", I94) + 1) + 1) + 1) + 1) + 1) + 1) + 1) + 1, IFERROR(FIND(",", I94, FIND(",", I94, FIND(",", I94, FIND(",", I94, FIND(",", I94, FIND(",", I94, FIND(",", I94, FIND(",", I94) + 1) + 1) + 1) + 1) + 1) + 1) + 1) - FIND(",", I94, FIND(",", I94, FIND(",", I94, FIND(",", I94, FIND(",", I94, FIND(",", I94, FIND(",", I94) + 1) + 1) + 1) + 1) + 1) + 1) - 1, LEN(I94)))), "") | Z94: =IFERROR(TRIM(MID(I94, FIND(",", I94, FIND(",", I94, FIND(",", I94, FIND(",", I94, FIND(",", I94, FIND(",", I94, FIND(",", I94, FIND(",", I94, FIND(",", I94) + 1) + 1) + 1) + 1) + 1) + 1) + 1) + 1) + 1, IFERROR(FIND(",", I94, FIND(",", I94, FIND(",", I94, FIND(",", I94, FIND(",", I94, FIND(",", I94, FIND(",", I94, FIND(",", I94, FIND(",", I94) + 1) + 1) + 1) + 1) + 1) + 1) + 1) + 1) - FIND(",", I94, FIND(",", I94, FIND(",", I94, FIND(",", I94, FIND(",", I94, FIND(",", I94, FIND(",", I94, FIND(",", I94) + 1) + 1) + 1) + 1) + 1) + 1) + 1) - 1, LEN(I94)))), "")
A95: 3617057267811FR-W24-23-79932 | B95: 3617057267811 | C95: FR-W24-23-79932 | D95: ¿Ya hicieron su Remix con el audio Soy Ranchero De Más En #Shorts ?~~~ #shortsvideo #AfinArte | E95: Los Dos Carnales | G95: AfinArte | H95: =100%-SUM(CatalogTable[[#This Row],[Artist 1 %]],CatalogTable[[#This Row],[Artist 2 %]],CatalogTable[[#This Row],[Artist 3 %]],CatalogTable[[#This Row],[Artist 4 %]],CatalogTable[[#This Row],[Artist 5 %]],CatalogTable[[#This Row],[Artist 6 %]],CatalogTable[[#This Row],[Artist 7 %]],CatalogTable[[#This Row],[Artist 8 %]],CatalogTable[[#This Row],[Artist 9%]]) -> 0.9 | I95: =IF(ISBLANK(E95),"",INDEX(UniqueArtist!B:B, MATCH(E95,UniqueArtist!A:A, 0))) -> Los Dos Carnales | J95: =IFERROR(TRIM(LEFT(I95, IFERROR(FIND(",", I95)-1, LEN(I95)))), "") -> Los Dos Carnales | K95: 0.1 | L95: =IFERROR(TRIM(MID(I95, FIND(",", I95) + 1, IFERROR(FIND(",", I95, FIND(",", I95) + 1) - FIND(",", I95) - 1, LEN(I95)))), "") | N95: =IFERROR(TRIM(MID(I95, FIND(",", I95, FIND(",", I95) + 1) + 1, IFERROR(FIND(",", I95, FIND(",", I95, FIND(",", I95) + 1) + 1) - FIND(",", I95, FIND(",", I95) + 1) - 1, LEN(I95)))), "") | P95: =IFERROR(TRIM(MID(I95, FIND(",", I95, FIND(",", I95, FIND(",", I95) + 1) + 1) + 1, IFERROR(FIND(",", I95, FIND(",", I95, FIND(",", I95, FIND(",", I95) + 1) + 1) + 1) - FIND(",", I95, FIND(",", I95, FIND(",", I95) + 1) + 1) - 1, LEN(I95)))), "") | R95: =IFERROR(TRIM(MID(I95, FIND(",", I95, FIND(",", I95, FIND(",", I95, FIND(",", I95) + 1) + 1) + 1) + 1, IFERROR(FIND(",", I95, FIND(",", I95, FIND(",", I95, FIND(",", I95, FIND(",", I95) + 1) + 1) + 1) + 1) - FIND(",", I95, FIND(",", I95, FIND(",", I95, FIND(",", I95) + 1) + 1) + 1) - 1, LEN(I95)))), "") | T95: =IFERROR(TRIM(MID(I95, FIND(",", I95, FIND(",", I95, FIND(",", I95, FIND(",", I95, FIND(",", I95, FIND(",", I95) + 1) + 1) + 1) + 1) + 1) + 1, IFERROR(FIND(",", I95, FIND(",", I95, FIND(",", I95, FIND(",", I95, FIND(",", I95, FIND(",", I95) + 1) + 1) + 1) + 1) + 1) - FIND(",", I95, FIND(",", I95, FIND(",", I95, FIND(",", I95, FIND(",", I95) + 1) + 1) + 1) + 1) - 1, LEN(I95)))), "") | V95: =IFERROR(TRIM(MID(I95, FIND(",", I95, FIND(",", I95, FIND(",", I95, FIND(",", I95, FIND(",", I95, FIND(",", I95, FIND(",", I95) + 1) + 1) + 1) + 1) + 1) + 1) + 1, IFERROR(FIND(",", I95, FIND(",", I95, FIND(",", I95, FIND(",", I95, FIND(",", I95, FIND(",", I95, FIND(",", I95) + 1) + 1) + 1) + 1) + 1) + 1) - FIND(",", I95, FIND(",", I95, FIND(",", I95, FIND(",", I95, FIND(",", I95, FIND(",", I95) + 1) + 1) + 1) + 1) + 1) - 1, LEN(I95)))), "") | X95: =IFERROR(TRIM(MID(I95, FIND(",", I95, FIND(",", I95, FIND(",", I95, FIND(",", I95, FIND(",", I95, FIND(",", I95, FIND(",", I95, FIND(",", I95) + 1) + 1) + 1) + 1) + 1) + 1) + 1) + 1, IFERROR(FIND(",", I95, FIND(",", I95, FIND(",", I95, FIND(",", I95, FIND(",", I95, FIND(",", I95, FIND(",", I95, FIND(",", I95) + 1) + 1) + 1) + 1) + 1) + 1) + 1) - FIND(",", I95, FIND(",", I95, FIND(",", I95, FIND(",", I95, FIND(",", I95, FIND(",", I95, FIND(",", I95) + 1) + 1) + 1) + 1) + 1) + 1) - 1, LEN(I95)))), "") | Z95: =IFERROR(TRIM(MID(I95, FIND(",", I95, FIND(",", I95, FIND(",", I95, FIND(",", I95, FIND(",", I95, FIND(",", I95, FIND(",", I95, FIND(",", I95, FIND(",", I95) + 1) + 1) + 1) + 1) + 1) + 1) + 1) + 1) + 1, IFERROR(FIND(",", I95, FIND(",", I95, FIND(",", I95, FIND(",", I95, FIND(",", I95, FIND(",", I95, FIND(",", I95, FIND(",", I95, FIND(",", I95) + 1) + 1) + 1) + 1) + 1) + 1) + 1) + 1) - FIND(",", I95, FIND(",", I95, FIND(",", I95, FIND(",", I95, FIND(",", I95, FIND(",", I95, FIND(",", I95, FIND(",", I95) + 1) + 1) + 1) + 1) + 1) + 1) + 1) - 1, LEN(I95)))), "")
A96: 3617228460973FR-26V-23-79382 | B96: 3617228460973 | C96: FR-26V-23-79382 | D96: ¿Ya viste la entrevista completa?😎 mírala en @adrianariosmusic #Shorts #Entrevista #AdrianaRios | E96: AfinArte Music | G96: AfinArte | H96: =100%-SUM(CatalogTable[[#This Row],[Artist 1 %]],CatalogTable[[#This Row],[Artist 2 %]],CatalogTable[[#This Row],[Artist 3 %]],CatalogTable[[#This Row],[Artist 4 %]],CatalogTable[[#This Row],[Artist 5 %]],CatalogTable[[#This Row],[Artist 6 %]],CatalogTable[[#This Row],[Artist 7 %]],CatalogTable[[#This Row],[Artist 8 %]],CatalogTable[[#This Row],[Artist 9%]]) -> 0 | I96: =IF(ISBLANK(E96),"",INDEX(UniqueArtist!B:B, MATCH(E96,UniqueArtist!A:A, 0))) -> AfinArte Music | J96: =IFERROR(TRIM(LEFT(I96, IFERROR(FIND(",", I96)-1, LEN(I96)))), "") -> AfinArte Music | K96: 1 | L96: =IFERROR(TRIM(MID(I96, FIND(",", I96) + 1, IFERROR(FIND(",", I96, FIND(",", I96) + 1) - FIND(",", I96) - 1, LEN(I96)))), "") | N96: =IFERROR(TRIM(MID(I96, FIND(",", I96, FIND(",", I96) + 1) + 1, IFERROR(FIND(",", I96, FIND(",", I96, FIND(",", I96) + 1) + 1) - FIND(",", I96, FIND(",", I96) + 1) - 1, LEN(I96)))), "") | P96: =IFERROR(TRIM(MID(I96, FIND(",", I96, FIND(",", I96, FIND(",", I96) + 1) + 1) + 1, IFERROR(FIND(",", I96, FIND(",", I96, FIND(",", I96, FIND(",", I96) + 1) + 1) + 1) - FIND(",", I96, FIND(",", I96, FIND(",", I96) + 1) + 1) - 1, LEN(I96)))), "") | R96: =IFERROR(TRIM(MID(I96, FIND(",", I96, FIND(",", I96, FIND(",", I96, FIND(",", I96) + 1) + 1) + 1) + 1, IFERROR(FIND(",", I96, FIND(",", I96, FIND(",", I96, FIND(",", I96, FIND(",", I96) + 1) + 1) + 1) + 1) - FIND(",", I96, FIND(",", I96, FIND(",", I96, FIND(",", I96) + 1) + 1) + 1) - 1, LEN(I96)))), "") | T96: =IFERROR(TRIM(MID(I96, FIND(",", I96, FIND(",", I96, FIND(",", I96, FIND(",", I96, FIND(",", I96, FIND(",", I96) + 1) + 1) + 1) + 1) + 1) + 1, IFERROR(FIND(",", I96, FIND(",", I96, FIND(",", I96, FIND(",", I96, FIND(",", I96, FIND(",", I96) + 1) + 1) + 1) + 1) + 1) - FIND(",", I96, FIND(",", I96, FIND(",", I96, FIND(",", I96, FIND(",", I96) + 1) + 1) + 1) + 1) - 1, LEN(I96)))), "") | V96: =IFERROR(TRIM(MID(I96, FIND(",", I96, FIND(",", I96, FIND(",", I96, FIND(",", I96, FIND(",", I96, FIND(",", I96, FIND(",", I96) + 1) + 1) + 1) + 1) + 1) + 1) + 1, IFERROR(FIND(",", I96, FIND(",", I96, FIND(",", I96, FIND(",", I96, FIND(",", I96, FIND(",", I96, FIND(",", I96) + 1) + 1) + 1) + 1) + 1) + 1) - FIND(",", I96, FIND(",", I96, FIND(",", I96, FIND(",", I96, FIND(",", I96, FIND(",", I96) + 1) + 1) + 1) + 1) + 1) - 1, LEN(I96)))), "") | X96: =IFERROR(TRIM(MID(I96, FIND(",", I96, FIND(",", I96, FIND(",", I96, FIND(",", I96, FIND(",", I96, FIND(",", I96, FIND(",", I96, FIND(",", I96) + 1) + 1) + 1) + 1) + 1) + 1) + 1) + 1, IFERROR(FIND(",", I96, FIND(",", I96, FIND(",", I96, FIND(",", I96, FIND(",", I96, FIND(",", I96, FIND(",", I96, FIND(",", I96) + 1) + 1) + 1) + 1) + 1) + 1) + 1) - FIND(",", I96, FIND(",", I96, FIND(",", I96, FIND(",", I96, FIND(",", I96, FIND(",", I96, FIND(",", I96) + 1) + 1) + 1) + 1) + 1) + 1) - 1, LEN(I96)))), "") | Z96: =IFERROR(TRIM(MID(I96, FIND(",", I96, FIND(",", I96, FIND(",", I96, FIND(",", I96, FIND(",", I96, FIND(",", I96, FIND(",", I96, FIND(",", I96, FIND(",", I96) + 1) + 1) + 1) + 1) + 1) + 1) + 1) + 1) + 1, IFERROR(FIND(",", I96, FIND(",", I96, FIND(",", I96, FIND(",", I96, FIND(",", I96, FIND(",", I96, FIND(",", I96, FIND(",", I96, FIND(",", I96) + 1) + 1) + 1) + 1) + 1) + 1) + 1) + 1) - FIND(",", I96, FIND(",", I96, FIND(",", I96, FIND(",", I96, FIND(",", I96, FIND(",", I96, FIND(",", I96, FIND(",", I96) + 1) + 1) + 1) + 1) + 1) + 1) + 1) - 1, LEN(I96)))), "")
A97: 3616555135189FR-W77-21-23338 | B97: 3616555135189 | C97: FR-W77-21-23338 | D97: (El Toro Josco ) Los Dos De Tamaulipas | E97: LOS DOS DE TAMAULIPAS | G97: AfinArte | H97: =100%-SUM(CatalogTable[[#This Row],[Artist 1 %]],CatalogTable[[#This Row],[Artist 2 %]],CatalogTable[[#This Row],[Artist 3 %]],CatalogTable[[#This Row],[Artist 4 %]],CatalogTable[[#This Row],[Artist 5 %]],CatalogTable[[#This Row],[Artist 6 %]],CatalogTable[[#This Row],[Artist 7 %]],CatalogTable[[#This Row],[Artist 8 %]],CatalogTable[[#This Row],[Artist 9%]]) -> 0.9 | I97: =IF(ISBLANK(E97),"",INDEX(UniqueArtist!B:B, MATCH(E97,UniqueArtist!A:A, 0))) -> Los Dos de Tamaulipas | J97: =IFERROR(TRIM(LEFT(I97, IFERROR(FIND(",", I97)-1, LEN(I97)))), "") -> Los Dos de Tamaulipas | K97: 0.1 | L97: =IFERROR(TRIM(MID(I97, FIND(",", I97) + 1, IFERROR(FIND(",", I97, FIND(",", I97) + 1) - FIND(",", I97) - 1, LEN(I97)))), "") | N97: =IFERROR(TRIM(MID(I97, FIND(",", I97, FIND(",", I97) + 1) + 1, IFERROR(FIND(",", I97, FIND(",", I97, FIND(",", I97) + 1) + 1) - FIND(",", I97, FIND(",", I97) + 1) - 1, LEN(I97)))), "") | P97: =IFERROR(TRIM(MID(I97, FIND(",", I97, FIND(",", I97, FIND(",", I97) + 1) + 1) + 1, IFERROR(FIND(",", I97, FIND(",", I97, FIND(",", I97, FIND(",", I97) + 1) + 1) + 1) - FIND(",", I97, FIND(",", I97, FIND(",", I97) + 1) + 1) - 1, LEN(I97)))), "") | R97: =IFERROR(TRIM(MID(I97, FIND(",", I97, FIND(",", I97, FIND(",", I97, FIND(",", I97) + 1) + 1) + 1) + 1, IFERROR(FIND(",", I97, FIND(",", I97, FIND(",", I97, FIND(",", I97, FIND(",", I97) + 1) + 1) + 1) + 1) - FIND(",", I97, FIND(",", I97, FIND(",", I97, FIND(",", I97) + 1) + 1) + 1) - 1, LEN(I97)))), "") | T97: =IFERROR(TRIM(MID(I97, FIND(",", I97, FIND(",", I97, FIND(",", I97, FIND(",", I97, FIND(",", I97, FIND(",", I97) + 1) + 1) + 1) + 1) + 1) + 1, IFERROR(FIND(",", I97, FIND(",", I97, FIND(",", I97, FIND(",", I97, FIND(",", I97, FIND(",", I97) + 1) + 1) + 1) + 1) + 1) - FIND(",", I97, FIND(",", I97, FIND(",", I97, FIND(",", I97, FIND(",", I97) + 1) + 1) + 1) + 1) - 1, LEN(I97)))), "") | V97: =IFERROR(TRIM(MID(I97, FIND(",", I97, FIND(",", I97, FIND(",", I97, FIND(",", I97, FIND(",", I97, FIND(",", I97, FIND(",", I97) + 1) + 1) + 1) + 1) + 1) + 1) + 1, IFERROR(FIND(",", I97, FIND(",", I97, FIND(",", I97, FIND(",", I97, FIND(",", I97, FIND(",", I97, FIND(",", I97) + 1) + 1) + 1) + 1) + 1) + 1) - FIND(",", I97, FIND(",", I97, FIND(",", I97, FIND(",", I97, FIND(",", I97, FIND(",", I97) + 1) + 1) + 1) + 1) + 1) - 1, LEN(I97)))), "") | X97: =IFERROR(TRIM(MID(I97, FIND(",", I97, FIND(",", I97, FIND(",", I97, FIND(",", I97, FIND(",", I97, FIND(",", I97, FIND(",", I97, FIND(",", I97) + 1) + 1) + 1) + 1) + 1) + 1) + 1) + 1, IFERROR(FIND(",", I97, FIND(",", I97, FIND(",", I97, FIND(",", I97, FIND(",", I97, FIND(",", I97, FIND(",", I97, FIND(",", I97) + 1) + 1) + 1) + 1) + 1) + 1) + 1) - FIND(",", I97, FIND(",", I97, FIND(",", I97, FIND(",", I97, FIND(",", I97, FIND(",", I97, FIND(",", I97) + 1) + 1) + 1) + 1) + 1) + 1) - 1, LEN(I97)))), "") | Z97: =IFERROR(TRIM(MID(I97, FIND(",", I97, FIND(",", I97, FIND(",", I97, FIND(",", I97, FIND(",", I97, FIND(",", I97, FIND(",", I97, FIND(",", I97, FIND(",", I97) + 1) + 1) + 1) + 1) + 1) + 1) + 1) + 1) + 1, IFERROR(FIND(",", I97, FIND(",", I97, FIND(",", I97, FIND(",", I97, FIND(",", I97, FIND(",", I97, FIND(",", I97, FIND(",", I97, FIND(",", I97) + 1) + 1) + 1) + 1) + 1) + 1) + 1) + 1) - FIND(",", I97, FIND(",", I97, FIND(",", I97, FIND(",", I97, FIND(",", I97, FIND(",", I97, FIND(",", I97, FIND(",", I97) + 1) + 1) + 1) + 1) + 1) + 1) + 1) - 1, LEN(I97)))), "")
A98: 3616555121847FR-W77-21-23070 | B98: 3616555121847 | C98: FR-W77-21-23070 | D98: (Por Alguien) Los Dos de Tamaulipas | E98: LOS DOS DE TAMAULIPAS | G98: AfinArte | H98: =100%-SUM(CatalogTable[[#This Row],[Artist 1 %]],CatalogTable[[#This Row],[Artist 2 %]],CatalogTable[[#This Row],[Artist 3 %]],CatalogTable[[#This Row],[Artist 4 %]],CatalogTable[[#This Row],[Artist 5 %]],CatalogTable[[#This Row],[Artist 6 %]],CatalogTable[[#This Row],[Artist 7 %]],CatalogTable[[#This Row],[Artist 8 %]],CatalogTable[[#This Row],[Artist 9%]]) -> 0.9 | I98: =IF(ISBLANK(E98),"",INDEX(UniqueArtist!B:B, MATCH(E98,UniqueArtist!A:A, 0))) -> Los Dos de Tamaulipas | J98: =IFERROR(TRIM(LEFT(I98, IFERROR(FIND(",", I98)-1, LEN(I98)))), "") -> Los Dos de Tamaulipas | K98: 0.1 | L98: =IFERROR(TRIM(MID(I98, FIND(",", I98) + 1, IFERROR(FIND(",", I98, FIND(",", I98) + 1) - FIND(",", I98) - 1, LEN(I98)))), "") | N98: =IFERROR(TRIM(MID(I98, FIND(",", I98, FIND(",", I98) + 1) + 1, IFERROR(FIND(",", I98, FIND(",", I98, FIND(",", I98) + 1) + 1) - FIND(",", I98, FIND(",", I98) + 1) - 1, LEN(I98)))), "") | P98: =IFERROR(TRIM(MID(I98, FIND(",", I98, FIND(",", I98, FIND(",", I98) + 1) + 1) + 1, IFERROR(FIND(",", I98, FIND(",", I98, FIND(",", I98, FIND(",", I98) + 1) + 1) + 1) - FIND(",", I98, FIND(",", I98, FIND(",", I98) + 1) + 1) - 1, LEN(I98)))), "") | R98: =IFERROR(TRIM(MID(I98, FIND(",", I98, FIND(",", I98, FIND(",", I98, FIND(",", I98) + 1) + 1) + 1) + 1, IFERROR(FIND(",", I98, FIND(",", I98, FIND(",", I98, FIND(",", I98, FIND(",", I98) + 1) + 1) + 1) + 1) - FIND(",", I98, FIND(",", I98, FIND(",", I98, FIND(",", I98) + 1) + 1) + 1) - 1, LEN(I98)))), "") | T98: =IFERROR(TRIM(MID(I98, FIND(",", I98, FIND(",", I98, FIND(",", I98, FIND(",", I98, FIND(",", I98, FIND(",", I98) + 1) + 1) + 1) + 1) + 1) + 1, IFERROR(FIND(",", I98, FIND(",", I98, FIND(",", I98, FIND(",", I98, FIND(",", I98, FIND(",", I98) + 1) + 1) + 1) + 1) + 1) - FIND(",", I98, FIND(",", I98, FIND(",", I98, FIND(",", I98, FIND(",", I98) + 1) + 1) + 1) + 1) - 1, LEN(I98)))), "") | V98: =IFERROR(TRIM(MID(I98, FIND(",", I98, FIND(",", I98, FIND(",", I98, FIND(",", I98, FIND(",", I98, FIND(",", I98, FIND(",", I98) + 1) + 1) + 1) + 1) + 1) + 1) + 1, IFERROR(FIND(",", I98, FIND(",", I98, FIND(",", I98, FIND(",", I98, FIND(",", I98, FIND(",", I98, FIND(",", I98) + 1) + 1) + 1) + 1) + 1) + 1) - FIND(",", I98, FIND(",", I98, FIND(",", I98, FIND(",", I98, FIND(",", I98, FIND(",", I98) + 1) + 1) + 1) + 1) + 1) - 1, LEN(I98)))), "") | X98: =IFERROR(TRIM(MID(I98, FIND(",", I98, FIND(",", I98, FIND(",", I98, FIND(",", I98, FIND(",", I98, FIND(",", I98, FIND(",", I98, FIND(",", I98) + 1) + 1) + 1) + 1) + 1) + 1) + 1) + 1, IFERROR(FIND(",", I98, FIND(",", I98, FIND(",", I98, FIND(",", I98, FIND(",", I98, FIND(",", I98, FIND(",", I98, FIND(",", I98) + 1) + 1) + 1) + 1) + 1) + 1) + 1) - FIND(",", I98, FIND(",", I98, FIND(",", I98, FIND(",", I98, FIND(",", I98, FIND(",", I98, FIND(",", I98) + 1) + 1) + 1) + 1) + 1) + 1) - 1, LEN(I98)))), "") | Z98: =IFERROR(TRIM(MID(I98, FIND(",", I98, FIND(",", I98, FIND(",", I98, FIND(",", I98, FIND(",", I98, FIND(",", I98, FIND(",", I98, FIND(",", I98, FIND(",", I98) + 1) + 1) + 1) + 1) + 1) + 1) + 1) + 1) + 1, IFERROR(FIND(",", I98, FIND(",", I98, FIND(",", I98, FIND(",", I98, FIND(",", I98, FIND(",", I98, FIND(",", I98, FIND(",", I98, FIND(",", I98) + 1) + 1) + 1) + 1) + 1) + 1) + 1) + 1) - FIND(",", I98, FIND(",", I98, FIND(",", I98, FIND(",", I98, FIND(",", I98, FIND(",", I98, FIND(",", I98, FIND(",", I98) + 1) + 1) + 1) + 1) + 1) + 1) + 1) - 1, LEN(I98)))), "")
A99: 3617051790056FR-X99-22-82436 | B99: 3617051790056 | C99: FR-X99-22-82436 | D99: @La Explosiva Banda De Maza #NYC #AfinArteMusic ~~~~~~~~~~~~ | E99: AfinArte Music | G99: AfinArte | H99: =100%-SUM(CatalogTable[[#This Row],[Artist 1 %]],CatalogTable[[#This Row],[Artist 2 %]],CatalogTable[[#This Row],[Artist 3 %]],CatalogTable[[#This Row],[Artist 4 %]],CatalogTable[[#This Row],[Artist 5 %]],CatalogTable[[#This Row],[Artist 6 %]],CatalogTable[[#This Row],[Artist 7 %]],CatalogTable[[#This Row],[Artist 8 %]],CatalogTable[[#This Row],[Artist 9%]]) -> 0 | I99: =IF(ISBLANK(E99),"",INDEX(UniqueArtist!B:B, MATCH(E99,UniqueArtist!A:A, 0))) -> AfinArte Music | J99: =IFERROR(TRIM(LEFT(I99, IFERROR(FIND(",", I99)-1, LEN(I99)))), "") -> AfinArte Music | K99: 1 | L99: =IFERROR(TRIM(MID(I99, FIND(",", I99) + 1, IFERROR(FIND(",", I99, FIND(",", I99) + 1) - FIND(",", I99) - 1, LEN(I99)))), "") | N99: =IFERROR(TRIM(MID(I99, FIND(",", I99, FIND(",", I99) + 1) + 1, IFERROR(FIND(",", I99, FIND(",", I99, FIND(",", I99) + 1) + 1) - FIND(",", I99, FIND(",", I99) + 1) - 1, LEN(I99)))), "") | P99: =IFERROR(TRIM(MID(I99, FIND(",", I99, FIND(",", I99, FIND(",", I99) + 1) + 1) + 1, IFERROR(FIND(",", I99, FIND(",", I99, FIND(",", I99, FIND(",", I99) + 1) + 1) + 1) - FIND(",", I99, FIND(",", I99, FIND(",", I99) + 1) + 1) - 1, LEN(I99)))), "") | R99: =IFERROR(TRIM(MID(I99, FIND(",", I99, FIND(",", I99, FIND(",", I99, FIND(",", I99) + 1) + 1) + 1) + 1, IFERROR(FIND(",", I99, FIND(",", I99, FIND(",", I99, FIND(",", I99, FIND(",", I99) + 1) + 1) + 1) + 1) - FIND(",", I99, FIND(",", I99, FIND(",", I99, FIND(",", I99) + 1) + 1) + 1) - 1, LEN(I99)))), "") | T99: =IFERROR(TRIM(MID(I99, FIND(",", I99, FIND(",", I99, FIND(",", I99, FIND(",", I99, FIND(",", I99, FIND(",", I99) + 1) + 1) + 1) + 1) + 1) + 1, IFERROR(FIND(",", I99, FIND(",", I99, FIND(",", I99, FIND(",", I99, FIND(",", I99, FIND(",", I99) + 1) + 1) + 1) + 1) + 1) - FIND(",", I99, FIND(",", I99, FIND(",", I99, FIND(",", I99, FIND(",", I99) + 1) + 1) + 1) + 1) - 1, LEN(I99)))), "") | V99: =IFERROR(TRIM(MID(I99, FIND(",", I99, FIND(",", I99, FIND(",", I99, FIND(",", I99, FIND(",", I99, FIND(",", I99, FIND(",", I99) + 1) + 1) + 1) + 1) + 1) + 1) + 1, IFERROR(FIND(",", I99, FIND(",", I99, FIND(",", I99, FIND(",", I99, FIND(",", I99, FIND(",", I99, FIND(",", I99) + 1) + 1) + 1) + 1) + 1) + 1) - FIND(",", I99, FIND(",", I99, FIND(",", I99, FIND(",", I99, FIND(",", I99, FIND(",", I99) + 1) + 1) + 1) + 1) + 1) - 1, LEN(I99)))), "") | X99: =IFERROR(TRIM(MID(I99, FIND(",", I99, FIND(",", I99, FIND(",", I99, FIND(",", I99, FIND(",", I99, FIND(",", I99, FIND(",", I99, FIND(",", I99) + 1) + 1) + 1) + 1) + 1) + 1) + 1) + 1, IFERROR(FIND(",", I99, FIND(",", I99, FIND(",", I99, FIND(",", I99, FIND(",", I99, FIND(",", I99, FIND(",", I99, FIND(",", I99) + 1) + 1) + 1) + 1) + 1) + 1) + 1) - FIND(",", I99, FIND(",", I99, FIND(",", I99, FIND(",", I99, FIND(",", I99, FIND(",", I99, FIND(",", I99) + 1) + 1) + 1) + 1) + 1) + 1) - 1, LEN(I99)))), "") | Z99: =IFERROR(TRIM(MID(I99, FIND(",", I99, FIND(",", I99, FIND(",", I99, FIND(",", I99, FIND(",", I99, FIND(",", I99, FIND(",", I99, FIND(",", I99, FIND(",", I99) + 1) + 1) + 1) + 1) + 1) + 1) + 1) + 1) + 1, IFERROR(FIND(",", I99, FIND(",", I99, FIND(",", I99, FIND(",", I99, FIND(",", I99, FIND(",", I99, FIND(",", I99, FIND(",", I99, FIND(",", I99) + 1) + 1) + 1) + 1) + 1) + 1) + 1) + 1) - FIND(",", I99, FIND(",", I99, FIND(",", I99, FIND(",", I99, FIND(",", I99, FIND(",", I99, FIND(",", I99, FIND(",", I99) + 1) + 1) + 1) + 1) + 1) + 1) + 1) - 1, LEN(I99)))), "")
A100: 3617227943897FR-26V-23-60748 | B100: 3617227943897 | C100: FR-26V-23-60748 | D100: @LosDosCarnales en evento junto a #LaMejor ⛽️ #Shorts #LosDosCarnales #YTShorts | E100: AfinArte Music | G100: AfinArte | H100: =100%-SUM(CatalogTable[[#This Row],[Artist 1 %]],CatalogTable[[#This Row],[Artist 2 %]],CatalogTable[[#This Row],[Artist 3 %]],CatalogTable[[#This Row],[Artist 4 %]],CatalogTable[[#This Row],[Artist 5 %]],CatalogTable[[#This Row],[Artist 6 %]],CatalogTable[[#This Row],[Artist 7 %]],CatalogTable[[#This Row],[Artist 8 %]],CatalogTable[[#This Row],[Artist 9%]]) -> 0 | I100: =IF(ISBLANK(E100),"",INDEX(UniqueArtist!B:B, MATCH(E100,UniqueArtist!A:A, 0))) -> AfinArte Music | J100: =IFERROR(TRIM(LEFT(I100, IFERROR(FIND(",", I100)-1, LEN(I100)))), "") -> AfinArte Music | K100: 1 | L100: =IFERROR(TRIM(MID(I100, FIND(",", I100) + 1, IFERROR(FIND(",", I100, FIND(",", I100) + 1) - FIND(",", I100) - 1, LEN(I100)))), "") | N100: =IFERROR(TRIM(MID(I100, FIND(",", I100, FIND(",", I100) + 1) + 1, IFERROR(FIND(",", I100, FIND(",", I100, FIND(",", I100) + 1) + 1) - FIND(",", I100, FIND(",", I100) + 1) - 1, LEN(I100)))), "") | P100: =IFERROR(TRIM(MID(I100, FIND(",", I100, FIND(",", I100, FIND(",", I100) + 1) + 1) + 1, IFERROR(FIND(",", I100, FIND(",", I100, FIND(",", I100, FIND(",", I100) + 1) + 1) + 1) - FIND(",", I100, FIND(",", I100, FIND(",", I100) + 1) + 1) - 1, LEN(I100)))), "") | R100: =IFERROR(TRIM(MID(I100, FIND(",", I100, FIND(",", I100, FIND(",", I100, FIND(",", I100) + 1) + 1) + 1) + 1, IFERROR(FIND(",", I100, FIND(",", I100, FIND(",", I100, FIND(",", I100, FIND(",", I100) + 1) + 1) + 1) + 1) - FIND(",", I100, FIND(",", I100, FIND(",", I100, FIND(",", I100) + 1) + 1) + 1) - 1, LEN(I100)))), "") | T100: =IFERROR(TRIM(MID(I100, FIND(",", I100, FIND(",", I100, FIND(",", I100, FIND(",", I100, FIND(",", I100, FIND(",", I100) + 1) + 1) + 1) + 1) + 1) + 1, IFERROR(FIND(",", I100, FIND(",", I100, FIND(",", I100, FIND(",", I100, FIND(",", I100, FIND(",", I100) + 1) + 1) + 1) + 1) + 1) - FIND(",", I100, FIND(",", I100, FIND(",", I100, FIND(",", I100, FIND(",", I100) + 1) + 1) + 1) + 1) - 1, LEN(I100)))), "") | V100: =IFERROR(TRIM(MID(I100, FIND(",", I100, FIND(",", I100, FIND(",", I100, FIND(",", I100, FIND(",", I100, FIND(",", I100, FIND(",", I100) + 1) + 1) + 1) + 1) + 1) + 1) + 1, IFERROR(FIND(",", I100, FIND(",", I100, FIND(",", I100, FIND(",", I100, FIND(",", I100, FIND(",", I100, FIND(",", I100) + 1) + 1) + 1) + 1) + 1) + 1) - FIND(",", I100, FIND(",", I100, FIND(",", I100, FIND(",", I100, FIND(",", I100, FIND(",", I100) + 1) + 1) + 1) + 1) + 1) - 1, LEN(I100)))), "") | X100: =IFERROR(TRIM(MID(I100, FIND(",", I100, FIND(",", I100, FIND(",", I100, FIND(",", I100, FIND(",", I100, FIND(",", I100, FIND(",", I100, FIND(",", I100) + 1) + 1) + 1) + 1) + 1) + 1) + 1) + 1, IFERROR(FIND(",", I100, FIND(",", I100, FIND(",", I100, FIND(",", I100, FIND(",", I100, FIND(",", I100, FIND(",", I100, FIND(",", I100) + 1) + 1) + 1) + 1) + 1) + 1) + 1) - FIND(",", I100, FIND(",", I100, FIND(",", I100, FIND(",", I100, FIND(",", I100, FIND(",", I100, FIND(",", I100) + 1) + 1) + 1) + 1) + 1) + 1) - 1, LEN(I100)))), "") | Z100: =IFERROR(TRIM(MID(I100, FIND(",", I100, FIND(",", I100, FIND(",", I100, FIND(",", I100, FIND(",", I100, FIND(",", I100, FIND(",", I100, FIND(",", I100, FIND(",", I100) + 1) + 1) + 1) + 1) + 1) + 1) + 1) + 1) + 1, IFERROR(FIND(",", I100, FIND(",", I100, FIND(",", I100, FIND(",", I100, FIND(",", I100, FIND(",", I100, FIND(",", I100, FIND(",", I100, FIND(",", I100) + 1) + 1) + 1) + 1) + 1) + 1) + 1) + 1) - FIND(",", I100, FIND(",", I100, FIND(",", I100, FIND(",", I100, FIND(",", I100, FIND(",", I100, FIND(",", I100, FIND(",", I100) + 1) + 1) + 1) + 1) + 1) + 1) + 1) - 1, LEN(I100)))), "")
... A154: 3615936949469FR-W24-19-19675 | B154: 3615936949469 | C154: FR-W24-19-19675 | D154: 10 En La Loquera Te Extraño - Voz de Mando 2018 | E154: Voz De Mando | G154: AfinArte | H154: =100%-SUM(CatalogTable[[#This Row],[Artist 1 %]],CatalogTable[[#This Row],[Artist 2 %]],CatalogTable[[#This Row],[Artist 3 %]],CatalogTable[[#This Row],[Artist 4 %]],CatalogTable[[#This Row],[Artist 5 %]],CatalogTable[[#This Row],[Artist 6 %]],CatalogTable[[#This Row],[Artist 7 %]],CatalogTable[[#This Row],[Artist 8 %]],CatalogTable[[#This Row],[Artist 9%]]) -> 0 | I154: =IF(ISBLANK(E154),"",INDEX(UniqueArtist!B:B, MATCH(E154,UniqueArtist!A:A, 0))) -> Voz de Mando | J154: =IFERROR(TRIM(LEFT(I154, IFERROR(FIND(",", I154)-1, LEN(I154)))), "") -> Voz de Mando | K154: 1 | L154: =IFERROR(TRIM(MID(I154, FIND(",", I154) + 1, IFERROR(FIND(",", I154, FIND(",", I154) + 1) - FIND(",", I154) - 1, LEN(I154)))), "") | N154: =IFERROR(TRIM(MID(I154, FIND(",", I154, FIND(",", I154) + 1) + 1, IFERROR(FIND(",", I154, FIND(",", I154, FIND(",", I154) + 1) + 1) - FIND(",", I154, FIND(",", I154) + 1) - 1, LEN(I154)))), "") | P154: =IFERROR(TRIM(MID(I154, FIND(",", I154, FIND(",", I154, FIND(",", I154) + 1) + 1) + 1, IFERROR(FIND(",", I154, FIND(",", I154, FIND(",", I154, FIND(",", I154) + 1) + 1) + 1) - FIND(",", I154, FIND(",", I154, FIND(",", I154) + 1) + 1) - 1, LEN(I154)))), "") | R154: =IFERROR(TRIM(MID(I154, FIND(",", I154, FIND(",", I154, FIND(",", I154, FIND(",", I154) + 1) + 1) + 1) + 1, IFERROR(FIND(",", I154, FIND(",", I154, FIND(",", I154, FIND(",", I154, FIND(",", I154) + 1) + 1) + 1) + 1) - FIND(",", I154, FIND(",", I154, FIND(",", I154, FIND(",", I154) + 1) + 1) + 1) - 1, LEN(I154)))), "") | T154: =IFERROR(TRIM(MID(I154, FIND(",", I154, FIND(",", I154, FIND(",", I154, FIND(",", I154, FIND(",", I154, FIND(",", I154) + 1) + 1) + 1) + 1) + 1) + 1, IFERROR(FIND(",", I154, FIND(",", I154, FIND(",", I154, FIND(",", I154, FIND(",", I154, FIND(",", I154) + 1) + 1) + 1) + 1) + 1) - FIND(",", I154, FIND(",", I154, FIND(",", I154, FIND(",", I154, FIND(",", I154) + 1) + 1) + 1) + 1) - 1, LEN(I154)))), "") | V154: =IFERROR(TRIM(MID(I154, FIND(",", I154, FIND(",", I154, FIND(",", I154, FIND(",", I154, FIND(",", I154, FIND(",", I154, FIND(",", I154) + 1) + 1) + 1) + 1) + 1) + 1) + 1, IFERROR(FIND(",", I154, FIND(",", I154, FIND(",", I154, FIND(",", I154, FIND(",", I154, FIND(",", I154, FIND(",", I154) + 1) + 1) + 1) + 1) + 1) + 1) - FIND(",", I154, FIND(",", I154, FIND(",", I154, FIND(",", I154, FIND(",", I154, FIND(",", I154) + 1) + 1) + 1) + 1) + 1) - 1, LEN(I154)))), "") | X154: =IFERROR(TRIM(MID(I154, FIND(",", I154, FIND(",", I154, FIND(",", I154, FIND(",", I154, FIND(",", I154, FIND(",", I154, FIND(",", I154, FIND(",", I154) + 1) + 1) + 1) + 1) + 1) + 1) + 1) + 1, IFERROR(FIND(",", I154, FIND(",", I154, FIND(",", I154, FIND(",", I154, FIND(",", I154, FIND(",", I154, FIND(",", I154, FIND(",", I154) + 1) + 1) + 1) + 1) + 1) + 1) + 1) - FIND(",", I154, FIND(",", I154, FIND(",", I154, FIND(",", I154, FIND(",", I154, FIND(",", I154, FIND(",", I154) + 1) + 1) + 1) + 1) + 1) + 1) - 1, LEN(I154)))), "") | Z154: =IFERROR(TRIM(MID(I154, FIND(",", I154, FIND(",", I154, FIND(",", I154, FIND(",", I154, FIND(",", I154, FIND(",", I154, FIND(",", I154, FIND(",", I154, FIND(",", I154) + 1) + 1) + 1) + 1) + 1) + 1) + 1) + 1) + 1, IFERROR(FIND(",", I154, FIND(",", I154, FIND(",", I154, FIND(",", I154, FIND(",", I154, FIND(",", I154, FIND(",", I154, FIND(",", I154, FIND(",", I154) + 1) + 1) + 1) + 1) + 1) + 1) + 1) + 1) - FIND(",", I154, FIND(",", I154, FIND(",", I154, FIND(",", I154, FIND(",", I154, FIND(",", I154, FIND(",", I154, FIND(",", I154) + 1) + 1) + 1) + 1) + 1) + 1) + 1) - 1, LEN(I154)))), "")
A155: 3616401453733 | B155: 3616401453733 | D155: 10 Kilates | E155: El Fantasma | F155: 43756 | G155: AfinArte | H155: =100%-SUM(CatalogTable[[#This Row],[Artist 1 %]],CatalogTable[[#This Row],[Artist 2 %]],CatalogTable[[#This Row],[Artist 3 %]],CatalogTable[[#This Row],[Artist 4 %]],CatalogTable[[#This Row],[Artist 5 %]],CatalogTable[[#This Row],[Artist 6 %]],CatalogTable[[#This Row],[Artist 7 %]],CatalogTable[[#This Row],[Artist 8 %]],CatalogTable[[#This Row],[Artist 9%]]) -> 0.75 | I155: =IF(ISBLANK(E155),"",INDEX(UniqueArtist!B:B, MATCH(E155,UniqueArtist!A:A, 0))) -> El Fantasma | J155: =IFERROR(TRIM(LEFT(I155, IFERROR(FIND(",", I155)-1, LEN(I155)))), "") -> El Fantasma | K155: 0.25 | L155: =IFERROR(TRIM(MID(I155, FIND(",", I155) + 1, IFERROR(FIND(",", I155, FIND(",", I155) + 1) - FIND(",", I155) - 1, LEN(I155)))), "") | N155: =IFERROR(TRIM(MID(I155, FIND(",", I155, FIND(",", I155) + 1) + 1, IFERROR(FIND(",", I155, FIND(",", I155, FIND(",", I155) + 1) + 1) - FIND(",", I155, FIND(",", I155) + 1) - 1, LEN(I155)))), "") | P155: =IFERROR(TRIM(MID(I155, FIND(",", I155, FIND(",", I155, FIND(",", I155) + 1) + 1) + 1, IFERROR(FIND(",", I155, FIND(",", I155, FIND(",", I155, FIND(",", I155) + 1) + 1) + 1) - FIND(",", I155, FIND(",", I155, FIND(",", I155) + 1) + 1) - 1, LEN(I155)))), "") | R155: =IFERROR(TRIM(MID(I155, FIND(",", I155, FIND(",", I155, FIND(",", I155, FIND(",", I155) + 1) + 1) + 1) + 1, IFERROR(FIND(",", I155, FIND(",", I155, FIND(",", I155, FIND(",", I155, FIND(",", I155) + 1) + 1) + 1) + 1) - FIND(",", I155, FIND(",", I155, FIND(",", I155, FIND(",", I155) + 1) + 1) + 1) - 1, LEN(I155)))), "") | T155: =IFERROR(TRIM(MID(I155, FIND(",", I155, FIND(",", I155, FIND(",", I155, FIND(",", I155, FIND(",", I155, FIND(",", I155) + 1) + 1) + 1) + 1) + 1) + 1, IFERROR(FIND(",", I155, FIND(",", I155, FIND(",", I155, FIND(",", I155, FIND(",", I155, FIND(",", I155) + 1) + 1) + 1) + 1) + 1) - FIND(",", I155, FIND(",", I155, FIND(",", I155, FIND(",", I155, FIND(",", I155) + 1) + 1) + 1) + 1) - 1, LEN(I155)))), "") | V155: =IFERROR(TRIM(MID(I155, FIND(",", I155, FIND(",", I155, FIND(",", I155, FIND(",", I155, FIND(",", I155, FIND(",", I155, FIND(",", I155) + 1) + 1) + 1) + 1) + 1) + 1) + 1, IFERROR(FIND(",", I155, FIND(",", I155, FIND(",", I155, FIND(",", I155, FIND(",", I155, FIND(",", I155, FIND(",", I155) + 1) + 1) + 1) + 1) + 1) + 1) - FIND(",", I155, FIND(",", I155, FIND(",", I155, FIND(",", I155, FIND(",", I155, FIND(",", I155) + 1) + 1) + 1) + 1) + 1) - 1, LEN(I155)))), "") | X155: =IFERROR(TRIM(MID(I155, FIND(",", I155, FIND(",", I155, FIND(",", I155, FIND(",", I155, FIND(",", I155, FIND(",", I155, FIND(",", I155, FIND(",", I155) + 1) + 1) + 1) + 1) + 1) + 1) + 1) + 1, IFERROR(FIND(",", I155, FIND(",", I155, FIND(",", I155, FIND(",", I155, FIND(",", I155, FIND(",", I155, FIND(",", I155, FIND(",", I155) + 1) + 1) + 1) + 1) + 1) + 1) + 1) - FIND(",", I155, FIND(",", I155, FIND(",", I155, FIND(",", I155, FIND(",", I155, FIND(",", I155, FIND(",", I155) + 1) + 1) + 1) + 1) + 1) + 1) - 1, LEN(I155)))), "") | Z155: =IFERROR(TRIM(MID(I155, FIND(",", I155, FIND(",", I155, FIND(",", I155, FIND(",", I155, FIND(",", I155, FIND(",", I155, FIND(",", I155, FIND(",", I155, FIND(",", I155) + 1) + 1) + 1) + 1) + 1) + 1) + 1) + 1) + 1, IFERROR(FIND(",", I155, FIND(",", I155, FIND(",", I155, FIND(",", I155, FIND(",", I155, FIND(",", I155, FIND(",", I155, FIND(",", I155, FIND(",", I155) + 1) + 1) + 1) + 1) + 1) + 1) + 1) + 1) - FIND(",", I155, FIND(",", I155, FIND(",", I155, FIND(",", I155, FIND(",", I155, FIND(",", I155, FIND(",", I155, FIND(",", I155) + 1) + 1) + 1) + 1) + 1) + 1) + 1) - 1, LEN(I155)))), "")
A156: 3616401839407FR-X99-19-12584 | B156: 3616401839407 | C156: FR-X99-19-12584 | D156: 10 Kilates (Disco Completo) | E156: El Fantasma | F156: 43756 | G156: AfinArte | H156: =100%-SUM(CatalogTable[[#This Row],[Artist 1 %]],CatalogTable[[#This Row],[Artist 2 %]],CatalogTable[[#This Row],[Artist 3 %]],CatalogTable[[#This Row],[Artist 4 %]],CatalogTable[[#This Row],[Artist 5 %]],CatalogTable[[#This Row],[Artist 6 %]],CatalogTable[[#This Row],[Artist 7 %]],CatalogTable[[#This Row],[Artist 8 %]],CatalogTable[[#This Row],[Artist 9%]]) -> 0.75 | I156: =IF(ISBLANK(E156),"",INDEX(UniqueArtist!B:B, MATCH(E156,UniqueArtist!A:A, 0))) -> El Fantasma | J156: =IFERROR(TRIM(LEFT(I156, IFERROR(FIND(",", I156)-1, LEN(I156)))), "") -> El Fantasma | K156: 0.25 | L156: =IFERROR(TRIM(MID(I156, FIND(",", I156) + 1, IFERROR(FIND(",", I156, FIND(",", I156) + 1) - FIND(",", I156) - 1, LEN(I156)))), "") | N156: =IFERROR(TRIM(MID(I156, FIND(",", I156, FIND(",", I156) + 1) + 1, IFERROR(FIND(",", I156, FIND(",", I156, FIND(",", I156) + 1) + 1) - FIND(",", I156, FIND(",", I156) + 1) - 1, LEN(I156)))), "") | P156: =IFERROR(TRIM(MID(I156, FIND(",", I156, FIND(",", I156, FIND(",", I156) + 1) + 1) + 1, IFERROR(FIND(",", I156, FIND(",", I156, FIND(",", I156, FIND(",", I156) + 1) + 1) + 1) - FIND(",", I156, FIND(",", I156, FIND(",", I156) + 1) + 1) - 1, LEN(I156)))), "") | R156: =IFERROR(TRIM(MID(I156, FIND(",", I156, FIND(",", I156, FIND(",", I156, FIND(",", I156) + 1) + 1) + 1) + 1, IFERROR(FIND(",", I156, FIND(",", I156, FIND(",", I156, FIND(",", I156, FIND(",", I156) + 1) + 1) + 1) + 1) - FIND(",", I156, FIND(",", I156, FIND(",", I156, FIND(",", I156) + 1) + 1) + 1) - 1, LEN(I156)))), "") | T156: =IFERROR(TRIM(MID(I156, FIND(",", I156, FIND(",", I156, FIND(",", I156, FIND(",", I156, FIND(",", I156, FIND(",", I156) + 1) + 1) + 1) + 1) + 1) + 1, IFERROR(FIND(",", I156, FIND(",", I156, FIND(",", I156, FIND(",", I156, FIND(",", I156, FIND(",", I156) + 1) + 1) + 1) + 1) + 1) - FIND(",", I156, FIND(",", I156, FIND(",", I156, FIND(",", I156, FIND(",", I156) + 1) + 1) + 1) + 1) - 1, LEN(I156)))), "") | V156: =IFERROR(TRIM(MID(I156, FIND(",", I156, FIND(",", I156, FIND(",", I156, FIND(",", I156, FIND(",", I156, FIND(",", I156, FIND(",", I156) + 1) + 1) + 1) + 1) + 1) + 1) + 1, IFERROR(FIND(",", I156, FIND(",", I156, FIND(",", I156, FIND(",", I156, FIND(",", I156, FIND(",", I156, FIND(",", I156) + 1) + 1) + 1) + 1) + 1) + 1) - FIND(",", I156, FIND(",", I156, FIND(",", I156, FIND(",", I156, FIND(",", I156, FIND(",", I156) + 1) + 1) + 1) + 1) + 1) - 1, LEN(I156)))), "") | X156: =IFERROR(TRIM(MID(I156, FIND(",", I156, FIND(",", I156, FIND(",", I156, FIND(",", I156, FIND(",", I156, FIND(",", I156, FIND(",", I156, FIND(",", I156) + 1) + 1) + 1) + 1) + 1) + 1) + 1) + 1, IFERROR(FIND(",", I156, FIND(",", I156, FIND(",", I156, FIND(",", I156, FIND(",", I156, FIND(",", I156, FIND(",", I156, FIND(",", I156) + 1) + 1) + 1) + 1) + 1) + 1) + 1) - FIND(",", I156, FIND(",", I156, FIND(",", I156, FIND(",", I156, FIND(",", I156, FIND(",", I156, FIND(",", I156) + 1) + 1) + 1) + 1) + 1) + 1) - 1, LEN(I156)))), "") | Z156: =IFERROR(TRIM(MID(I156, FIND(",", I156, FIND(",", I156, FIND(",", I156, FIND(",", I156, FIND(",", I156, FIND(",", I156, FIND(",", I156, FIND(",", I156, FIND(",", I156) + 1) + 1) + 1) + 1) + 1) + 1) + 1) + 1) + 1, IFERROR(FIND(",", I156, FIND(",", I156, FIND(",", I156, FIND(",", I156, FIND(",", I156, FIND(",", I156, FIND(",", I156, FIND(",", I156, FIND(",", I156) + 1) + 1) + 1) + 1) + 1) + 1) + 1) + 1) - FIND(",", I156, FIND(",", I156, FIND(",", I156, FIND(",", I156, FIND(",", I156, FIND(",", I156, FIND(",", I156, FIND(",", I156) + 1) + 1) + 1) + 1) + 1) + 1) + 1) - 1, LEN(I156)))), "")
A157: 3616400513483FR-W77-19-57065 | B157: 3616400513483 | C157: FR-W77-19-57065 | D157: 10. El Fantasma - La Suerte del Señor ft. Los 2 Carnales | E157: El Fantasma | F157: 43616 | G157: AfinArte | H157: =100%-SUM(CatalogTable[[#This Row],[Artist 1 %]],CatalogTable[[#This Row],[Artist 2 %]],CatalogTable[[#This Row],[Artist 3 %]],CatalogTable[[#This Row],[Artist 4 %]],CatalogTable[[#This Row],[Artist 5 %]],CatalogTable[[#This Row],[Artist 6 %]],CatalogTable[[#This Row],[Artist 7 %]],CatalogTable[[#This Row],[Artist 8 %]],CatalogTable[[#This Row],[Artist 9%]]) -> 0.75 | I157: =IF(ISBLANK(E157),"",INDEX(UniqueArtist!B:B, MATCH(E157,UniqueArtist!A:A, 0))) -> El Fantasma | J157: =IFERROR(TRIM(LEFT(I157, IFERROR(FIND(",", I157)-1, LEN(I157)))), "") -> El Fantasma | K157: 0.25 | L157: =IFERROR(TRIM(MID(I157, FIND(",", I157) + 1, IFERROR(FIND(",", I157, FIND(",", I157) + 1) - FIND(",", I157) - 1, LEN(I157)))), "") | N157: =IFERROR(TRIM(MID(I157, FIND(",", I157, FIND(",", I157) + 1) + 1, IFERROR(FIND(",", I157, FIND(",", I157, FIND(",", I157) + 1) + 1) - FIND(",", I157, FIND(",", I157) + 1) - 1, LEN(I157)))), "") | P157: =IFERROR(TRIM(MID(I157, FIND(",", I157, FIND(",", I157, FIND(",", I157) + 1) + 1) + 1, IFERROR(FIND(",", I157, FIND(",", I157, FIND(",", I157, FIND(",", I157) + 1) + 1) + 1) - FIND(",", I157, FIND(",", I157, FIND(",", I157) + 1) + 1) - 1, LEN(I157)))), "") | R157: =IFERROR(TRIM(MID(I157, FIND(",", I157, FIND(",", I157, FIND(",", I157, FIND(",", I157) + 1) + 1) + 1) + 1, IFERROR(FIND(",", I157, FIND(",", I157, FIND(",", I157, FIND(",", I157, FIND(",", I157) + 1) + 1) + 1) + 1) - FIND(",", I157, FIND(",", I157, FIND(",", I157, FIND(",", I157) + 1) + 1) + 1) - 1, LEN(I157)))), "") | T157: =IFERROR(TRIM(MID(I157, FIND(",", I157, FIND(",", I157, FIND(",", I157, FIND(",", I157, FIND(",", I157, FIND(",", I157) + 1) + 1) + 1) + 1) + 1) + 1, IFERROR(FIND(",", I157, FIND(",", I157, FIND(",", I157, FIND(",", I157, FIND(",", I157, FIND(",", I157) + 1) + 1) + 1) + 1) + 1) - FIND(",", I157, FIND(",", I157, FIND(",", I157, FIND(",", I157, FIND(",", I157) + 1) + 1) + 1) + 1) - 1, LEN(I157)))), "") | V157: =IFERROR(TRIM(MID(I157, FIND(",", I157, FIND(",", I157, FIND(",", I157, FIND(",", I157, FIND(",", I157, FIND(",", I157, FIND(",", I157) + 1) + 1) + 1) + 1) + 1) + 1) + 1, IFERROR(FIND(",", I157, FIND(",", I157, FIND(",", I157, FIND(",", I157, FIND(",", I157, FIND(",", I157, FIND(",", I157) + 1) + 1) + 1) + 1) + 1) + 1) - FIND(",", I157, FIND(",", I157, FIND(",", I157, FIND(",", I157, FIND(",", I157, FIND(",", I157) + 1) + 1) + 1) + 1) + 1) - 1, LEN(I157)))), "") | X157: =IFERROR(TRIM(MID(I157, FIND(",", I157, FIND(",", I157, FIND(",", I157, FIND(",", I157, FIND(",", I157, FIND(",", I157, FIND(",", I157, FIND(",", I157) + 1) + 1) + 1) + 1) + 1) + 1) + 1) + 1, IFERROR(FIND(",", I157, FIND(",", I157, FIND(",", I157, FIND(",", I157, FIND(",", I157, FIND(",", I157, FIND(",", I157, FIND(",", I157) + 1) + 1) + 1) + 1) + 1) + 1) + 1) - FIND(",", I157, FIND(",", I157, FIND(",", I157, FIND(",", I157, FIND(",", I157, FIND(",", I157, FIND(",", I157) + 1) + 1) + 1) + 1) + 1) + 1) - 1, LEN(I157)))), "") | Z157: =IFERROR(TRIM(MID(I157, FIND(",", I157, FIND(",", I157, FIND(",", I157, FIND(",", I157, FIND(",", I157, FIND(",", I157, FIND(",", I157, FIND(",", I157, FIND(",", I157) + 1) + 1) + 1) + 1) + 1) + 1) + 1) + 1) + 1, IFERROR(FIND(",", I157, FIND(",", I157, FIND(",", I157, FIND(",", I157, FIND(",", I157, FIND(",", I157, FIND(",", I157, FIND(",", I157, FIND(",", I157) + 1) + 1) + 1) + 1) + 1) + 1) + 1) + 1) - FIND(",", I157, FIND(",", I157, FIND(",", I157, FIND(",", I157, FIND(",", I157, FIND(",", I157, FIND(",", I157, FIND(",", I157) + 1) + 1) + 1) + 1) + 1) + 1) + 1) - 1, LEN(I157)))), "")
A158: 3617228195226FR-26V-23-71294 | B158: 3617228195226 | C158: FR-26V-23-71294 | D158: 10. La Cumbia Del Viper | E158: Alemi Bustos | G158: AfinArte | H158: =100%-SUM(CatalogTable[[#This Row],[Artist 1 %]],CatalogTable[[#This Row],[Artist 2 %]],CatalogTable[[#This Row],[Artist 3 %]],CatalogTable[[#This Row],[Artist 4 %]],CatalogTable[[#This Row],[Artist 5 %]],CatalogTable[[#This Row],[Artist 6 %]],CatalogTable[[#This Row],[Artist 7 %]],CatalogTable[[#This Row],[Artist 8 %]],CatalogTable[[#This Row],[Artist 9%]]) -> 0.9 | I158: =IF(ISBLANK(E158),"",INDEX(UniqueArtist!B:B, MATCH(E158,UniqueArtist!A:A, 0))) -> Alemi Bustos | J158: =IFERROR(TRIM(LEFT(I158, IFERROR(FIND(",", I158)-1, LEN(I158)))), "") -> Alemi Bustos | K158: 0.1 | L158: =IFERROR(TRIM(MID(I158, FIND(",", I158) + 1, IFERROR(FIND(",", I158, FIND(",", I158) + 1) - FIND(",", I158) - 1, LEN(I158)))), "") | N158: =IFERROR(TRIM(MID(I158, FIND(",", I158, FIND(",", I158) + 1) + 1, IFERROR(FIND(",", I158, FIND(",", I158, FIND(",", I158) + 1) + 1) - FIND(",", I158, FIND(",", I158) + 1) - 1, LEN(I158)))), "") | P158: =IFERROR(TRIM(MID(I158, FIND(",", I158, FIND(",", I158, FIND(",", I158) + 1) + 1) + 1, IFERROR(FIND(",", I158, FIND(",", I158, FIND(",", I158, FIND(",", I158) + 1) + 1) + 1) - FIND(",", I158, FIND(",", I158, FIND(",", I158) + 1) + 1) - 1, LEN(I158)))), "") | R158: =IFERROR(TRIM(MID(I158, FIND(",", I158, FIND(",", I158, FIND(",", I158, FIND(",", I158) + 1) + 1) + 1) + 1, IFERROR(FIND(",", I158, FIND(",", I158, FIND(",", I158, FIND(",", I158, FIND(",", I158) + 1) + 1) + 1) + 1) - FIND(",", I158, FIND(",", I158, FIND(",", I158, FIND(",", I158) + 1) + 1) + 1) - 1, LEN(I158)))), "") | T158: =IFERROR(TRIM(MID(I158, FIND(",", I158, FIND(",", I158, FIND(",", I158, FIND(",", I158, FIND(",", I158, FIND(",", I158) + 1) + 1) + 1) + 1) + 1) + 1, IFERROR(FIND(",", I158, FIND(",", I158, FIND(",", I158, FIND(",", I158, FIND(",", I158, FIND(",", I158) + 1) + 1) + 1) + 1) + 1) - FIND(",", I158, FIND(",", I158, FIND(",", I158, FIND(",", I158, FIND(",", I158) + 1) + 1) + 1) + 1) - 1, LEN(I158)))), "") | V158: =IFERROR(TRIM(MID(I158, FIND(",", I158, FIND(",", I158, FIND(",", I158, FIND(",", I158, FIND(",", I158, FIND(",", I158, FIND(",", I158) + 1) + 1) + 1) + 1) + 1) + 1) + 1, IFERROR(FIND(",", I158, FIND(",", I158, FIND(",", I158, FIND(",", I158, FIND(",", I158, FIND(",", I158, FIND(",", I158) + 1) + 1) + 1) + 1) + 1) + 1) - FIND(",", I158, FIND(",", I158, FIND(",", I158, FIND(",", I158, FIND(",", I158, FIND(",", I158) + 1) + 1) + 1) + 1) + 1) - 1, LEN(I158)))), "") | X158: =IFERROR(TRIM(MID(I158, FIND(",", I158, FIND(",", I158, FIND(",", I158, FIND(",", I158, FIND(",", I158, FIND(",", I158, FIND(",", I158, FIND(",", I158) + 1) + 1) + 1) + 1) + 1) + 1) + 1) + 1, IFERROR(FIND(",", I158, FIND(",", I158, FIND(",", I158, FIND(",", I158, FIND(",", I158, FIND(",", I158, FIND(",", I158, FIND(",", I158) + 1) + 1) + 1) + 1) + 1) + 1) + 1) - FIND(",", I158, FIND(",", I158, FIND(",", I158, FIND(",", I158, FIND(",", I158, FIND(",", I158, FIND(",", I158) + 1) + 1) + 1) + 1) + 1) + 1) - 1, LEN(I158)))), "") | Z158: =IFERROR(TRIM(MID(I158, FIND(",", I158, FIND(",", I158, FIND(",", I158, FIND(",", I158, FIND(",", I158, FIND(",", I158, FIND(",", I158, FIND(",", I158, FIND(",", I158) + 1) + 1) + 1) + 1) + 1) + 1) + 1) + 1) + 1, IFERROR(FIND(",", I158, FIND(",", I158, FIND(",", I158, FIND(",", I158, FIND(",", I158, FIND(",", I158, FIND(",", I158, FIND(",", I158, FIND(",", I158) + 1) + 1) + 1) + 1) + 1) + 1) + 1) + 1) - FIND(",", I158, FIND(",", I158, FIND(",", I158, FIND(",", I158, FIND(",", I158, FIND(",", I158, FIND(",", I158, FIND(",", I158) + 1) + 1) + 1) + 1) + 1) + 1) + 1) - 1, LEN(I158)))), "")
A159: 3617226961830FR-26V-23-26105 | B159: 3617226961830 | C159: FR-26V-23-26105 | D159: 10.- Los Dos Carnales - Ti Todo Lo Doy (Visualizer) | E159: Los Dos Carnales | G159: AfinArte | H159: =100%-SUM(CatalogTable[[#This Row],[Artist 1 %]],CatalogTable[[#This Row],[Artist 2 %]],CatalogTable[[#This Row],[Artist 3 %]],CatalogTable[[#This Row],[Artist 4 %]],CatalogTable[[#This Row],[Artist 5 %]],CatalogTable[[#This Row],[Artist 6 %]],CatalogTable[[#This Row],[Artist 7 %]],CatalogTable[[#This Row],[Artist 8 %]],CatalogTable[[#This Row],[Artist 9%]]) -> 0.9 | I159: =IF(ISBLANK(E159),"",INDEX(UniqueArtist!B:B, MATCH(E159,UniqueArtist!A:A, 0))) -> Los Dos Carnales | J159: =IFERROR(TRIM(LEFT(I159, IFERROR(FIND(",", I159)-1, LEN(I159)))), "") -> Los Dos Carnales | K159: 0.1 | L159: =IFERROR(TRIM(MID(I159, FIND(",", I159) + 1, IFERROR(FIND(",", I159, FIND(",", I159) + 1) - FIND(",", I159) - 1, LEN(I159)))), "") | N159: =IFERROR(TRIM(MID(I159, FIND(",", I159, FIND(",", I159) + 1) + 1, IFERROR(FIND(",", I159, FIND(",", I159, FIND(",", I159) + 1) + 1) - FIND(",", I159, FIND(",", I159) + 1) - 1, LEN(I159)))), "") | P159: =IFERROR(TRIM(MID(I159, FIND(",", I159, FIND(",", I159, FIND(",", I159) + 1) + 1) + 1, IFERROR(FIND(",", I159, FIND(",", I159, FIND(",", I159, FIND(",", I159) + 1) + 1) + 1) - FIND(",", I159, FIND(",", I159, FIND(",", I159) + 1) + 1) - 1, LEN(I159)))), "") | R159: =IFERROR(TRIM(MID(I159, FIND(",", I159, FIND(",", I159, FIND(",", I159, FIND(",", I159) + 1) + 1) + 1) + 1, IFERROR(FIND(",", I159, FIND(",", I159, FIND(",", I159, FIND(",", I159, FIND(",", I159) + 1) + 1) + 1) + 1) - FIND(",", I159, FIND(",", I159, FIND(",", I159, FIND(",", I159) + 1) + 1) + 1) - 1, LEN(I159)))), "") | T159: =IFERROR(TRIM(MID(I159, FIND(",", I159, FIND(",", I159, FIND(",", I159, FIND(",", I159, FIND(",", I159, FIND(",", I159) + 1) + 1) + 1) + 1) + 1) + 1, IFERROR(FIND(",", I159, FIND(",", I159, FIND(",", I159, FIND(",", I159, FIND(",", I159, FIND(",", I159) + 1) + 1) + 1) + 1) + 1) - FIND(",", I159, FIND(",", I159, FIND(",", I159, FIND(",", I159, FIND(",", I159) + 1) + 1) + 1) + 1) - 1, LEN(I159)))), "") | V159: =IFERROR(TRIM(MID(I159, FIND(",", I159, FIND(",", I159, FIND(",", I159, FIND(",", I159, FIND(",", I159, FIND(",", I159, FIND(",", I159) + 1) + 1) + 1) + 1) + 1) + 1) + 1, IFERROR(FIND(",", I159, FIND(",", I159, FIND(",", I159, FIND(",", I159, FIND(",", I159, FIND(",", I159, FIND(",", I159) + 1) + 1) + 1) + 1) + 1) + 1) - FIND(",", I159, FIND(",", I159, FIND(",", I159, FIND(",", I159, FIND(",", I159, FIND(",", I159) + 1) + 1) + 1) + 1) + 1) - 1, LEN(I159)))), "") | X159: =IFERROR(TRIM(MID(I159, FIND(",", I159, FIND(",", I159, FIND(",", I159, FIND(",", I159, FIND(",", I159, FIND(",", I159, FIND(",", I159, FIND(",", I159) + 1) + 1) + 1) + 1) + 1) + 1) + 1) + 1, IFERROR(FIND(",", I159, FIND(",", I159, FIND(",", I159, FIND(",", I159, FIND(",", I159, FIND(",", I159, FIND(",", I159, FIND(",", I159) + 1) + 1) + 1) + 1) + 1) + 1) + 1) - FIND(",", I159, FIND(",", I159, FIND(",", I159, FIND(",", I159, FIND(",", I159, FIND(",", I159, FIND(",", I159) + 1) + 1) + 1) + 1) + 1) + 1) - 1, LEN(I159)))), "") | Z159: =IFERROR(TRIM(MID(I159, FIND(",", I159, FIND(",", I159, FIND(",", I159, FIND(",", I159, FIND(",", I159, FIND(",", I159, FIND(",", I159, FIND(",", I159, FIND(",", I159) + 1) + 1) + 1) + 1) + 1) + 1) + 1) + 1) + 1, IFERROR(FIND(",", I159, FIND(",", I159, FIND(",", I159, FIND(",", I159, FIND(",", I159, FIND(",", I159, FIND(",", I159, FIND(",", I159, FIND(",", I159) + 1) + 1) + 1) + 1) + 1) + 1) + 1) + 1) - FIND(",", I159, FIND(",", I159, FIND(",", I159, FIND(",", I159, FIND(",", I159, FIND(",", I159, FIND(",", I159, FIND(",", I159) + 1) + 1) + 1) + 1) + 1) + 1) + 1) - 1, LEN(I159)))), "")
A160: 3617228185159FR-26V-23-70943 | B160: 3617228185159 | C160: FR-26V-23-70943 | D160: 10.- MI ORGULLO | E160: Alemi Bustos | G160: AfinArte | H160: =100%-SUM(CatalogTable[[#This Row],[Artist 1 %]],CatalogTable[[#This Row],[Artist 2 %]],CatalogTable[[#This Row],[Artist 3 %]],CatalogTable[[#This Row],[Artist 4 %]],CatalogTable[[#This Row],[Artist 5 %]],CatalogTable[[#This Row],[Artist 6 %]],CatalogTable[[#This Row],[Artist 7 %]],CatalogTable[[#This Row],[Artist 8 %]],CatalogTable[[#This Row],[Artist 9%]]) -> 0.9 | I160: =IF(ISBLANK(E160),"",INDEX(UniqueArtist!B:B, MATCH(E160,UniqueArtist!A:A, 0))) -> Alemi Bustos | J160: =IFERROR(TRIM(LEFT(I160, IFERROR(FIND(",", I160)-1, LEN(I160)))), "") -> Alemi Bustos | K160: 0.1 | L160: =IFERROR(TRIM(MID(I160, FIND(",", I160) + 1, IFERROR(FIND(",", I160, FIND(",", I160) + 1) - FIND(",", I160) - 1, LEN(I160)))), "") | N160: =IFERROR(TRIM(MID(I160, FIND(",", I160, FIND(",", I160) + 1) + 1, IFERROR(FIND(",", I160, FIND(",", I160, FIND(",", I160) + 1) + 1) - FIND(",", I160, FIND(",", I160) + 1) - 1, LEN(I160)))), "") | P160: =IFERROR(TRIM(MID(I160, FIND(",", I160, FIND(",", I160, FIND(",", I160) + 1) + 1) + 1, IFERROR(FIND(",", I160, FIND(",", I160, FIND(",", I160, FIND(",", I160) + 1) + 1) + 1) - FIND(",", I160, FIND(",", I160, FIND(",", I160) + 1) + 1) - 1, LEN(I160)))), "") | R160: =IFERROR(TRIM(MID(I160, FIND(",", I160, FIND(",", I160, FIND(",", I160, FIND(",", I160) + 1) + 1) + 1) + 1, IFERROR(FIND(",", I160, FIND(",", I160, FIND(",", I160, FIND(",", I160, FIND(",", I160) + 1) + 1) + 1) + 1) - FIND(",", I160, FIND(",", I160, FIND(",", I160, FIND(",", I160) + 1) + 1) + 1) - 1, LEN(I160)))), "") | T160: =IFERROR(TRIM(MID(I160, FIND(",", I160, FIND(",", I160, FIND(",", I160, FIND(",", I160, FIND(",", I160, FIND(",", I160) + 1) + 1) + 1) + 1) + 1) + 1, IFERROR(FIND(",", I160, FIND(",", I160, FIND(",", I160, FIND(",", I160, FIND(",", I160, FIND(",", I160) + 1) + 1) + 1) + 1) + 1) - FIND(",", I160, FIND(",", I160, FIND(",", I160, FIND(",", I160, FIND(",", I160) + 1) + 1) + 1) + 1) - 1, LEN(I160)))), "") | V160: =IFERROR(TRIM(MID(I160, FIND(",", I160, FIND(",", I160, FIND(",", I160, FIND(",", I160, FIND(",", I160, FIND(",", I160, FIND(",", I160) + 1) + 1) + 1) + 1) + 1) + 1) + 1, IFERROR(FIND(",", I160, FIND(",", I160, FIND(",", I160, FIND(",", I160, FIND(",", I160, FIND(",", I160, FIND(",", I160) + 1) + 1) + 1) + 1) + 1) + 1) - FIND(",", I160, FIND(",", I160, FIND(",", I160, FIND(",", I160, FIND(",", I160, FIND(",", I160) + 1) + 1) + 1) + 1) + 1) - 1, LEN(I160)))), "") | X160: =IFERROR(TRIM(MID(I160, FIND(",", I160, FIND(",", I160, FIND(",", I160, FIND(",", I160, FIND(",", I160, FIND(",", I160, FIND(",", I160, FIND(",", I160) + 1) + 1) + 1) + 1) + 1) + 1) + 1) + 1, IFERROR(FIND(",", I160, FIND(",", I160, FIND(",", I160, FIND(",", I160, FIND(",", I160, FIND(",", I160, FIND(",", I160, FIND(",", I160) + 1) + 1) + 1) + 1) + 1) + 1) + 1) - FIND(",", I160, FIND(",", I160, FIND(",", I160, FIND(",", I160, FIND(",", I160, FIND(",", I160, FIND(",", I160) + 1) + 1) + 1) + 1) + 1) + 1) - 1, LEN(I160)))), "") | Z160: =IFERROR(TRIM(MID(I160, FIND(",", I160, FIND(",", I160, FIND(",", I160, FIND(",", I160, FIND(",", I160, FIND(",", I160, FIND(",", I160, FIND(",", I160, FIND(",", I160) + 1) + 1) + 1) + 1) + 1) + 1) + 1) + 1) + 1, IFERROR(FIND(",", I160, FIND(",", I160, FIND(",", I160, FIND(",", I160, FIND(",", I160, FIND(",", I160, FIND(",", I160, FIND(",", I160, FIND(",", I160) + 1) + 1) + 1) + 1) + 1) + 1) + 1) + 1) - FIND(",", I160, FIND(",", I160, FIND(",", I160, FIND(",", I160, FIND(",", I160, FIND(",", I160, FIND(",", I160, FIND(",", I160) + 1) + 1) + 1) + 1) + 1) + 1) + 1) - 1, LEN(I160)))), "")
A161: 3617226299766DG-A07-23-81559 | B161: 3617226299766 | C161: DG-A07-23-81559 | D161: 100pre | E161: Los Dos Carnales | G161: AfinArte | H161: =100%-SUM(CatalogTable[[#This Row],[Artist 1 %]],CatalogTable[[#This Row],[Artist 2 %]],CatalogTable[[#This Row],[Artist 3 %]],CatalogTable[[#This Row],[Artist 4 %]],CatalogTable[[#This Row],[Artist 5 %]],CatalogTable[[#This Row],[Artist 6 %]],CatalogTable[[#This Row],[Artist 7 %]],CatalogTable[[#This Row],[Artist 8 %]],CatalogTable[[#This Row],[Artist 9%]]) -> 0.9 | I161: =IF(ISBLANK(E161),"",INDEX(UniqueArtist!B:B, MATCH(E161,UniqueArtist!A:A, 0))) -> Los Dos Carnales | J161: =IFERROR(TRIM(LEFT(I161, IFERROR(FIND(",", I161)-1, LEN(I161)))), "") -> Los Dos Carnales | K161: 0.1 | L161: =IFERROR(TRIM(MID(I161, FIND(",", I161) + 1, IFERROR(FIND(",", I161, FIND(",", I161) + 1) - FIND(",", I161) - 1, LEN(I161)))), "") | N161: =IFERROR(TRIM(MID(I161, FIND(",", I161, FIND(",", I161) + 1) + 1, IFERROR(FIND(",", I161, FIND(",", I161, FIND(",", I161) + 1) + 1) - FIND(",", I161, FIND(",", I161) + 1) - 1, LEN(I161)))), "") | P161: =IFERROR(TRIM(MID(I161, FIND(",", I161, FIND(",", I161, FIND(",", I161) + 1) + 1) + 1, IFERROR(FIND(",", I161, FIND(",", I161, FIND(",", I161, FIND(",", I161) + 1) + 1) + 1) - FIND(",", I161, FIND(",", I161, FIND(",", I161) + 1) + 1) - 1, LEN(I161)))), "") | R161: =IFERROR(TRIM(MID(I161, FIND(",", I161, FIND(",", I161, FIND(",", I161, FIND(",", I161) + 1) + 1) + 1) + 1, IFERROR(FIND(",", I161, FIND(",", I161, FIND(",", I161, FIND(",", I161, FIND(",", I161) + 1) + 1) + 1) + 1) - FIND(",", I161, FIND(",", I161, FIND(",", I161, FIND(",", I161) + 1) + 1) + 1) - 1, LEN(I161)))), "") | T161: =IFERROR(TRIM(MID(I161, FIND(",", I161, FIND(",", I161, FIND(",", I161, FIND(",", I161, FIND(",", I161, FIND(",", I161) + 1) + 1) + 1) + 1) + 1) + 1, IFERROR(FIND(",", I161, FIND(",", I161, FIND(",", I161, FIND(",", I161, FIND(",", I161, FIND(",", I161) + 1) + 1) + 1) + 1) + 1) - FIND(",", I161, FIND(",", I161, FIND(",", I161, FIND(",", I161, FIND(",", I161) + 1) + 1) + 1) + 1) - 1, LEN(I161)))), "") | V161: =IFERROR(TRIM(MID(I161, FIND(",", I161, FIND(",", I161, FIND(",", I161, FIND(",", I161, FIND(",", I161, FIND(",", I161, FIND(",", I161) + 1) + 1) + 1) + 1) + 1) + 1) + 1, IFERROR(FIND(",", I161, FIND(",", I161, FIND(",", I161, FIND(",", I161, FIND(",", I161, FIND(",", I161, FIND(",", I161) + 1) + 1) + 1) + 1) + 1) + 1) - FIND(",", I161, FIND(",", I161, FIND(",", I161, FIND(",", I161, FIND(",", I161, FIND(",", I161) + 1) + 1) + 1) + 1) + 1) - 1, LEN(I161)))), "") | X161: =IFERROR(TRIM(MID(I161, FIND(",", I161, FIND(",", I161, FIND(",", I161, FIND(",", I161, FIND(",", I161, FIND(",", I161, FIND(",", I161, FIND(",", I161) + 1) + 1) + 1) + 1) + 1) + 1) + 1) + 1, IFERROR(FIND(",", I161, FIND(",", I161, FIND(",", I161, FIND(",", I161, FIND(",", I161, FIND(",", I161, FIND(",", I161, FIND(",", I161) + 1) + 1) + 1) + 1) + 1) + 1) + 1) - FIND(",", I161, FIND(",", I161, FIND(",", I161, FIND(",", I161, FIND(",", I161, FIND(",", I161, FIND(",", I161) + 1) + 1) + 1) + 1) + 1) + 1) - 1, LEN(I161)))), "") | Z161: =IFERROR(TRIM(MID(I161, FIND(",", I161, FIND(",", I161, FIND(",", I161, FIND(",", I161, FIND(",", I161, FIND(",", I161, FIND(",", I161, FIND(",", I161, FIND(",", I161) + 1) + 1) + 1) + 1) + 1) + 1) + 1) + 1) + 1, IFERROR(FIND(",", I161, FIND(",", I161, FIND(",", I161, FIND(",", I161, FIND(",", I161, FIND(",", I161, FIND(",", I161, FIND(",", I161, FIND(",", I161) + 1) + 1) + 1) + 1) + 1) + 1) + 1) + 1) - FIND(",", I161, FIND(",", I161, FIND(",", I161, FIND(",", I161, FIND(",", I161, FIND(",", I161, FIND(",", I161, FIND(",", I161) + 1) + 1) + 1) + 1) + 1) + 1) + 1) - 1, LEN(I161)))), "")
A162: 3617226584534DG-A07-23-81559 | B162: 3617226584534 | C162: DG-A07-23-81559 | D162: 100pre | E162: Los Dos Carnales | G162: AfinArte | H162: =100%-SUM(CatalogTable[[#This Row],[Artist 1 %]],CatalogTable[[#This Row],[Artist 2 %]],CatalogTable[[#This Row],[Artist 3 %]],CatalogTable[[#This Row],[Artist 4 %]],CatalogTable[[#This Row],[Artist 5 %]],CatalogTable[[#This Row],[Artist 6 %]],CatalogTable[[#This Row],[Artist 7 %]],CatalogTable[[#This Row],[Artist 8 %]],CatalogTable[[#This Row],[Artist 9%]]) -> 0.9 | I162: =IF(ISBLANK(E162),"",INDEX(UniqueArtist!B:B, MATCH(E162,UniqueArtist!A:A, 0))) -> Los Dos Carnales | J162: =IFERROR(TRIM(LEFT(I162, IFERROR(FIND(",", I162)-1, LEN(I162)))), "") -> Los Dos Carnales | K162: 0.1 | L162: =IFERROR(TRIM(MID(I162, FIND(",", I162) + 1, IFERROR(FIND(",", I162, FIND(",", I162) + 1) - FIND(",", I162) - 1, LEN(I162)))), "") | N162: =IFERROR(TRIM(MID(I162, FIND(",", I162, FIND(",", I162) + 1) + 1, IFERROR(FIND(",", I162, FIND(",", I162, FIND(",", I162) + 1) + 1) - FIND(",", I162, FIND(",", I162) + 1) - 1, LEN(I162)))), "") | P162: =IFERROR(TRIM(MID(I162, FIND(",", I162, FIND(",", I162, FIND(",", I162) + 1) + 1) + 1, IFERROR(FIND(",", I162, FIND(",", I162, FIND(",", I162, FIND(",", I162) + 1) + 1) + 1) - FIND(",", I162, FIND(",", I162, FIND(",", I162) + 1) + 1) - 1, LEN(I162)))), "") | R162: =IFERROR(TRIM(MID(I162, FIND(",", I162, FIND(",", I162, FIND(",", I162, FIND(",", I162) + 1) + 1) + 1) + 1, IFERROR(FIND(",", I162, FIND(",", I162, FIND(",", I162, FIND(",", I162, FIND(",", I162) + 1) + 1) + 1) + 1) - FIND(",", I162, FIND(",", I162, FIND(",", I162, FIND(",", I162) + 1) + 1) + 1) - 1, LEN(I162)))), "") | T162: =IFERROR(TRIM(MID(I162, FIND(",", I162, FIND(",", I162, FIND(",", I162, FIND(",", I162, FIND(",", I162, FIND(",", I162) + 1) + 1) + 1) + 1) + 1) + 1, IFERROR(FIND(",", I162, FIND(",", I162, FIND(",", I162, FIND(",", I162, FIND(",", I162, FIND(",", I162) + 1) + 1) + 1) + 1) + 1) - FIND(",", I162, FIND(",", I162, FIND(",", I162, FIND(",", I162, FIND(",", I162) + 1) + 1) + 1) + 1) - 1, LEN(I162)))), "") | V162: =IFERROR(TRIM(MID(I162, FIND(",", I162, FIND(",", I162, FIND(",", I162, FIND(",", I162, FIND(",", I162, FIND(",", I162, FIND(",", I162) + 1) + 1) + 1) + 1) + 1) + 1) + 1, IFERROR(FIND(",", I162, FIND(",", I162, FIND(",", I162, FIND(",", I162, FIND(",", I162, FIND(",", I162, FIND(",", I162) + 1) + 1) + 1) + 1) + 1) + 1) - FIND(",", I162, FIND(",", I162, FIND(",", I162, FIND(",", I162, FIND(",", I162, FIND(",", I162) + 1) + 1) + 1) + 1) + 1) - 1, LEN(I162)))), "") | X162: =IFERROR(TRIM(MID(I162, FIND(",", I162, FIND(",", I162, FIND(",", I162, FIND(",", I162, FIND(",", I162, FIND(",", I162, FIND(",", I162, FIND(",", I162) + 1) + 1) + 1) + 1) + 1) + 1) + 1) + 1, IFERROR(FIND(",", I162, FIND(",", I162, FIND(",", I162, FIND(",", I162, FIND(",", I162, FIND(",", I162, FIND(",", I162, FIND(",", I162) + 1) + 1) + 1) + 1) + 1) + 1) + 1) - FIND(",", I162, FIND(",", I162, FIND(",", I162, FIND(",", I162, FIND(",", I162, FIND(",", I162, FIND(",", I162) + 1) + 1) + 1) + 1) + 1) + 1) - 1, LEN(I162)))), "") | Z162: =IFERROR(TRIM(MID(I162, FIND(",", I162, FIND(",", I162, FIND(",", I162, FIND(",", I162, FIND(",", I162, FIND(",", I162, FIND(",", I162, FIND(",", I162, FIND(",", I162) + 1) + 1) + 1) + 1) + 1) + 1) + 1) + 1) + 1, IFERROR(FIND(",", I162, FIND(",", I162, FIND(",", I162, FIND(",", I162, FIND(",", I162, FIND(",", I162, FIND(",", I162, FIND(",", I162, FIND(",", I162) + 1) + 1) + 1) + 1) + 1) + 1) + 1) + 1) - FIND(",", I162, FIND(",", I162, FIND(",", I162, FIND(",", I162, FIND(",", I162, FIND(",", I162, FIND(",", I162, FIND(",", I162) + 1) + 1) + 1) + 1) + 1) + 1) + 1) - 1, LEN(I162)))), "")
A163: 3617226780882FR-26V-23-18528 | B163: 3617226780882 | C163: FR-26V-23-18528 | D163: 100PRE | E163: Los Dos Carnales | G163: AfinArte | H163: =100%-SUM(CatalogTable[[#This Row],[Artist 1 %]],CatalogTable[[#This Row],[Artist 2 %]],CatalogTable[[#This Row],[Artist 3 %]],CatalogTable[[#This Row],[Artist 4 %]],CatalogTable[[#This Row],[Artist 5 %]],CatalogTable[[#This Row],[Artist 6 %]],CatalogTable[[#This Row],[Artist 7 %]],CatalogTable[[#This Row],[Artist 8 %]],CatalogTable[[#This Row],[Artist 9%]]) -> 0.9 | I163: =IF(ISBLANK(E163),"",INDEX(UniqueArtist!B:B, MATCH(E163,UniqueArtist!A:A, 0))) -> Los Dos Carnales | J163: =IFERROR(TRIM(LEFT(I163, IFERROR(FIND(",", I163)-1, LEN(I163)))), "") -> Los Dos Carnales | K163: 0.1 | L163: =IFERROR(TRIM(MID(I163, FIND(",", I163) + 1, IFERROR(FIND(",", I163, FIND(",", I163) + 1) - FIND(",", I163) - 1, LEN(I163)))), "") | N163: =IFERROR(TRIM(MID(I163, FIND(",", I163, FIND(",", I163) + 1) + 1, IFERROR(FIND(",", I163, FIND(",", I163, FIND(",", I163) + 1) + 1) - FIND(",", I163, FIND(",", I163) + 1) - 1, LEN(I163)))), "") | P163: =IFERROR(TRIM(MID(I163, FIND(",", I163, FIND(",", I163, FIND(",", I163) + 1) + 1) + 1, IFERROR(FIND(",", I163, FIND(",", I163, FIND(",", I163, FIND(",", I163) + 1) + 1) + 1) - FIND(",", I163, FIND(",", I163, FIND(",", I163) + 1) + 1) - 1, LEN(I163)))), "") | R163: =IFERROR(TRIM(MID(I163, FIND(",", I163, FIND(",", I163, FIND(",", I163, FIND(",", I163) + 1) + 1) + 1) + 1, IFERROR(FIND(",", I163, FIND(",", I163, FIND(",", I163, FIND(",", I163, FIND(",", I163) + 1) + 1) + 1) + 1) - FIND(",", I163, FIND(",", I163, FIND(",", I163, FIND(",", I163) + 1) + 1) + 1) - 1, LEN(I163)))), "") | T163: =IFERROR(TRIM(MID(I163, FIND(",", I163, FIND(",", I163, FIND(",", I163, FIND(",", I163, FIND(",", I163, FIND(",", I163) + 1) + 1) + 1) + 1) + 1) + 1, IFERROR(FIND(",", I163, FIND(",", I163, FIND(",", I163, FIND(",", I163, FIND(",", I163, FIND(",", I163) + 1) + 1) + 1) + 1) + 1) - FIND(",", I163, FIND(",", I163, FIND(",", I163, FIND(",", I163, FIND(",", I163) + 1) + 1) + 1) + 1) - 1, LEN(I163)))), "") | V163: =IFERROR(TRIM(MID(I163, FIND(",", I163, FIND(",", I163, FIND(",", I163, FIND(",", I163, FIND(",", I163, FIND(",", I163, FIND(",", I163) + 1) + 1) + 1) + 1) + 1) + 1) + 1, IFERROR(FIND(",", I163, FIND(",", I163, FIND(",", I163, FIND(",", I163, FIND(",", I163, FIND(",", I163, FIND(",", I163) + 1) + 1) + 1) + 1) + 1) + 1) - FIND(",", I163, FIND(",", I163, FIND(",", I163, FIND(",", I163, FIND(",", I163, FIND(",", I163) + 1) + 1) + 1) + 1) + 1) - 1, LEN(I163)))), "") | X163: =IFERROR(TRIM(MID(I163, FIND(",", I163, FIND(",", I163, FIND(",", I163, FIND(",", I163, FIND(",", I163, FIND(",", I163, FIND(",", I163, FIND(",", I163) + 1) + 1) + 1) + 1) + 1) + 1) + 1) + 1, IFERROR(FIND(",", I163, FIND(",", I163, FIND(",", I163, FIND(",", I163, FIND(",", I163, FIND(",", I163, FIND(",", I163, FIND(",", I163) + 1) + 1) + 1) + 1) + 1) + 1) + 1) - FIND(",", I163, FIND(",", I163, FIND(",", I163, FIND(",", I163, FIND(",", I163, FIND(",", I163, FIND(",", I163) + 1) + 1) + 1) + 1) + 1) + 1) - 1, LEN(I163)))), "") | Z163: =IFERROR(TRIM(MID(I163, FIND(",", I163, FIND(",", I163, FIND(",", I163, FIND(",", I163, FIND(",", I163, FIND(",", I163, FIND(",", I163, FIND(",", I163, FIND(",", I163) + 1) + 1) + 1) + 1) + 1) + 1) + 1) + 1) + 1, IFERROR(FIND(",", I163, FIND(",", I163, FIND(",", I163, FIND(",", I163, FIND(",", I163, FIND(",", I163, FIND(",", I163, FIND(",", I163, FIND(",", I163) + 1) + 1) + 1) + 1) + 1) + 1) + 1) + 1) - FIND(",", I163, FIND(",", I163, FIND(",", I163, FIND(",", I163, FIND(",", I163, FIND(",", I163, FIND(",", I163, FIND(",", I163) + 1) + 1) + 1) + 1) + 1) + 1) + 1) - 1, LEN(I163)))), "")
A164: 3617227197917FR-26V-23-32580 | B164: 3617227197917 | C164: FR-26V-23-32580 | D164: 100PRE (Letra Oficial) | E164: Los Dos Carnales | G164: AfinArte | H164: =100%-SUM(CatalogTable[[#This Row],[Artist 1 %]],CatalogTable[[#This Row],[Artist 2 %]],CatalogTable[[#This Row],[Artist 3 %]],CatalogTable[[#This Row],[Artist 4 %]],CatalogTable[[#This Row],[Artist 5 %]],CatalogTable[[#This Row],[Artist 6 %]],CatalogTable[[#This Row],[Artist 7 %]],CatalogTable[[#This Row],[Artist 8 %]],CatalogTable[[#This Row],[Artist 9%]]) -> 0.9 | I164: =IF(ISBLANK(E164),"",INDEX(UniqueArtist!B:B, MATCH(E164,UniqueArtist!A:A, 0))) -> Los Dos Carnales | J164: =IFERROR(TRIM(LEFT(I164, IFERROR(FIND(",", I164)-1, LEN(I164)))), "") -> Los Dos Carnales | K164: 0.1 | L164: =IFERROR(TRIM(MID(I164, FIND(",", I164) + 1, IFERROR(FIND(",", I164, FIND(",", I164) + 1) - FIND(",", I164) - 1, LEN(I164)))), "") | N164: =IFERROR(TRIM(MID(I164, FIND(",", I164, FIND(",", I164) + 1) + 1, IFERROR(FIND(",", I164, FIND(",", I164, FIND(",", I164) + 1) + 1) - FIND(",", I164, FIND(",", I164) + 1) - 1, LEN(I164)))), "") | P164: =IFERROR(TRIM(MID(I164, FIND(",", I164, FIND(",", I164, FIND(",", I164) + 1) + 1) + 1, IFERROR(FIND(",", I164, FIND(",", I164, FIND(",", I164, FIND(",", I164) + 1) + 1) + 1) - FIND(",", I164, FIND(",", I164, FIND(",", I164) + 1) + 1) - 1, LEN(I164)))), "") | R164: =IFERROR(TRIM(MID(I164, FIND(",", I164, FIND(",", I164, FIND(",", I164, FIND(",", I164) + 1) + 1) + 1) + 1, IFERROR(FIND(",", I164, FIND(",", I164, FIND(",", I164, FIND(",", I164, FIND(",", I164) + 1) + 1) + 1) + 1) - FIND(",", I164, FIND(",", I164, FIND(",", I164, FIND(",", I164) + 1) + 1) + 1) - 1, LEN(I164)))), "") | T164: =IFERROR(TRIM(MID(I164, FIND(",", I164, FIND(",", I164, FIND(",", I164, FIND(",", I164, FIND(",", I164, FIND(",", I164) + 1) + 1) + 1) + 1) + 1) + 1, IFERROR(FIND(",", I164, FIND(",", I164, FIND(",", I164, FIND(",", I164, FIND(",", I164, FIND(",", I164) + 1) + 1) + 1) + 1) + 1) - FIND(",", I164, FIND(",", I164, FIND(",", I164, FIND(",", I164, FIND(",", I164) + 1) + 1) + 1) + 1) - 1, LEN(I164)))), "") | V164: =IFERROR(TRIM(MID(I164, FIND(",", I164, FIND(",", I164, FIND(",", I164, FIND(",", I164, FIND(",", I164, FIND(",", I164, FIND(",", I164) + 1) + 1) + 1) + 1) + 1) + 1) + 1, IFERROR(FIND(",", I164, FIND(",", I164, FIND(",", I164, FIND(",", I164, FIND(",", I164, FIND(",", I164, FIND(",", I164) + 1) + 1) + 1) + 1) + 1) + 1) - FIND(",", I164, FIND(",", I164, FIND(",", I164, FIND(",", I164, FIND(",", I164, FIND(",", I164) + 1) + 1) + 1) + 1) + 1) - 1, LEN(I164)))), "") | X164: =IFERROR(TRIM(MID(I164, FIND(",", I164, FIND(",", I164, FIND(",", I164, FIND(",", I164, FIND(",", I164, FIND(",", I164, FIND(",", I164, FIND(",", I164) + 1) + 1) + 1) + 1) + 1) + 1) + 1) + 1, IFERROR(FIND(",", I164, FIND(",", I164, FIND(",", I164, FIND(",", I164, FIND(",", I164, FIND(",", I164, FIND(",", I164, FIND(",", I164) + 1) + 1) + 1) + 1) + 1) + 1) + 1) - FIND(",", I164, FIND(",", I164, FIND(",", I164, FIND(",", I164, FIND(",", I164, FIND(",", I164, FIND(",", I164) + 1) + 1) + 1) + 1) + 1) + 1) - 1, LEN(I164)))), "") | Z164: =IFERROR(TRIM(MID(I164, FIND(",", I164, FIND(",", I164, FIND(",", I164, FIND(",", I164, FIND(",", I164, FIND(",", I164, FIND(",", I164, FIND(",", I164, FIND(",", I164) + 1) + 1) + 1) + 1) + 1) + 1) + 1) + 1) + 1, IFERROR(FIND(",", I164, FIND(",", I164, FIND(",", I164, FIND(",", I164, FIND(",", I164, FIND(",", I164, FIND(",", I164, FIND(",", I164, FIND(",", I164) + 1) + 1) + 1) + 1) + 1) + 1) + 1) + 1) - FIND(",", I164, FIND(",", I164, FIND(",", I164, FIND(",", I164, FIND(",", I164, FIND(",", I164, FIND(",", I164, FIND(",", I164) + 1) + 1) + 1) + 1) + 1) + 1) + 1) - 1, LEN(I164)))), "")
A165: 3615936953619FR-W24-19-19982 | B165: 3615936953619 | C165: FR-W24-19-19982 | D165: 11 Mentiras - Voz de Mando 2018 | E165: Voz De Mando | G165: AfinArte | H165: =100%-SUM(CatalogTable[[#This Row],[Artist 1 %]],CatalogTable[[#This Row],[Artist 2 %]],CatalogTable[[#This Row],[Artist 3 %]],CatalogTable[[#This Row],[Artist 4 %]],CatalogTable[[#This Row],[Artist 5 %]],CatalogTable[[#This Row],[Artist 6 %]],CatalogTable[[#This Row],[Artist 7 %]],CatalogTable[[#This Row],[Artist 8 %]],CatalogTable[[#This Row],[Artist 9%]]) -> 0 | I165: =IF(ISBLANK(E165),"",INDEX(UniqueArtist!B:B, MATCH(E165,UniqueArtist!A:A, 0))) -> Voz de Mando | J165: =IFERROR(TRIM(LEFT(I165, IFERROR(FIND(",", I165)-1, LEN(I165)))), "") -> Voz de Mando | K165: 1 | L165: =IFERROR(TRIM(MID(I165, FIND(",", I165) + 1, IFERROR(FIND(",", I165, FIND(",", I165) + 1) - FIND(",", I165) - 1, LEN(I165)))), "") | N165: =IFERROR(TRIM(MID(I165, FIND(",", I165, FIND(",", I165) + 1) + 1, IFERROR(FIND(",", I165, FIND(",", I165, FIND(",", I165) + 1) + 1) - FIND(",", I165, FIND(",", I165) + 1) - 1, LEN(I165)))), "") | P165: =IFERROR(TRIM(MID(I165, FIND(",", I165, FIND(",", I165, FIND(",", I165) + 1) + 1) + 1, IFERROR(FIND(",", I165, FIND(",", I165, FIND(",", I165, FIND(",", I165) + 1) + 1) + 1) - FIND(",", I165, FIND(",", I165, FIND(",", I165) + 1) + 1) - 1, LEN(I165)))), "") | R165: =IFERROR(TRIM(MID(I165, FIND(",", I165, FIND(",", I165, FIND(",", I165, FIND(",", I165) + 1) + 1) + 1) + 1, IFERROR(FIND(",", I165, FIND(",", I165, FIND(",", I165, FIND(",", I165, FIND(",", I165) + 1) + 1) + 1) + 1) - FIND(",", I165, FIND(",", I165, FIND(",", I165, FIND(",", I165) + 1) + 1) + 1) - 1, LEN(I165)))), "") | T165: =IFERROR(TRIM(MID(I165, FIND(",", I165, FIND(",", I165, FIND(",", I165, FIND(",", I165, FIND(",", I165, FIND(",", I165) + 1) + 1) + 1) + 1) + 1) + 1, IFERROR(FIND(",", I165, FIND(",", I165, FIND(",", I165, FIND(",", I165, FIND(",", I165, FIND(",", I165) + 1) + 1) + 1) + 1) + 1) - FIND(",", I165, FIND(",", I165, FIND(",", I165, FIND(",", I165, FIND(",", I165) + 1) + 1) + 1) + 1) - 1, LEN(I165)))), "") | V165: =IFERROR(TRIM(MID(I165, FIND(",", I165, FIND(",", I165, FIND(",", I165, FIND(",", I165, FIND(",", I165, FIND(",", I165, FIND(",", I165) + 1) + 1) + 1) + 1) + 1) + 1) + 1, IFERROR(FIND(",", I165, FIND(",", I165, FIND(",", I165, FIND(",", I165, FIND(",", I165, FIND(",", I165, FIND(",", I165) + 1) + 1) + 1) + 1) + 1) + 1) - FIND(",", I165, FIND(",", I165, FIND(",", I165, FIND(",", I165, FIND(",", I165, FIND(",", I165) + 1) + 1) + 1) + 1) + 1) - 1, LEN(I165)))), "") | X165: =IFERROR(TRIM(MID(I165, FIND(",", I165, FIND(",", I165, FIND(",", I165, FIND(",", I165, FIND(",", I165, FIND(",", I165, FIND(",", I165, FIND(",", I165) + 1) + 1) + 1) + 1) + 1) + 1) + 1) + 1, IFERROR(FIND(",", I165, FIND(",", I165, FIND(",", I165, FIND(",", I165, FIND(",", I165, FIND(",", I165, FIND(",", I165, FIND(",", I165) + 1) + 1) + 1) + 1) + 1) + 1) + 1) - FIND(",", I165, FIND(",", I165, FIND(",", I165, FIND(",", I165, FIND(",", I165, FIND(",", I165, FIND(",", I165) + 1) + 1) + 1) + 1) + 1) + 1) - 1, LEN(I165)))), "") | Z165: =IFERROR(TRIM(MID(I165, FIND(",", I165, FIND(",", I165, FIND(",", I165, FIND(",", I165, FIND(",", I165, FIND(",", I165, FIND(",", I165, FIND(",", I165, FIND(",", I165) + 1) + 1) + 1) + 1) + 1) + 1) + 1) + 1) + 1, IFERROR(FIND(",", I165, FIND(",", I165, FIND(",", I165, FIND(",", I165, FIND(",", I165, FIND(",", I165, FIND(",", I165, FIND(",", I165, FIND(",", I165) + 1) + 1) + 1) + 1) + 1) + 1) + 1) + 1) - FIND(",", I165, FIND(",", I165, FIND(",", I165, FIND(",", I165, FIND(",", I165, FIND(",", I165, FIND(",", I165, FIND(",", I165) + 1) + 1) + 1) + 1) + 1) + 1) + 1) - 1, LEN(I165)))), "")
A166: 3617228415164FR-26V-23-78267 | B166: 3617228415164 | C166: FR-26V-23-78267 | D166: 11. Los Puentes De La Frontera | E166: Alemi Bustos | G166: AfinArte | H166: =100%-SUM(CatalogTable[[#This Row],[Artist 1 %]],CatalogTable[[#This Row],[Artist 2 %]],CatalogTable[[#This Row],[Artist 3 %]],CatalogTable[[#This Row],[Artist 4 %]],CatalogTable[[#This Row],[Artist 5 %]],CatalogTable[[#This Row],[Artist 6 %]],CatalogTable[[#This Row],[Artist 7 %]],CatalogTable[[#This Row],[Artist 8 %]],CatalogTable[[#This Row],[Artist 9%]]) -> 0.9 | I166: =IF(ISBLANK(E166),"",INDEX(UniqueArtist!B:B, MATCH(E166,UniqueArtist!A:A, 0))) -> Alemi Bustos | J166: =IFERROR(TRIM(LEFT(I166, IFERROR(FIND(",", I166)-1, LEN(I166)))), "") -> Alemi Bustos | K166: 0.1 | L166: =IFERROR(TRIM(MID(I166, FIND(",", I166) + 1, IFERROR(FIND(",", I166, FIND(",", I166) + 1) - FIND(",", I166) - 1, LEN(I166)))), "") | N166: =IFERROR(TRIM(MID(I166, FIND(",", I166, FIND(",", I166) + 1) + 1, IFERROR(FIND(",", I166, FIND(",", I166, FIND(",", I166) + 1) + 1) - FIND(",", I166, FIND(",", I166) + 1) - 1, LEN(I166)))), "") | P166: =IFERROR(TRIM(MID(I166, FIND(",", I166, FIND(",", I166, FIND(",", I166) + 1) + 1) + 1, IFERROR(FIND(",", I166, FIND(",", I166, FIND(",", I166, FIND(",", I166) + 1) + 1) + 1) - FIND(",", I166, FIND(",", I166, FIND(",", I166) + 1) + 1) - 1, LEN(I166)))), "") | R166: =IFERROR(TRIM(MID(I166, FIND(",", I166, FIND(",", I166, FIND(",", I166, FIND(",", I166) + 1) + 1) + 1) + 1, IFERROR(FIND(",", I166, FIND(",", I166, FIND(",", I166, FIND(",", I166, FIND(",", I166) + 1) + 1) + 1) + 1) - FIND(",", I166, FIND(",", I166, FIND(",", I166, FIND(",", I166) + 1) + 1) + 1) - 1, LEN(I166)))), "") | T166: =IFERROR(TRIM(MID(I166, FIND(",", I166, FIND(",", I166, FIND(",", I166, FIND(",", I166, FIND(",", I166, FIND(",", I166) + 1) + 1) + 1) + 1) + 1) + 1, IFERROR(FIND(",", I166, FIND(",", I166, FIND(",", I166, FIND(",", I166, FIND(",", I166, FIND(",", I166) + 1) + 1) + 1) + 1) + 1) - FIND(",", I166, FIND(",", I166, FIND(",", I166, FIND(",", I166, FIND(",", I166) + 1) + 1) + 1) + 1) - 1, LEN(I166)))), "") | V166: =IFERROR(TRIM(MID(I166, FIND(",", I166, FIND(",", I166, FIND(",", I166, FIND(",", I166, FIND(",", I166, FIND(",", I166, FIND(",", I166) + 1) + 1) + 1) + 1) + 1) + 1) + 1, IFERROR(FIND(",", I166, FIND(",", I166, FIND(",", I166, FIND(",", I166, FIND(",", I166, FIND(",", I166, FIND(",", I166) + 1) + 1) + 1) + 1) + 1) + 1) - FIND(",", I166, FIND(",", I166, FIND(",", I166, FIND(",", I166, FIND(",", I166, FIND(",", I166) + 1) + 1) + 1) + 1) + 1) - 1, LEN(I166)))), "") | X166: =IFERROR(TRIM(MID(I166, FIND(",", I166, FIND(",", I166, FIND(",", I166, FIND(",", I166, FIND(",", I166, FIND(",", I166, FIND(",", I166, FIND(",", I166) + 1) + 1) + 1) + 1) + 1) + 1) + 1) + 1, IFERROR(FIND(",", I166, FIND(",", I166, FIND(",", I166, FIND(",", I166, FIND(",", I166, FIND(",", I166, FIND(",", I166, FIND(",", I166) + 1) + 1) + 1) + 1) + 1) + 1) + 1) - FIND(",", I166, FIND(",", I166, FIND(",", I166, FIND(",", I166, FIND(",", I166, FIND(",", I166, FIND(",", I166) + 1) + 1) + 1) + 1) + 1) + 1) - 1, LEN(I166)))), "") | Z166: =IFERROR(TRIM(MID(I166, FIND(",", I166, FIND(",", I166, FIND(",", I166, FIND(",", I166, FIND(",", I166, FIND(",", I166, FIND(",", I166, FIND(",", I166, FIND(",", I166) + 1) + 1) + 1) + 1) + 1) + 1) + 1) + 1) + 1, IFERROR(FIND(",", I166, FIND(",", I166, FIND(",", I166, FIND(",", I166, FIND(",", I166, FIND(",", I166, FIND(",", I166, FIND(",", I166, FIND(",", I166) + 1) + 1) + 1) + 1) + 1) + 1) + 1) + 1) - FIND(",", I166, FIND(",", I166, FIND(",", I166, FIND(",", I166, FIND(",", I166, FIND(",", I166, FIND(",", I166, FIND(",", I166) + 1) + 1) + 1) + 1) + 1) + 1) + 1) - 1, LEN(I166)))), "")
A167: 3617226958847FR-26V-23-25862 | B167: 3617226958847 | C167: FR-26V-23-25862 | D167: 11.- Los Dos Carnales - Se Me Solto El Hocico (Visualizer) | E167: Los Dos Carnales | G167: AfinArte | H167: =100%-SUM(CatalogTable[[#This Row],[Artist 1 %]],CatalogTable[[#This Row],[Artist 2 %]],CatalogTable[[#This Row],[Artist 3 %]],CatalogTable[[#This Row],[Artist 4 %]],CatalogTable[[#This Row],[Artist 5 %]],CatalogTable[[#This Row],[Artist 6 %]],CatalogTable[[#This Row],[Artist 7 %]],CatalogTable[[#This Row],[Artist 8 %]],CatalogTable[[#This Row],[Artist 9%]]) -> 0.9 | I167: =IF(ISBLANK(E167),"",INDEX(UniqueArtist!B:B, MATCH(E167,UniqueArtist!A:A, 0))) -> Los Dos Carnales | J167: =IFERROR(TRIM(LEFT(I167, IFERROR(FIND(",", I167)-1, LEN(I167)))), "") -> Los Dos Carnales | K167: 0.1 | L167: =IFERROR(TRIM(MID(I167, FIND(",", I167) + 1, IFERROR(FIND(",", I167, FIND(",", I167) + 1) - FIND(",", I167) - 1, LEN(I167)))), "") | N167: =IFERROR(TRIM(MID(I167, FIND(",", I167, FIND(",", I167) + 1) + 1, IFERROR(FIND(",", I167, FIND(",", I167, FIND(",", I167) + 1) + 1) - FIND(",", I167, FIND(",", I167) + 1) - 1, LEN(I167)))), "") | P167: =IFERROR(TRIM(MID(I167, FIND(",", I167, FIND(",", I167, FIND(",", I167) + 1) + 1) + 1, IFERROR(FIND(",", I167, FIND(",", I167, FIND(",", I167, FIND(",", I167) + 1) + 1) + 1) - FIND(",", I167, FIND(",", I167, FIND(",", I167) + 1) + 1) - 1, LEN(I167)))), "") | R167: =IFERROR(TRIM(MID(I167, FIND(",", I167, FIND(",", I167, FIND(",", I167, FIND(",", I167) + 1) + 1) + 1) + 1, IFERROR(FIND(",", I167, FIND(",", I167, FIND(",", I167, FIND(",", I167, FIND(",", I167) + 1) + 1) + 1) + 1) - FIND(",", I167, FIND(",", I167, FIND(",", I167, FIND(",", I167) + 1) + 1) + 1) - 1, LEN(I167)))), "") | T167: =IFERROR(TRIM(MID(I167, FIND(",", I167, FIND(",", I167, FIND(",", I167, FIND(",", I167, FIND(",", I167, FIND(",", I167) + 1) + 1) + 1) + 1) + 1) + 1, IFERROR(FIND(",", I167, FIND(",", I167, FIND(",", I167, FIND(",", I167, FIND(",", I167, FIND(",", I167) + 1) + 1) + 1) + 1) + 1) - FIND(",", I167, FIND(",", I167, FIND(",", I167, FIND(",", I167, FIND(",", I167) + 1) + 1) + 1) + 1) - 1, LEN(I167)))), "") | V167: =IFERROR(TRIM(MID(I167, FIND(",", I167, FIND(",", I167, FIND(",", I167, FIND(",", I167, FIND(",", I167, FIND(",", I167, FIND(",", I167) + 1) + 1) + 1) + 1) + 1) + 1) + 1, IFERROR(FIND(",", I167, FIND(",", I167, FIND(",", I167, FIND(",", I167, FIND(",", I167, FIND(",", I167, FIND(",", I167) + 1) + 1) + 1) + 1) + 1) + 1) - FIND(",", I167, FIND(",", I167, FIND(",", I167, FIND(",", I167, FIND(",", I167, FIND(",", I167) + 1) + 1) + 1) + 1) + 1) - 1, LEN(I167)))), "") | X167: =IFERROR(TRIM(MID(I167, FIND(",", I167, FIND(",", I167, FIND(",", I167, FIND(",", I167, FIND(",", I167, FIND(",", I167, FIND(",", I167, FIND(",", I167) + 1) + 1) + 1) + 1) + 1) + 1) + 1) + 1, IFERROR(FIND(",", I167, FIND(",", I167, FIND(",", I167, FIND(",", I167, FIND(",", I167, FIND(",", I167, FIND(",", I167, FIND(",", I167) + 1) + 1) + 1) + 1) + 1) + 1) + 1) - FIND(",", I167, FIND(",", I167, FIND(",", I167, FIND(",", I167, FIND(",", I167, FIND(",", I167, FIND(",", I167) + 1) + 1) + 1) + 1) + 1) + 1) - 1, LEN(I167)))), "") | Z167: =IFERROR(TRIM(MID(I167, FIND(",", I167, FIND(",", I167, FIND(",", I167, FIND(",", I167, FIND(",", I167, FIND(",", I167, FIND(",", I167, FIND(",", I167, FIND(",", I167) + 1) + 1) + 1) + 1) + 1) + 1) + 1) + 1) + 1, IFERROR(FIND(",", I167, FIND(",", I167, FIND(",", I167, FIND(",", I167, FIND(",", I167, FIND(",", I167, FIND(",", I167, FIND(",", I167, FIND(",", I167) + 1) + 1) + 1) + 1) + 1) + 1) + 1) + 1) - FIND(",", I167, FIND(",", I167, FIND(",", I167, FIND(",", I167, FIND(",", I167, FIND(",", I167, FIND(",", I167, FIND(",", I167) + 1) + 1) + 1) + 1) + 1) + 1) + 1) - 1, LEN(I167)))), "")
A168: 3617228175723FR-26V-23-70517 | B168: 3617228175723 | C168: FR-26V-23-70517 | D168: 11.- MI PROBLEMA | E168: Alemi Bustos | G168: AfinArte | H168: =100%-SUM(CatalogTable[[#This Row],[Artist 1 %]],CatalogTable[[#This Row],[Artist 2 %]],CatalogTable[[#This Row],[Artist 3 %]],CatalogTable[[#This Row],[Artist 4 %]],CatalogTable[[#This Row],[Artist 5 %]],CatalogTable[[#This Row],[Artist 6 %]],CatalogTable[[#This Row],[Artist 7 %]],CatalogTable[[#This Row],[Artist 8 %]],CatalogTable[[#This Row],[Artist 9%]]) -> 0.9 | I168: =IF(ISBLANK(E168),"",INDEX(UniqueArtist!B:B, MATCH(E168,UniqueArtist!A:A, 0))) -> Alemi Bustos | J168: =IFERROR(TRIM(LEFT(I168, IFERROR(FIND(",", I168)-1, LEN(I168)))), "") -> Alemi Bustos | K168: 0.1 | L168: =IFERROR(TRIM(MID(I168, FIND(",", I168) + 1, IFERROR(FIND(",", I168, FIND(",", I168) + 1) - FIND(",", I168) - 1, LEN(I168)))), "") | N168: =IFERROR(TRIM(MID(I168, FIND(",", I168, FIND(",", I168) + 1) + 1, IFERROR(FIND(",", I168, FIND(",", I168, FIND(",", I168) + 1) + 1) - FIND(",", I168, FIND(",", I168) + 1) - 1, LEN(I168)))), "") | P168: =IFERROR(TRIM(MID(I168, FIND(",", I168, FIND(",", I168, FIND(",", I168) + 1) + 1) + 1, IFERROR(FIND(",", I168, FIND(",", I168, FIND(",", I168, FIND(",", I168) + 1) + 1) + 1) - FIND(",", I168, FIND(",", I168, FIND(",", I168) + 1) + 1) - 1, LEN(I168)))), "") | R168: =IFERROR(TRIM(MID(I168, FIND(",", I168, FIND(",", I168, FIND(",", I168, FIND(",", I168) + 1) + 1) + 1) + 1, IFERROR(FIND(",", I168, FIND(",", I168, FIND(",", I168, FIND(",", I168, FIND(",", I168) + 1) + 1) + 1) + 1) - FIND(",", I168, FIND(",", I168, FIND(",", I168, FIND(",", I168) + 1) + 1) + 1) - 1, LEN(I168)))), "") | T168: =IFERROR(TRIM(MID(I168, FIND(",", I168, FIND(",", I168, FIND(",", I168, FIND(",", I168, FIND(",", I168, FIND(",", I168) + 1) + 1) + 1) + 1) + 1) + 1, IFERROR(FIND(",", I168, FIND(",", I168, FIND(",", I168, FIND(",", I168, FIND(",", I168, FIND(",", I168) + 1) + 1) + 1) + 1) + 1) - FIND(",", I168, FIND(",", I168, FIND(",", I168, FIND(",", I168, FIND(",", I168) + 1) + 1) + 1) + 1) - 1, LEN(I168)))), "") | V168: =IFERROR(TRIM(MID(I168, FIND(",", I168, FIND(",", I168, FIND(",", I168, FIND(",", I168, FIND(",", I168, FIND(",", I168, FIND(",", I168) + 1) + 1) + 1) + 1) + 1) + 1) + 1, IFERROR(FIND(",", I168, FIND(",", I168, FIND(",", I168, FIND(",", I168, FIND(",", I168, FIND(",", I168, FIND(",", I168) + 1) + 1) + 1) + 1) + 1) + 1) - FIND(",", I168, FIND(",", I168, FIND(",", I168, FIND(",", I168, FIND(",", I168, FIND(",", I168) + 1) + 1) + 1) + 1) + 1) - 1, LEN(I168)))), "") | X168: =IFERROR(TRIM(MID(I168, FIND(",", I168, FIND(",", I168, FIND(",", I168, FIND(",", I168, FIND(",", I168, FIND(",", I168, FIND(",", I168, FIND(",", I168) + 1) + 1) + 1) + 1) + 1) + 1) + 1) + 1, IFERROR(FIND(",", I168, FIND(",", I168, FIND(",", I168, FIND(",", I168, FIND(",", I168, FIND(",", I168, FIND(",", I168, FIND(",", I168) + 1) + 1) + 1) + 1) + 1) + 1) + 1) - FIND(",", I168, FIND(",", I168, FIND(",", I168, FIND(",", I168, FIND(",", I168, FIND(",", I168, FIND(",", I168) + 1) + 1) + 1) + 1) + 1) + 1) - 1, LEN(I168)))), "") | Z168: =IFERROR(TRIM(MID(I168, FIND(",", I168, FIND(",", I168, FIND(",", I168, FIND(",", I168, FIND(",", I168, FIND(",", I168, FIND(",", I168, FIND(",", I168, FIND(",", I168) + 1) + 1) + 1) + 1) + 1) + 1) + 1) + 1) + 1, IFERROR(FIND(",", I168, FIND(",", I168, FIND(",", I168, FIND(",", I168, FIND(",", I168, FIND(",", I168, FIND(",", I168, FIND(",", I168, FIND(",", I168) + 1) + 1) + 1) + 1) + 1) + 1) + 1) + 1) - FIND(",", I168, FIND(",", I168, FIND(",", I168, FIND(",", I168, FIND(",", I168, FIND(",", I168, FIND(",", I168, FIND(",", I168) + 1) + 1) + 1) + 1) + 1) + 1) + 1) - 1, LEN(I168)))), "")
A169: 3617056796831FR-59R-23-72662 | B169: 3617056796831 | C169: FR-59R-23-72662 | D169: 118 Balazos | E169: LOS DOS DE TAMAULIPAS | G169: AfinArte | H169: =100%-SUM(CatalogTable[[#This Row],[Artist 1 %]],CatalogTable[[#This Row],[Artist 2 %]],CatalogTable[[#This Row],[Artist 3 %]],CatalogTable[[#This Row],[Artist 4 %]],CatalogTable[[#This Row],[Artist 5 %]],CatalogTable[[#This Row],[Artist 6 %]],CatalogTable[[#This Row],[Artist 7 %]],CatalogTable[[#This Row],[Artist 8 %]],CatalogTable[[#This Row],[Artist 9%]]) -> 0.9 | I169: =IF(ISBLANK(E169),"",INDEX(UniqueArtist!B:B, MATCH(E169,UniqueArtist!A:A, 0))) -> Los Dos de Tamaulipas | J169: =IFERROR(TRIM(LEFT(I169, IFERROR(FIND(",", I169)-1, LEN(I169)))), "") -> Los Dos de Tamaulipas | K169: 0.1 | L169: =IFERROR(TRIM(MID(I169, FIND(",", I169) + 1, IFERROR(FIND(",", I169, FIND(",", I169) + 1) - FIND(",", I169) - 1, LEN(I169)))), "") | N169: =IFERROR(TRIM(MID(I169, FIND(",", I169, FIND(",", I169) + 1) + 1, IFERROR(FIND(",", I169, FIND(",", I169, FIND(",", I169) + 1) + 1) - FIND(",", I169, FIND(",", I169) + 1) - 1, LEN(I169)))), "") | P169: =IFERROR(TRIM(MID(I169, FIND(",", I169, FIND(",", I169, FIND(",", I169) + 1) + 1) + 1, IFERROR(FIND(",", I169, FIND(",", I169, FIND(",", I169, FIND(",", I169) + 1) + 1) + 1) - FIND(",", I169, FIND(",", I169, FIND(",", I169) + 1) + 1) - 1, LEN(I169)))), "") | R169: =IFERROR(TRIM(MID(I169, FIND(",", I169, FIND(",", I169, FIND(",", I169, FIND(",", I169) + 1) + 1) + 1) + 1, IFERROR(FIND(",", I169, FIND(",", I169, FIND(",", I169, FIND(",", I169, FIND(",", I169) + 1) + 1) + 1) + 1) - FIND(",", I169, FIND(",", I169, FIND(",", I169, FIND(",", I169) + 1) + 1) + 1) - 1, LEN(I169)))), "") | T169: =IFERROR(TRIM(MID(I169, FIND(",", I169, FIND(",", I169, FIND(",", I169, FIND(",", I169, FIND(",", I169, FIND(",", I169) + 1) + 1) + 1) + 1) + 1) + 1, IFERROR(FIND(",", I169, FIND(",", I169, FIND(",", I169, FIND(",", I169, FIND(",", I169, FIND(",", I169) + 1) + 1) + 1) + 1) + 1) - FIND(",", I169, FIND(",", I169, FIND(",", I169, FIND(",", I169, FIND(",", I169) + 1) + 1) + 1) + 1) - 1, LEN(I169)))), "") | V169: =IFERROR(TRIM(MID(I169, FIND(",", I169, FIND(",", I169, FIND(",", I169, FIND(",", I169, FIND(",", I169, FIND(",", I169, FIND(",", I169) + 1) + 1) + 1) + 1) + 1) + 1) + 1, IFERROR(FIND(",", I169, FIND(",", I169, FIND(",", I169, FIND(",", I169, FIND(",", I169, FIND(",", I169, FIND(",", I169) + 1) + 1) + 1) + 1) + 1) + 1) - FIND(",", I169, FIND(",", I169, FIND(",", I169, FIND(",", I169, FIND(",", I169, FIND(",", I169) + 1) + 1) + 1) + 1) + 1) - 1, LEN(I169)))), "") | X169: =IFERROR(TRIM(MID(I169, FIND(",", I169, FIND(",", I169, FIND(",", I169, FIND(",", I169, FIND(",", I169, FIND(",", I169, FIND(",", I169, FIND(",", I169) + 1) + 1) + 1) + 1) + 1) + 1) + 1) + 1, IFERROR(FIND(",", I169, FIND(",", I169, FIND(",", I169, FIND(",", I169, FIND(",", I169, FIND(",", I169, FIND(",", I169, FIND(",", I169) + 1) + 1) + 1) + 1) + 1) + 1) + 1) - FIND(",", I169, FIND(",", I169, FIND(",", I169, FIND(",", I169, FIND(",", I169, FIND(",", I169, FIND(",", I169) + 1) + 1) + 1) + 1) + 1) + 1) - 1, LEN(I169)))), "") | Z169: =IFERROR(TRIM(MID(I169, FIND(",", I169, FIND(",", I169, FIND(",", I169, FIND(",", I169, FIND(",", I169, FIND(",", I169, FIND(",", I169, FIND(",", I169, FIND(",", I169) + 1) + 1) + 1) + 1) + 1) + 1) + 1) + 1) + 1, IFERROR(FIND(",", I169, FIND(",", I169, FIND(",", I169, FIND(",", I169, FIND(",", I169, FIND(",", I169, FIND(",", I169, FIND(",", I169, FIND(",", I169) + 1) + 1) + 1) + 1) + 1) + 1) + 1) + 1) - FIND(",", I169, FIND(",", I169, FIND(",", I169, FIND(",", I169, FIND(",", I169, FIND(",", I169, FIND(",", I169, FIND(",", I169) + 1) + 1) + 1) + 1) + 1) + 1) + 1) - 1, LEN(I169)))), "")
... A180: 3615936948011FR-W24-19-19565 | B180: 3615936948011 | C180: FR-W24-19-19565 | D180: 16 Mi Cajita De Madera - Voz de Mando 2018 | E180: Voz De Mando | G180: AfinArte | H180: =100%-SUM(CatalogTable[[#This Row],[Artist 1 %]],CatalogTable[[#This Row],[Artist 2 %]],CatalogTable[[#This Row],[Artist 3 %]],CatalogTable[[#This Row],[Artist 4 %]],CatalogTable[[#This Row],[Artist 5 %]],CatalogTable[[#This Row],[Artist 6 %]],CatalogTable[[#This Row],[Artist 7 %]],CatalogTable[[#This Row],[Artist 8 %]],CatalogTable[[#This Row],[Artist 9%]]) -> 0 | I180: =IF(ISBLANK(E180),"",INDEX(UniqueArtist!B:B, MATCH(E180,UniqueArtist!A:A, 0))) -> Voz de Mando | J180: =IFERROR(TRIM(LEFT(I180, IFERROR(FIND(",", I180)-1, LEN(I180)))), "") -> Voz de Mando | K180: 1 | L180: =IFERROR(TRIM(MID(I180, FIND(",", I180) + 1, IFERROR(FIND(",", I180, FIND(",", I180) + 1) - FIND(",", I180) - 1, LEN(I180)))), "") | N180: =IFERROR(TRIM(MID(I180, FIND(",", I180, FIND(",", I180) + 1) + 1, IFERROR(FIND(",", I180, FIND(",", I180, FIND(",", I180) + 1) + 1) - FIND(",", I180, FIND(",", I180) + 1) - 1, LEN(I180)))), "") | P180: =IFERROR(TRIM(MID(I180, FIND(",", I180, FIND(",", I180, FIND(",", I180) + 1) + 1) + 1, IFERROR(FIND(",", I180, FIND(",", I180, FIND(",", I180, FIND(",", I180) + 1) + 1) + 1) - FIND(",", I180, FIND(",", I180, FIND(",", I180) + 1) + 1) - 1, LEN(I180)))), "") | R180: =IFERROR(TRIM(MID(I180, FIND(",", I180, FIND(",", I180, FIND(",", I180, FIND(",", I180) + 1) + 1) + 1) + 1, IFERROR(FIND(",", I180, FIND(",", I180, FIND(",", I180, FIND(",", I180, FIND(",", I180) + 1) + 1) + 1) + 1) - FIND(",", I180, FIND(",", I180, FIND(",", I180, FIND(",", I180) + 1) + 1) + 1) - 1, LEN(I180)))), "") | T180: =IFERROR(TRIM(MID(I180, FIND(",", I180, FIND(",", I180, FIND(",", I180, FIND(",", I180, FIND(",", I180, FIND(",", I180) + 1) + 1) + 1) + 1) + 1) + 1, IFERROR(FIND(",", I180, FIND(",", I180, FIND(",", I180, FIND(",", I180, FIND(",", I180, FIND(",", I180) + 1) + 1) + 1) + 1) + 1) - FIND(",", I180, FIND(",", I180, FIND(",", I180, FIND(",", I180, FIND(",", I180) + 1) + 1) + 1) + 1) - 1, LEN(I180)))), "") | V180: =IFERROR(TRIM(MID(I180, FIND(",", I180, FIND(",", I180, FIND(",", I180, FIND(",", I180, FIND(",", I180, FIND(",", I180, FIND(",", I180) + 1) + 1) + 1) + 1) + 1) + 1) + 1, IFERROR(FIND(",", I180, FIND(",", I180, FIND(",", I180, FIND(",", I180, FIND(",", I180, FIND(",", I180, FIND(",", I180) + 1) + 1) + 1) + 1) + 1) + 1) - FIND(",", I180, FIND(",", I180, FIND(",", I180, FIND(",", I180, FIND(",", I180, FIND(",", I180) + 1) + 1) + 1) + 1) + 1) - 1, LEN(I180)))), "") | X180: =IFERROR(TRIM(MID(I180, FIND(",", I180, FIND(",", I180, FIND(",", I180, FIND(",", I180, FIND(",", I180, FIND(",", I180, FIND(",", I180, FIND(",", I180) + 1) + 1) + 1) + 1) + 1) + 1) + 1) + 1, IFERROR(FIND(",", I180, FIND(",", I180, FIND(",", I180, FIND(",", I180, FIND(",", I180, FIND(",", I180, FIND(",", I180, FIND(",", I180) + 1) + 1) + 1) + 1) + 1) + 1) + 1) - FIND(",", I180, FIND(",", I180, FIND(",", I180, FIND(",", I180, FIND(",", I180, FIND(",", I180, FIND(",", I180) + 1) + 1) + 1) + 1) + 1) + 1) - 1, LEN(I180)))), "") | Z180: =IFERROR(TRIM(MID(I180, FIND(",", I180, FIND(",", I180, FIND(",", I180, FIND(",", I180, FIND(",", I180, FIND(",", I180, FIND(",", I180, FIND(",", I180, FIND(",", I180) + 1) + 1) + 1) + 1) + 1) + 1) + 1) + 1) + 1, IFERROR(FIND(",", I180, FIND(",", I180, FIND(",", I180, FIND(",", I180, FIND(",", I180, FIND(",", I180, FIND(",", I180, FIND(",", I180, FIND(",", I180) + 1) + 1) + 1) + 1) + 1) + 1) + 1) + 1) - FIND(",", I180, FIND(",", I180, FIND(",", I180, FIND(",", I180, FIND(",", I180, FIND(",", I180, FIND(",", I180, FIND(",", I180) + 1) + 1) + 1) + 1) + 1) + 1) + 1) - 1, LEN(I180)))), "")
A181: 3616400513469FR-W77-19-57063 | B181: 3616400513469 | C181: FR-W77-19-57063 | D181: 2. El Fantasma - La Vieja Escuela | E181: El Fantasma | F181: 43616 | G181: AfinArte | H181: =100%-SUM(CatalogTable[[#This Row],[Artist 1 %]],CatalogTable[[#This Row],[Artist 2 %]],CatalogTable[[#This Row],[Artist 3 %]],CatalogTable[[#This Row],[Artist 4 %]],CatalogTable[[#This Row],[Artist 5 %]],CatalogTable[[#This Row],[Artist 6 %]],CatalogTable[[#This Row],[Artist 7 %]],CatalogTable[[#This Row],[Artist 8 %]],CatalogTable[[#This Row],[Artist 9%]]) -> 0.75 | I181: =IF(ISBLANK(E181),"",INDEX(UniqueArtist!B:B, MATCH(E181,UniqueArtist!A:A, 0))) -> El Fantasma | J181: =IFERROR(TRIM(LEFT(I181, IFERROR(FIND(",", I181)-1, LEN(I181)))), "") -> El Fantasma | K181: 0.25 | L181: =IFERROR(TRIM(MID(I181, FIND(",", I181) + 1, IFERROR(FIND(",", I181, FIND(",", I181) + 1) - FIND(",", I181) - 1, LEN(I181)))), "") | N181: =IFERROR(TRIM(MID(I181, FIND(",", I181, FIND(",", I181) + 1) + 1, IFERROR(FIND(",", I181, FIND(",", I181, FIND(",", I181) + 1) + 1) - FIND(",", I181, FIND(",", I181) + 1) - 1, LEN(I181)))), "") | P181: =IFERROR(TRIM(MID(I181, FIND(",", I181, FIND(",", I181, FIND(",", I181) + 1) + 1) + 1, IFERROR(FIND(",", I181, FIND(",", I181, FIND(",", I181, FIND(",", I181) + 1) + 1) + 1) - FIND(",", I181, FIND(",", I181, FIND(",", I181) + 1) + 1) - 1, LEN(I181)))), "") | R181: =IFERROR(TRIM(MID(I181, FIND(",", I181, FIND(",", I181, FIND(",", I181, FIND(",", I181) + 1) + 1) + 1) + 1, IFERROR(FIND(",", I181, FIND(",", I181, FIND(",", I181, FIND(",", I181, FIND(",", I181) + 1) + 1) + 1) + 1) - FIND(",", I181, FIND(",", I181, FIND(",", I181, FIND(",", I181) + 1) + 1) + 1) - 1, LEN(I181)))), "") | T181: =IFERROR(TRIM(MID(I181, FIND(",", I181, FIND(",", I181, FIND(",", I181, FIND(",", I181, FIND(",", I181, FIND(",", I181) + 1) + 1) + 1) + 1) + 1) + 1, IFERROR(FIND(",", I181, FIND(",", I181, FIND(",", I181, FIND(",", I181, FIND(",", I181, FIND(",", I181) + 1) + 1) + 1) + 1) + 1) - FIND(",", I181, FIND(",", I181, FIND(",", I181, FIND(",", I181, FIND(",", I181) + 1) + 1) + 1) + 1) - 1, LEN(I181)))), "") | V181: =IFERROR(TRIM(MID(I181, FIND(",", I181, FIND(",", I181, FIND(",", I181, FIND(",", I181, FIND(",", I181, FIND(",", I181, FIND(",", I181) + 1) + 1) + 1) + 1) + 1) + 1) + 1, IFERROR(FIND(",", I181, FIND(",", I181, FIND(",", I181, FIND(",", I181, FIND(",", I181, FIND(",", I181, FIND(",", I181) + 1) + 1) + 1) + 1) + 1) + 1) - FIND(",", I181, FIND(",", I181, FIND(",", I181, FIND(",", I181, FIND(",", I181, FIND(",", I181) + 1) + 1) + 1) + 1) + 1) - 1, LEN(I181)))), "") | X181: =IFERROR(TRIM(MID(I181, FIND(",", I181, FIND(",", I181, FIND(",", I181, FIND(",", I181, FIND(",", I181, FIND(",", I181, FIND(",", I181, FIND(",", I181) + 1) + 1) + 1) + 1) + 1) + 1) + 1) + 1, IFERROR(FIND(",", I181, FIND(",", I181, FIND(",", I181, FIND(",", I181, FIND(",", I181, FIND(",", I181, FIND(",", I181, FIND(",", I181) + 1) + 1) + 1) + 1) + 1) + 1) + 1) - FIND(",", I181, FIND(",", I181, FIND(",", I181, FIND(",", I181, FIND(",", I181, FIND(",", I181, FIND(",", I181) + 1) + 1) + 1) + 1) + 1) + 1) - 1, LEN(I181)))), "") | Z181: =IFERROR(TRIM(MID(I181, FIND(",", I181, FIND(",", I181, FIND(",", I181, FIND(",", I181, FIND(",", I181, FIND(",", I181, FIND(",", I181, FIND(",", I181, FIND(",", I181) + 1) + 1) + 1) + 1) + 1) + 1) + 1) + 1) + 1, IFERROR(FIND(",", I181, FIND(",", I181, FIND(",", I181, FIND(",", I181, FIND(",", I181, FIND(",", I181, FIND(",", I181, FIND(",", I181, FIND(",", I181) + 1) + 1) + 1) + 1) + 1) + 1) + 1) + 1) - FIND(",", I181, FIND(",", I181, FIND(",", I181, FIND(",", I181, FIND(",", I181, FIND(",", I181, FIND(",", I181, FIND(",", I181) + 1) + 1) + 1) + 1) + 1) + 1) + 1) - 1, LEN(I181)))), "")
A182: 3617228193673FR-26V-23-71200 | B182: 3617228193673 | C182: FR-26V-23-71200 | D182: 2.- AQUI ME LES PRESENTO | E182: Alemi Bustos | G182: AfinArte | H182: =100%-SUM(CatalogTable[[#This Row],[Artist 1 %]],CatalogTable[[#This Row],[Artist 2 %]],CatalogTable[[#This Row],[Artist 3 %]],CatalogTable[[#This Row],[Artist 4 %]],CatalogTable[[#This Row],[Artist 5 %]],CatalogTable[[#This Row],[Artist 6 %]],CatalogTable[[#This Row],[Artist 7 %]],CatalogTable[[#This Row],[Artist 8 %]],CatalogTable[[#This Row],[Artist 9%]]) -> 0.9 | I182: =IF(ISBLANK(E182),"",INDEX(UniqueArtist!B:B, MATCH(E182,UniqueArtist!A:A, 0))) -> Alemi Bustos | J182: =IFERROR(TRIM(LEFT(I182, IFERROR(FIND(",", I182)-1, LEN(I182)))), "") -> Alemi Bustos | K182: 0.1 | L182: =IFERROR(TRIM(MID(I182, FIND(",", I182) + 1, IFERROR(FIND(",", I182, FIND(",", I182) + 1) - FIND(",", I182) - 1, LEN(I182)))), "") | N182: =IFERROR(TRIM(MID(I182, FIND(",", I182, FIND(",", I182) + 1) + 1, IFERROR(FIND(",", I182, FIND(",", I182, FIND(",", I182) + 1) + 1) - FIND(",", I182, FIND(",", I182) + 1) - 1, LEN(I182)))), "") | P182: =IFERROR(TRIM(MID(I182, FIND(",", I182, FIND(",", I182, FIND(",", I182) + 1) + 1) + 1, IFERROR(FIND(",", I182, FIND(",", I182, FIND(",", I182, FIND(",", I182) + 1) + 1) + 1) - FIND(",", I182, FIND(",", I182, FIND(",", I182) + 1) + 1) - 1, LEN(I182)))), "") | R182: =IFERROR(TRIM(MID(I182, FIND(",", I182, FIND(",", I182, FIND(",", I182, FIND(",", I182) + 1) + 1) + 1) + 1, IFERROR(FIND(",", I182, FIND(",", I182, FIND(",", I182, FIND(",", I182, FIND(",", I182) + 1) + 1) + 1) + 1) - FIND(",", I182, FIND(",", I182, FIND(",", I182, FIND(",", I182) + 1) + 1) + 1) - 1, LEN(I182)))), "") | T182: =IFERROR(TRIM(MID(I182, FIND(",", I182, FIND(",", I182, FIND(",", I182, FIND(",", I182, FIND(",", I182, FIND(",", I182) + 1) + 1) + 1) + 1) + 1) + 1, IFERROR(FIND(",", I182, FIND(",", I182, FIND(",", I182, FIND(",", I182, FIND(",", I182, FIND(",", I182) + 1) + 1) + 1) + 1) + 1) - FIND(",", I182, FIND(",", I182, FIND(",", I182, FIND(",", I182, FIND(",", I182) + 1) + 1) + 1) + 1) - 1, LEN(I182)))), "") | V182: =IFERROR(TRIM(MID(I182, FIND(",", I182, FIND(",", I182, FIND(",", I182, FIND(",", I182, FIND(",", I182, FIND(",", I182, FIND(",", I182) + 1) + 1) + 1) + 1) + 1) + 1) + 1, IFERROR(FIND(",", I182, FIND(",", I182, FIND(",", I182, FIND(",", I182, FIND(",", I182, FIND(",", I182, FIND(",", I182) + 1) + 1) + 1) + 1) + 1) + 1) - FIND(",", I182, FIND(",", I182, FIND(",", I182, FIND(",", I182, FIND(",", I182, FIND(",", I182) + 1) + 1) + 1) + 1) + 1) - 1, LEN(I182)))), "") | X182: =IFERROR(TRIM(MID(I182, FIND(",", I182, FIND(",", I182, FIND(",", I182, FIND(",", I182, FIND(",", I182, FIND(",", I182, FIND(",", I182, FIND(",", I182) + 1) + 1) + 1) + 1) + 1) + 1) + 1) + 1, IFERROR(FIND(",", I182, FIND(",", I182, FIND(",", I182, FIND(",", I182, FIND(",", I182, FIND(",", I182, FIND(",", I182, FIND(",", I182) + 1) + 1) + 1) + 1) + 1) + 1) + 1) - FIND(",", I182, FIND(",", I182, FIND(",", I182, FIND(",", I182, FIND(",", I182, FIND(",", I182, FIND(",", I182) + 1) + 1) + 1) + 1) + 1) + 1) - 1, LEN(I182)))), "") | Z182: =IFERROR(TRIM(MID(I182, FIND(",", I182, FIND(",", I182, FIND(",", I182, FIND(",", I182, FIND(",", I182, FIND(",", I182, FIND(",", I182, FIND(",", I182, FIND(",", I182) + 1) + 1) + 1) + 1) + 1) + 1) + 1) + 1) + 1, IFERROR(FIND(",", I182, FIND(",", I182, FIND(",", I182, FIND(",", I182, FIND(",", I182, FIND(",", I182, FIND(",", I182, FIND(",", I182, FIND(",", I182) + 1) + 1) + 1) + 1) + 1) + 1) + 1) + 1) - FIND(",", I182, FIND(",", I182, FIND(",", I182, FIND(",", I182, FIND(",", I182, FIND(",", I182, FIND(",", I182, FIND(",", I182) + 1) + 1) + 1) + 1) + 1) + 1) + 1) - 1, LEN(I182)))), "")
A183: 3617226962042FR-26V-23-26117 | B183: 3617226962042 | C183: FR-26V-23-26117 | D183: 2.- Los Dos Carnales - Soy El Cuervo (Visualizer) | E183: Los Dos Carnales | G183: AfinArte | H183: =100%-SUM(CatalogTable[[#This Row],[Artist 1 %]],CatalogTable[[#This Row],[Artist 2 %]],CatalogTable[[#This Row],[Artist 3 %]],CatalogTable[[#This Row],[Artist 4 %]],CatalogTable[[#This Row],[Artist 5 %]],CatalogTable[[#This Row],[Artist 6 %]],CatalogTable[[#This Row],[Artist 7 %]],CatalogTable[[#This Row],[Artist 8 %]],CatalogTable[[#This Row],[Artist 9%]]) -> 0.9 | I183: =IF(ISBLANK(E183),"",INDEX(UniqueArtist!B:B, MATCH(E183,UniqueArtist!A:A, 0))) -> Los Dos Carnales | J183: =IFERROR(TRIM(LEFT(I183, IFERROR(FIND(",", I183)-1, LEN(I183)))), "") -> Los Dos Carnales | K183: 0.1 | L183: =IFERROR(TRIM(MID(I183, FIND(",", I183) + 1, IFERROR(FIND(",", I183, FIND(",", I183) + 1) - FIND(",", I183) - 1, LEN(I183)))), "") | N183: =IFERROR(TRIM(MID(I183, FIND(",", I183, FIND(",", I183) + 1) + 1, IFERROR(FIND(",", I183, FIND(",", I183, FIND(",", I183) + 1) + 1) - FIND(",", I183, FIND(",", I183) + 1) - 1, LEN(I183)))), "") | P183: =IFERROR(TRIM(MID(I183, FIND(",", I183, FIND(",", I183, FIND(",", I183) + 1) + 1) + 1, IFERROR(FIND(",", I183, FIND(",", I183, FIND(",", I183, FIND(",", I183) + 1) + 1) + 1) - FIND(",", I183, FIND(",", I183, FIND(",", I183) + 1) + 1) - 1, LEN(I183)))), "") | R183: =IFERROR(TRIM(MID(I183, FIND(",", I183, FIND(",", I183, FIND(",", I183, FIND(",", I183) + 1) + 1) + 1) + 1, IFERROR(FIND(",", I183, FIND(",", I183, FIND(",", I183, FIND(",", I183, FIND(",", I183) + 1) + 1) + 1) + 1) - FIND(",", I183, FIND(",", I183, FIND(",", I183, FIND(",", I183) + 1) + 1) + 1) - 1, LEN(I183)))), "") | T183: =IFERROR(TRIM(MID(I183, FIND(",", I183, FIND(",", I183, FIND(",", I183, FIND(",", I183, FIND(",", I183, FIND(",", I183) + 1) + 1) + 1) + 1) + 1) + 1, IFERROR(FIND(",", I183, FIND(",", I183, FIND(",", I183, FIND(",", I183, FIND(",", I183, FIND(",", I183) + 1) + 1) + 1) + 1) + 1) - FIND(",", I183, FIND(",", I183, FIND(",", I183, FIND(",", I183, FIND(",", I183) + 1) + 1) + 1) + 1) - 1, LEN(I183)))), "") | V183: =IFERROR(TRIM(MID(I183, FIND(",", I183, FIND(",", I183, FIND(",", I183, FIND(",", I183, FIND(",", I183, FIND(",", I183, FIND(",", I183) + 1) + 1) + 1) + 1) + 1) + 1) + 1, IFERROR(FIND(",", I183, FIND(",", I183, FIND(",", I183, FIND(",", I183, FIND(",", I183, FIND(",", I183, FIND(",", I183) + 1) + 1) + 1) + 1) + 1) + 1) - FIND(",", I183, FIND(",", I183, FIND(",", I183, FIND(",", I183, FIND(",", I183, FIND(",", I183) + 1) + 1) + 1) + 1) + 1) - 1, LEN(I183)))), "") | X183: =IFERROR(TRIM(MID(I183, FIND(",", I183, FIND(",", I183, FIND(",", I183, FIND(",", I183, FIND(",", I183, FIND(",", I183, FIND(",", I183, FIND(",", I183) + 1) + 1) + 1) + 1) + 1) + 1) + 1) + 1, IFERROR(FIND(",", I183, FIND(",", I183, FIND(",", I183, FIND(",", I183, FIND(",", I183, FIND(",", I183, FIND(",", I183, FIND(",", I183) + 1) + 1) + 1) + 1) + 1) + 1) + 1) - FIND(",", I183, FIND(",", I183, FIND(",", I183, FIND(",", I183, FIND(",", I183, FIND(",", I183, FIND(",", I183) + 1) + 1) + 1) + 1) + 1) + 1) - 1, LEN(I183)))), "") | Z183: =IFERROR(TRIM(MID(I183, FIND(",", I183, FIND(",", I183, FIND(",", I183, FIND(",", I183, FIND(",", I183, FIND(",", I183, FIND(",", I183, FIND(",", I183, FIND(",", I183) + 1) + 1) + 1) + 1) + 1) + 1) + 1) + 1) + 1, IFERROR(FIND(",", I183, FIND(",", I183, FIND(",", I183, FIND(",", I183, FIND(",", I183, FIND(",", I183, FIND(",", I183, FIND(",", I183, FIND(",", I183) + 1) + 1) + 1) + 1) + 1) + 1) + 1) + 1) - FIND(",", I183, FIND(",", I183, FIND(",", I183, FIND(",", I183, FIND(",", I183, FIND(",", I183, FIND(",", I183, FIND(",", I183) + 1) + 1) + 1) + 1) + 1) + 1) + 1) - 1, LEN(I183)))), "")
A184: 3617225242343FR-S18-23-59096 | B184: 3617225242343 | C184: FR-S18-23-59096 | D184: 24/7 quiere que le meta 🔥 #shorts #ShortsVidel #TinTin #Zeze #YoSoyFifty #ArteFino | E184: Artefino Music | G184: AfinArte | H184: =100%-SUM(CatalogTable[[#This Row],[Artist 1 %]],CatalogTable[[#This Row],[Artist 2 %]],CatalogTable[[#This Row],[Artist 3 %]],CatalogTable[[#This Row],[Artist 4 %]],CatalogTable[[#This Row],[Artist 5 %]],CatalogTable[[#This Row],[Artist 6 %]],CatalogTable[[#This Row],[Artist 7 %]],CatalogTable[[#This Row],[Artist 8 %]],CatalogTable[[#This Row],[Artist 9%]]) -> 0 | I184: =IF(ISBLANK(E184),"",INDEX(UniqueArtist!B:B, MATCH(E184,UniqueArtist!A:A, 0))) -> Artefino Music | J184: =IFERROR(TRIM(LEFT(I184, IFERROR(FIND(",", I184)-1, LEN(I184)))), "") -> Artefino Music | K184: 1 | L184: =IFERROR(TRIM(MID(I184, FIND(",", I184) + 1, IFERROR(FIND(",", I184, FIND(",", I184) + 1) - FIND(",", I184) - 1, LEN(I184)))), "") | N184: =IFERROR(TRIM(MID(I184, FIND(",", I184, FIND(",", I184) + 1) + 1, IFERROR(FIND(",", I184, FIND(",", I184, FIND(",", I184) + 1) + 1) - FIND(",", I184, FIND(",", I184) + 1) - 1, LEN(I184)))), "") | P184: =IFERROR(TRIM(MID(I184, FIND(",", I184, FIND(",", I184, FIND(",", I184) + 1) + 1) + 1, IFERROR(FIND(",", I184, FIND(",", I184, FIND(",", I184, FIND(",", I184) + 1) + 1) + 1) - FIND(",", I184, FIND(",", I184, FIND(",", I184) + 1) + 1) - 1, LEN(I184)))), "") | R184: =IFERROR(TRIM(MID(I184, FIND(",", I184, FIND(",", I184, FIND(",", I184, FIND(",", I184) + 1) + 1) + 1) + 1, IFERROR(FIND(",", I184, FIND(",", I184, FIND(",", I184, FIND(",", I184, FIND(",", I184) + 1) + 1) + 1) + 1) - FIND(",", I184, FIND(",", I184, FIND(",", I184, FIND(",", I184) + 1) + 1) + 1) - 1, LEN(I184)))), "") | T184: =IFERROR(TRIM(MID(I184, FIND(",", I184, FIND(",", I184, FIND(",", I184, FIND(",", I184, FIND(",", I184, FIND(",", I184) + 1) + 1) + 1) + 1) + 1) + 1, IFERROR(FIND(",", I184, FIND(",", I184, FIND(",", I184, FIND(",", I184, FIND(",", I184, FIND(",", I184) + 1) + 1) + 1) + 1) + 1) - FIND(",", I184, FIND(",", I184, FIND(",", I184, FIND(",", I184, FIND(",", I184) + 1) + 1) + 1) + 1) - 1, LEN(I184)))), "") | V184: =IFERROR(TRIM(MID(I184, FIND(",", I184, FIND(",", I184, FIND(",", I184, FIND(",", I184, FIND(",", I184, FIND(",", I184, FIND(",", I184) + 1) + 1) + 1) + 1) + 1) + 1) + 1, IFERROR(FIND(",", I184, FIND(",", I184, FIND(",", I184, FIND(",", I184, FIND(",", I184, FIND(",", I184, FIND(",", I184) + 1) + 1) + 1) + 1) + 1) + 1) - FIND(",", I184, FIND(",", I184, FIND(",", I184, FIND(",", I184, FIND(",", I184, FIND(",", I184) + 1) + 1) + 1) + 1) + 1) - 1, LEN(I184)))), "") | X184: =IFERROR(TRIM(MID(I184, FIND(",", I184, FIND(",", I184, FIND(",", I184, FIND(",", I184, FIND(",", I184, FIND(",", I184, FIND(",", I184, FIND(",", I184) + 1) + 1) + 1) + 1) + 1) + 1) + 1) + 1, IFERROR(FIND(",", I184, FIND(",", I184, FIND(",", I184, FIND(",", I184, FIND(",", I184, FIND(",", I184, FIND(",", I184, FIND(",", I184) + 1) + 1) + 1) + 1) + 1) + 1) + 1) - FIND(",", I184, FIND(",", I184, FIND(",", I184, FIND(",", I184, FIND(",", I184, FIND(",", I184, FIND(",", I184) + 1) + 1) + 1) + 1) + 1) + 1) - 1, LEN(I184)))), "") | Z184: =IFERROR(TRIM(MID(I184, FIND(",", I184, FIND(",", I184, FIND(",", I184, FIND(",", I184, FIND(",", I184, FIND(",", I184, FIND(",", I184, FIND(",", I184, FIND(",", I184) + 1) + 1) + 1) + 1) + 1) + 1) + 1) + 1) + 1, IFERROR(FIND(",", I184, FIND(",", I184, FIND(",", I184, FIND(",", I184, FIND(",", I184, FIND(",", I184, FIND(",", I184, FIND(",", I184, FIND(",", I184) + 1) + 1) + 1) + 1) + 1) + 1) + 1) + 1) - FIND(",", I184, FIND(",", I184, FIND(",", I184, FIND(",", I184, FIND(",", I184, FIND(",", I184, FIND(",", I184, FIND(",", I184) + 1) + 1) + 1) + 1) + 1) + 1) + 1) - 1, LEN(I184)))), "")
A185: 3615936536010TC-ADX-18-59380 | B185: 3615936536010 | C185: TC-ADX-18-59380 | D185: 28 Abriles | E185: LOS DOS DE TAMAULIPAS | G185: AfinArte | H185: =100%-SUM(CatalogTable[[#This Row],[Artist 1 %]],CatalogTable[[#This Row],[Artist 2 %]],CatalogTable[[#This Row],[Artist 3 %]],CatalogTable[[#This Row],[Artist 4 %]],CatalogTable[[#This Row],[Artist 5 %]],CatalogTable[[#This Row],[Artist 6 %]],CatalogTable[[#This Row],[Artist 7 %]],CatalogTable[[#This Row],[Artist 8 %]],CatalogTable[[#This Row],[Artist 9%]]) -> 0.9 | I185: =IF(ISBLANK(E185),"",INDEX(UniqueArtist!B:B, MATCH(E185,UniqueArtist!A:A, 0))) -> Los Dos de Tamaulipas | J185: =IFERROR(TRIM(LEFT(I185, IFERROR(FIND(",", I185)-1, LEN(I185)))), "") -> Los Dos de Tamaulipas | K185: 0.1 | L185: =IFERROR(TRIM(MID(I185, FIND(",", I185) + 1, IFERROR(FIND(",", I185, FIND(",", I185) + 1) - FIND(",", I185) - 1, LEN(I185)))), "") | N185: =IFERROR(TRIM(MID(I185, FIND(",", I185, FIND(",", I185) + 1) + 1, IFERROR(FIND(",", I185, FIND(",", I185, FIND(",", I185) + 1) + 1) - FIND(",", I185, FIND(",", I185) + 1) - 1, LEN(I185)))), "") | P185: =IFERROR(TRIM(MID(I185, FIND(",", I185, FIND(",", I185, FIND(",", I185) + 1) + 1) + 1, IFERROR(FIND(",", I185, FIND(",", I185, FIND(",", I185, FIND(",", I185) + 1) + 1) + 1) - FIND(",", I185, FIND(",", I185, FIND(",", I185) + 1) + 1) - 1, LEN(I185)))), "") | R185: =IFERROR(TRIM(MID(I185, FIND(",", I185, FIND(",", I185, FIND(",", I185, FIND(",", I185) + 1) + 1) + 1) + 1, IFERROR(FIND(",", I185, FIND(",", I185, FIND(",", I185, FIND(",", I185, FIND(",", I185) + 1) + 1) + 1) + 1) - FIND(",", I185, FIND(",", I185, FIND(",", I185, FIND(",", I185) + 1) + 1) + 1) - 1, LEN(I185)))), "") | T185: =IFERROR(TRIM(MID(I185, FIND(",", I185, FIND(",", I185, FIND(",", I185, FIND(",", I185, FIND(",", I185, FIND(",", I185) + 1) + 1) + 1) + 1) + 1) + 1, IFERROR(FIND(",", I185, FIND(",", I185, FIND(",", I185, FIND(",", I185, FIND(",", I185, FIND(",", I185) + 1) + 1) + 1) + 1) + 1) - FIND(",", I185, FIND(",", I185, FIND(",", I185, FIND(",", I185, FIND(",", I185) + 1) + 1) + 1) + 1) - 1, LEN(I185)))), "") | V185: =IFERROR(TRIM(MID(I185, FIND(",", I185, FIND(",", I185, FIND(",", I185, FIND(",", I185, FIND(",", I185, FIND(",", I185, FIND(",", I185) + 1) + 1) + 1) + 1) + 1) + 1) + 1, IFERROR(FIND(",", I185, FIND(",", I185, FIND(",", I185, FIND(",", I185, FIND(",", I185, FIND(",", I185, FIND(",", I185) + 1) + 1) + 1) + 1) + 1) + 1) - FIND(",", I185, FIND(",", I185, FIND(",", I185, FIND(",", I185, FIND(",", I185, FIND(",", I185) + 1) + 1) + 1) + 1) + 1) - 1, LEN(I185)))), "") | X185: =IFERROR(TRIM(MID(I185, FIND(",", I185, FIND(",", I185, FIND(",", I185, FIND(",", I185, FIND(",", I185, FIND(",", I185, FIND(",", I185, FIND(",", I185) + 1) + 1) + 1) + 1) + 1) + 1) + 1) + 1, IFERROR(FIND(",", I185, FIND(",", I185, FIND(",", I185, FIND(",", I185, FIND(",", I185, FIND(",", I185, FIND(",", I185, FIND(",", I185) + 1) + 1) + 1) + 1) + 1) + 1) + 1) - FIND(",", I185, FIND(",", I185, FIND(",", I185, FIND(",", I185, FIND(",", I185, FIND(",", I185, FIND(",", I185) + 1) + 1) + 1) + 1) + 1) + 1) - 1, LEN(I185)))), "") | Z185: =IFERROR(TRIM(MID(I185, FIND(",", I185, FIND(",", I185, FIND(",", I185, FIND(",", I185, FIND(",", I185, FIND(",", I185, FIND(",", I185, FIND(",", I185, FIND(",", I185) + 1) + 1) + 1) + 1) + 1) + 1) + 1) + 1) + 1, IFERROR(FIND(",", I185, FIND(",", I185, FIND(",", I185, FIND(",", I185, FIND(",", I185, FIND(",", I185, FIND(",", I185, FIND(",", I185, FIND(",", I185) + 1) + 1) + 1) + 1) + 1) + 1) + 1) + 1) - FIND(",", I185, FIND(",", I185, FIND(",", I185, FIND(",", I185, FIND(",", I185, FIND(",", I185, FIND(",", I185, FIND(",", I185) + 1) + 1) + 1) + 1) + 1) + 1) + 1) - 1, LEN(I185)))), "")
A186: 3617226299766DG-A07-23-81566 | B186: 3617226299766 | C186: DG-A07-23-81566 | D186: 28 Abriles | E186: Los Dos Carnales | G186: AfinArte | H186: =100%-SUM(CatalogTable[[#This Row],[Artist 1 %]],CatalogTable[[#This Row],[Artist 2 %]],CatalogTable[[#This Row],[Artist 3 %]],CatalogTable[[#This Row],[Artist 4 %]],CatalogTable[[#This Row],[Artist 5 %]],CatalogTable[[#This Row],[Artist 6 %]],CatalogTable[[#This Row],[Artist 7 %]],CatalogTable[[#This Row],[Artist 8 %]],CatalogTable[[#This Row],[Artist 9%]]) -> 0.9 | I186: =IF(ISBLANK(E186),"",INDEX(UniqueArtist!B:B, MATCH(E186,UniqueArtist!A:A, 0))) -> Los Dos Carnales | J186: =IFERROR(TRIM(LEFT(I186, IFERROR(FIND(",", I186)-1, LEN(I186)))), "") -> Los Dos Carnales | K186: 0.1 | L186: =IFERROR(TRIM(MID(I186, FIND(",", I186) + 1, IFERROR(FIND(",", I186, FIND(",", I186) + 1) - FIND(",", I186) - 1, LEN(I186)))), "") | N186: =IFERROR(TRIM(MID(I186, FIND(",", I186, FIND(",", I186) + 1) + 1, IFERROR(FIND(",", I186, FIND(",", I186, FIND(",", I186) + 1) + 1) - FIND(",", I186, FIND(",", I186) + 1) - 1, LEN(I186)))), "") | P186: =IFERROR(TRIM(MID(I186, FIND(",", I186, FIND(",", I186, FIND(",", I186) + 1) + 1) + 1, IFERROR(FIND(",", I186, FIND(",", I186, FIND(",", I186, FIND(",", I186) + 1) + 1) + 1) - FIND(",", I186, FIND(",", I186, FIND(",", I186) + 1) + 1) - 1, LEN(I186)))), "") | R186: =IFERROR(TRIM(MID(I186, FIND(",", I186, FIND(",", I186, FIND(",", I186, FIND(",", I186) + 1) + 1) + 1) + 1, IFERROR(FIND(",", I186, FIND(",", I186, FIND(",", I186, FIND(",", I186, FIND(",", I186) + 1) + 1) + 1) + 1) - FIND(",", I186, FIND(",", I186, FIND(",", I186, FIND(",", I186) + 1) + 1) + 1) - 1, LEN(I186)))), "") | T186: =IFERROR(TRIM(MID(I186, FIND(",", I186, FIND(",", I186, FIND(",", I186, FIND(",", I186, FIND(",", I186, FIND(",", I186) + 1) + 1) + 1) + 1) + 1) + 1, IFERROR(FIND(",", I186, FIND(",", I186, FIND(",", I186, FIND(",", I186, FIND(",", I186, FIND(",", I186) + 1) + 1) + 1) + 1) + 1) - FIND(",", I186, FIND(",", I186, FIND(",", I186, FIND(",", I186, FIND(",", I186) + 1) + 1) + 1) + 1) - 1, LEN(I186)))), "") | V186: =IFERROR(TRIM(MID(I186, FIND(",", I186, FIND(",", I186, FIND(",", I186, FIND(",", I186, FIND(",", I186, FIND(",", I186, FIND(",", I186) + 1) + 1) + 1) + 1) + 1) + 1) + 1, IFERROR(FIND(",", I186, FIND(",", I186, FIND(",", I186, FIND(",", I186, FIND(",", I186, FIND(",", I186, FIND(",", I186) + 1) + 1) + 1) + 1) + 1) + 1) - FIND(",", I186, FIND(",", I186, FIND(",", I186, FIND(",", I186, FIND(",", I186, FIND(",", I186) + 1) + 1) + 1) + 1) + 1) - 1, LEN(I186)))), "") | X186: =IFERROR(TRIM(MID(I186, FIND(",", I186, FIND(",", I186, FIND(",", I186, FIND(",", I186, FIND(",", I186, FIND(",", I186, FIND(",", I186, FIND(",", I186) + 1) + 1) + 1) + 1) + 1) + 1) + 1) + 1, IFERROR(FIND(",", I186, FIND(",", I186, FIND(",", I186, FIND(",", I186, FIND(",", I186, FIND(",", I186, FIND(",", I186, FIND(",", I186) + 1) + 1) + 1) + 1) + 1) + 1) + 1) - FIND(",", I186, FIND(",", I186, FIND(",", I186, FIND(",", I186, FIND(",", I186, FIND(",", I186, FIND(",", I186) + 1) + 1) + 1) + 1) + 1) + 1) - 1, LEN(I186)))), "") | Z186: =IFERROR(TRIM(MID(I186, FIND(",", I186, FIND(",", I186, FIND(",", I186, FIND(",", I186, FIND(",", I186, FIND(",", I186, FIND(",", I186, FIND(",", I186, FIND(",", I186) + 1) + 1) + 1) + 1) + 1) + 1) + 1) + 1) + 1, IFERROR(FIND(",", I186, FIND(",", I186, FIND(",", I186, FIND(",", I186, FIND(",", I186, FIND(",", I186, FIND(",", I186, FIND(",", I186, FIND(",", I186) + 1) + 1) + 1) + 1) + 1) + 1) + 1) + 1) - FIND(",", I186, FIND(",", I186, FIND(",", I186, FIND(",", I186, FIND(",", I186, FIND(",", I186, FIND(",", I186, FIND(",", I186) + 1) + 1) + 1) + 1) + 1) + 1) + 1) - 1, LEN(I186)))), "")
A187: 3617226325267FR-26V-23-03502 | B187: 3617226325267 | C187: FR-26V-23-03502 | D187: 3 Doritos Depues 😂Nos cayo la tormenta!🌧️ #Shorts #ShortsVideo #LosDosCarnales #AfinArte | E187: Los Dos Carnales | G187: AfinArte | H187: =100%-SUM(CatalogTable[[#This Row],[Artist 1 %]],CatalogTable[[#This Row],[Artist 2 %]],CatalogTable[[#This Row],[Artist 3 %]],CatalogTable[[#This Row],[Artist 4 %]],CatalogTable[[#This Row],[Artist 5 %]],CatalogTable[[#This Row],[Artist 6 %]],CatalogTable[[#This Row],[Artist 7 %]],CatalogTable[[#This Row],[Artist 8 %]],CatalogTable[[#This Row],[Artist 9%]]) -> 0.9 | I187: =IF(ISBLANK(E187),"",INDEX(UniqueArtist!B:B, MATCH(E187,UniqueArtist!A:A, 0))) -> Los Dos Carnales | J187: =IFERROR(TRIM(LEFT(I187, IFERROR(FIND(",", I187)-1, LEN(I187)))), "") -> Los Dos Carnales | K187: 0.1 | L187: =IFERROR(TRIM(MID(I187, FIND(",", I187) + 1, IFERROR(FIND(",", I187, FIND(",", I187) + 1) - FIND(",", I187) - 1, LEN(I187)))), "") | N187: =IFERROR(TRIM(MID(I187, FIND(",", I187, FIND(",", I187) + 1) + 1, IFERROR(FIND(",", I187, FIND(",", I187, FIND(",", I187) + 1) + 1) - FIND(",", I187, FIND(",", I187) + 1) - 1, LEN(I187)))), "") | P187: =IFERROR(TRIM(MID(I187, FIND(",", I187, FIND(",", I187, FIND(",", I187) + 1) + 1) + 1, IFERROR(FIND(",", I187, FIND(",", I187, FIND(",", I187, FIND(",", I187) + 1) + 1) + 1) - FIND(",", I187, FIND(",", I187, FIND(",", I187) + 1) + 1) - 1, LEN(I187)))), "") | R187: =IFERROR(TRIM(MID(I187, FIND(",", I187, FIND(",", I187, FIND(",", I187, FIND(",", I187) + 1) + 1) + 1) + 1, IFERROR(FIND(",", I187, FIND(",", I187, FIND(",", I187, FIND(",", I187, FIND(",", I187) + 1) + 1) + 1) + 1) - FIND(",", I187, FIND(",", I187, FIND(",", I187, FIND(",", I187) + 1) + 1) + 1) - 1, LEN(I187)))), "") | T187: =IFERROR(TRIM(MID(I187, FIND(",", I187, FIND(",", I187, FIND(",", I187, FIND(",", I187, FIND(",", I187, FIND(",", I187) + 1) + 1) + 1) + 1) + 1) + 1, IFERROR(FIND(",", I187, FIND(",", I187, FIND(",", I187, FIND(",", I187, FIND(",", I187, FIND(",", I187) + 1) + 1) + 1) + 1) + 1) - FIND(",", I187, FIND(",", I187, FIND(",", I187, FIND(",", I187, FIND(",", I187) + 1) + 1) + 1) + 1) - 1, LEN(I187)))), "") | V187: =IFERROR(TRIM(MID(I187, FIND(",", I187, FIND(",", I187, FIND(",", I187, FIND(",", I187, FIND(",", I187, FIND(",", I187, FIND(",", I187) + 1) + 1) + 1) + 1) + 1) + 1) + 1, IFERROR(FIND(",", I187, FIND(",", I187, FIND(",", I187, FIND(",", I187, FIND(",", I187, FIND(",", I187, FIND(",", I187) + 1) + 1) + 1) + 1) + 1) + 1) - FIND(",", I187, FIND(",", I187, FIND(",", I187, FIND(",", I187, FIND(",", I187, FIND(",", I187) + 1) + 1) + 1) + 1) + 1) - 1, LEN(I187)))), "") | X187: =IFERROR(TRIM(MID(I187, FIND(",", I187, FIND(",", I187, FIND(",", I187, FIND(",", I187, FIND(",", I187, FIND(",", I187, FIND(",", I187, FIND(",", I187) + 1) + 1) + 1) + 1) + 1) + 1) + 1) + 1, IFERROR(FIND(",", I187, FIND(",", I187, FIND(",", I187, FIND(",", I187, FIND(",", I187, FIND(",", I187, FIND(",", I187, FIND(",", I187) + 1) + 1) + 1) + 1) + 1) + 1) + 1) - FIND(",", I187, FIND(",", I187, FIND(",", I187, FIND(",", I187, FIND(",", I187, FIND(",", I187, FIND(",", I187) + 1) + 1) + 1) + 1) + 1) + 1) - 1, LEN(I187)))), "") | Z187: =IFERROR(TRIM(MID(I187, FIND(",", I187, FIND(",", I187, FIND(",", I187, FIND(",", I187, FIND(",", I187, FIND(",", I187, FIND(",", I187, FIND(",", I187, FIND(",", I187) + 1) + 1) + 1) + 1) + 1) + 1) + 1) + 1) + 1, IFERROR(FIND(",", I187, FIND(",", I187, FIND(",", I187, FIND(",", I187, FIND(",", I187, FIND(",", I187, FIND(",", I187, FIND(",", I187, FIND(",", I187) + 1) + 1) + 1) + 1) + 1) + 1) + 1) + 1) - FIND(",", I187, FIND(",", I187, FIND(",", I187, FIND(",", I187, FIND(",", I187, FIND(",", I187, FIND(",", I187, FIND(",", I187) + 1) + 1) + 1) + 1) + 1) + 1) + 1) - 1, LEN(I187)))), "")
A188: 3615936535594TC-ADU-18-54837 | B188: 3615936535594 | C188: TC-ADU-18-54837 | D188: 3 Vueltas En Vivo | E188: Codice | G188: AfinArte | H188: =100%-SUM(CatalogTable[[#This Row],[Artist 1 %]],CatalogTable[[#This Row],[Artist 2 %]],CatalogTable[[#This Row],[Artist 3 %]],CatalogTable[[#This Row],[Artist 4 %]],CatalogTable[[#This Row],[Artist 5 %]],CatalogTable[[#This Row],[Artist 6 %]],CatalogTable[[#This Row],[Artist 7 %]],CatalogTable[[#This Row],[Artist 8 %]],CatalogTable[[#This Row],[Artist 9%]]) -> 0.9 | I188: =IF(ISBLANK(E188),"",INDEX(UniqueArtist!B:B, MATCH(E188,UniqueArtist!A:A, 0))) -> Codice | J188: =IFERROR(TRIM(LEFT(I188, IFERROR(FIND(",", I188)-1, LEN(I188)))), "") -> Codice | K188: 0.1 | L188: =IFERROR(TRIM(MID(I188, FIND(",", I188) + 1, IFERROR(FIND(",", I188, FIND(",", I188) + 1) - FIND(",", I188) - 1, LEN(I188)))), "") | N188: =IFERROR(TRIM(MID(I188, FIND(",", I188, FIND(",", I188) + 1) + 1, IFERROR(FIND(",", I188, FIND(",", I188, FIND(",", I188) + 1) + 1) - FIND(",", I188, FIND(",", I188) + 1) - 1, LEN(I188)))), "") | P188: =IFERROR(TRIM(MID(I188, FIND(",", I188, FIND(",", I188, FIND(",", I188) + 1) + 1) + 1, IFERROR(FIND(",", I188, FIND(",", I188, FIND(",", I188, FIND(",", I188) + 1) + 1) + 1) - FIND(",", I188, FIND(",", I188, FIND(",", I188) + 1) + 1) - 1, LEN(I188)))), "") | R188: =IFERROR(TRIM(MID(I188, FIND(",", I188, FIND(",", I188, FIND(",", I188, FIND(",", I188) + 1) + 1) + 1) + 1, IFERROR(FIND(",", I188, FIND(",", I188, FIND(",", I188, FIND(",", I188, FIND(",", I188) + 1) + 1) + 1) + 1) - FIND(",", I188, FIND(",", I188, FIND(",", I188, FIND(",", I188) + 1) + 1) + 1) - 1, LEN(I188)))), "") | T188: =IFERROR(TRIM(MID(I188, FIND(",", I188, FIND(",", I188, FIND(",", I188, FIND(",", I188, FIND(",", I188, FIND(",", I188) + 1) + 1) + 1) + 1) + 1) + 1, IFERROR(FIND(",", I188, FIND(",", I188, FIND(",", I188, FIND(",", I188, FIND(",", I188, FIND(",", I188) + 1) + 1) + 1) + 1) + 1) - FIND(",", I188, FIND(",", I188, FIND(",", I188, FIND(",", I188, FIND(",", I188) + 1) + 1) + 1) + 1) - 1, LEN(I188)))), "") | V188: =IFERROR(TRIM(MID(I188, FIND(",", I188, FIND(",", I188, FIND(",", I188, FIND(",", I188, FIND(",", I188, FIND(",", I188, FIND(",", I188) + 1) + 1) + 1) + 1) + 1) + 1) + 1, IFERROR(FIND(",", I188, FIND(",", I188, FIND(",", I188, FIND(",", I188, FIND(",", I188, FIND(",", I188, FIND(",", I188) + 1) + 1) + 1) + 1) + 1) + 1) - FIND(",", I188, FIND(",", I188, FIND(",", I188, FIND(",", I188, FIND(",", I188, FIND(",", I188) + 1) + 1) + 1) + 1) + 1) - 1, LEN(I188)))), "") | X188: =IFERROR(TRIM(MID(I188, FIND(",", I188, FIND(",", I188, FIND(",", I188, FIND(",", I188, FIND(",", I188, FIND(",", I188, FIND(",", I188, FIND(",", I188) + 1) + 1) + 1) + 1) + 1) + 1) + 1) + 1, IFERROR(FIND(",", I188, FIND(",", I188, FIND(",", I188, FIND(",", I188, FIND(",", I188, FIND(",", I188, FIND(",", I188, FIND(",", I188) + 1) + 1) + 1) + 1) + 1) + 1) + 1) - FIND(",", I188, FIND(",", I188, FIND(",", I188, FIND(",", I188, FIND(",", I188, FIND(",", I188, FIND(",", I188) + 1) + 1) + 1) + 1) + 1) + 1) - 1, LEN(I188)))), "") | Z188: =IFERROR(TRIM(MID(I188, FIND(",", I188, FIND(",", I188, FIND(",", I188, FIND(",", I188, FIND(",", I188, FIND(",", I188, FIND(",", I188, FIND(",", I188, FIND(",", I188) + 1) + 1) + 1) + 1) + 1) + 1) + 1) + 1) + 1, IFERROR(FIND(",", I188, FIND(",", I188, FIND(",", I188, FIND(",", I188, FIND(",", I188, FIND(",", I188, FIND(",", I188, FIND(",", I188, FIND(",", I188) + 1) + 1) + 1) + 1) + 1) + 1) + 1) + 1) - FIND(",", I188, FIND(",", I188, FIND(",", I188, FIND(",", I188, FIND(",", I188, FIND(",", I188, FIND(",", I188, FIND(",", I188) + 1) + 1) + 1) + 1) + 1) + 1) + 1) - 1, LEN(I188)))), "")
A189: 3617228167421FR-26V-23-69957 | B189: 3617228167421 | C189: FR-26V-23-69957 | D189: 3.- EL DE CIUDAD HIDALGO | E189: Alemi Bustos | G189: AfinArte | H189: =100%-SUM(CatalogTable[[#This Row],[Artist 1 %]],CatalogTable[[#This Row],[Artist 2 %]],CatalogTable[[#This Row],[Artist 3 %]],CatalogTable[[#This Row],[Artist 4 %]],CatalogTable[[#This Row],[Artist 5 %]],CatalogTable[[#This Row],[Artist 6 %]],CatalogTable[[#This Row],[Artist 7 %]],CatalogTable[[#This Row],[Artist 8 %]],CatalogTable[[#This Row],[Artist 9%]]) -> 0.9 | I189: =IF(ISBLANK(E189),"",INDEX(UniqueArtist!B:B, MATCH(E189,UniqueArtist!A:A, 0))) -> Alemi Bustos | J189: =IFERROR(TRIM(LEFT(I189, IFERROR(FIND(",", I189)-1, LEN(I189)))), "") -> Alemi Bustos | K189: 0.1 | L189: =IFERROR(TRIM(MID(I189, FIND(",", I189) + 1, IFERROR(FIND(",", I189, FIND(",", I189) + 1) - FIND(",", I189) - 1, LEN(I189)))), "") | N189: =IFERROR(TRIM(MID(I189, FIND(",", I189, FIND(",", I189) + 1) + 1, IFERROR(FIND(",", I189, FIND(",", I189, FIND(",", I189) + 1) + 1) - FIND(",", I189, FIND(",", I189) + 1) - 1, LEN(I189)))), "") | P189: =IFERROR(TRIM(MID(I189, FIND(",", I189, FIND(",", I189, FIND(",", I189) + 1) + 1) + 1, IFERROR(FIND(",", I189, FIND(",", I189, FIND(",", I189, FIND(",", I189) + 1) + 1) + 1) - FIND(",", I189, FIND(",", I189, FIND(",", I189) + 1) + 1) - 1, LEN(I189)))), "") | R189: =IFERROR(TRIM(MID(I189, FIND(",", I189, FIND(",", I189, FIND(",", I189, FIND(",", I189) + 1) + 1) + 1) + 1, IFERROR(FIND(",", I189, FIND(",", I189, FIND(",", I189, FIND(",", I189, FIND(",", I189) + 1) + 1) + 1) + 1) - FIND(",", I189, FIND(",", I189, FIND(",", I189, FIND(",", I189) + 1) + 1) + 1) - 1, LEN(I189)))), "") | T189: =IFERROR(TRIM(MID(I189, FIND(",", I189, FIND(",", I189, FIND(",", I189, FIND(",", I189, FIND(",", I189, FIND(",", I189) + 1) + 1) + 1) + 1) + 1) + 1, IFERROR(FIND(",", I189, FIND(",", I189, FIND(",", I189, FIND(",", I189, FIND(",", I189, FIND(",", I189) + 1) + 1) + 1) + 1) + 1) - FIND(",", I189, FIND(",", I189, FIND(",", I189, FIND(",", I189, FIND(",", I189) + 1) + 1) + 1) + 1) - 1, LEN(I189)))), "") | V189: =IFERROR(TRIM(MID(I189, FIND(",", I189, FIND(",", I189, FIND(",", I189, FIND(",", I189, FIND(",", I189, FIND(",", I189, FIND(",", I189) + 1) + 1) + 1) + 1) + 1) + 1) + 1, IFERROR(FIND(",", I189, FIND(",", I189, FIND(",", I189, FIND(",", I189, FIND(",", I189, FIND(",", I189, FIND(",", I189) + 1) + 1) + 1) + 1) + 1) + 1) - FIND(",", I189, FIND(",", I189, FIND(",", I189, FIND(",", I189, FIND(",", I189, FIND(",", I189) + 1) + 1) + 1) + 1) + 1) - 1, LEN(I189)))), "") | X189: =IFERROR(TRIM(MID(I189, FIND(",", I189, FIND(",", I189, FIND(",", I189, FIND(",", I189, FIND(",", I189, FIND(",", I189, FIND(",", I189, FIND(",", I189) + 1) + 1) + 1) + 1) + 1) + 1) + 1) + 1, IFERROR(FIND(",", I189, FIND(",", I189, FIND(",", I189, FIND(",", I189, FIND(",", I189, FIND(",", I189, FIND(",", I189, FIND(",", I189) + 1) + 1) + 1) + 1) + 1) + 1) + 1) - FIND(",", I189, FIND(",", I189, FIND(",", I189, FIND(",", I189, FIND(",", I189, FIND(",", I189, FIND(",", I189) + 1) + 1) + 1) + 1) + 1) + 1) - 1, LEN(I189)))), "") | Z189: =IFERROR(TRIM(MID(I189, FIND(",", I189, FIND(",", I189, FIND(",", I189, FIND(",", I189, FIND(",", I189, FIND(",", I189, FIND(",", I189, FIND(",", I189, FIND(",", I189) + 1) + 1) + 1) + 1) + 1) + 1) + 1) + 1) + 1, IFERROR(FIND(",", I189, FIND(",", I189, FIND(",", I189, FIND(",", I189, FIND(",", I189, FIND(",", I189, FIND(",", I189, FIND(",", I189, FIND(",", I189) + 1) + 1) + 1) + 1) + 1) + 1) + 1) + 1) - FIND(",", I189, FIND(",", I189, FIND(",", I189, FIND(",", I189, FIND(",", I189, FIND(",", I189, FIND(",", I189, FIND(",", I189) + 1) + 1) + 1) + 1) + 1) + 1) + 1) - 1, LEN(I189)))), "")
A190: 3617226962547FR-26V-23-26155 | B190: 3617226962547 | C190: FR-26V-23-26155 | D190: 3.- Los Dos Carnales - Al Pasar La Lista (Visualizer) | E190: Los Dos Carnales | G190: AfinArte | H190: =100%-SUM(CatalogTable[[#This Row],[Artist 1 %]],CatalogTable[[#This Row],[Artist 2 %]],CatalogTable[[#This Row],[Artist 3 %]],CatalogTable[[#This Row],[Artist 4 %]],CatalogTable[[#This Row],[Artist 5 %]],CatalogTable[[#This Row],[Artist 6 %]],CatalogTable[[#This Row],[Artist 7 %]],CatalogTable[[#This Row],[Artist 8 %]],CatalogTable[[#This Row],[Artist 9%]]) -> 0.9 | I190: =IF(ISBLANK(E190),"",INDEX(UniqueArtist!B:B, MATCH(E190,UniqueArtist!A:A, 0))) -> Los Dos Carnales | J190: =IFERROR(TRIM(LEFT(I190, IFERROR(FIND(",", I190)-1, LEN(I190)))), "") -> Los Dos Carnales | K190: 0.1 | L190: =IFERROR(TRIM(MID(I190, FIND(",", I190) + 1, IFERROR(FIND(",", I190, FIND(",", I190) + 1) - FIND(",", I190) - 1, LEN(I190)))), "") | N190: =IFERROR(TRIM(MID(I190, FIND(",", I190, FIND(",", I190) + 1) + 1, IFERROR(FIND(",", I190, FIND(",", I190, FIND(",", I190) + 1) + 1) - FIND(",", I190, FIND(",", I190) + 1) - 1, LEN(I190)))), "") | P190: =IFERROR(TRIM(MID(I190, FIND(",", I190, FIND(",", I190, FIND(",", I190) + 1) + 1) + 1, IFERROR(FIND(",", I190, FIND(",", I190, FIND(",", I190, FIND(",", I190) + 1) + 1) + 1) - FIND(",", I190, FIND(",", I190, FIND(",", I190) + 1) + 1) - 1, LEN(I190)))), "") | R190: =IFERROR(TRIM(MID(I190, FIND(",", I190, FIND(",", I190, FIND(",", I190, FIND(",", I190) + 1) + 1) + 1) + 1, IFERROR(FIND(",", I190, FIND(",", I190, FIND(",", I190, FIND(",", I190, FIND(",", I190) + 1) + 1) + 1) + 1) - FIND(",", I190, FIND(",", I190, FIND(",", I190, FIND(",", I190) + 1) + 1) + 1) - 1, LEN(I190)))), "") | T190: =IFERROR(TRIM(MID(I190, FIND(",", I190, FIND(",", I190, FIND(",", I190, FIND(",", I190, FIND(",", I190, FIND(",", I190) + 1) + 1) + 1) + 1) + 1) + 1, IFERROR(FIND(",", I190, FIND(",", I190, FIND(",", I190, FIND(",", I190, FIND(",", I190, FIND(",", I190) + 1) + 1) + 1) + 1) + 1) - FIND(",", I190, FIND(",", I190, FIND(",", I190, FIND(",", I190, FIND(",", I190) + 1) + 1) + 1) + 1) - 1, LEN(I190)))), "") | V190: =IFERROR(TRIM(MID(I190, FIND(",", I190, FIND(",", I190, FIND(",", I190, FIND(",", I190, FIND(",", I190, FIND(",", I190, FIND(",", I190) + 1) + 1) + 1) + 1) + 1) + 1) + 1, IFERROR(FIND(",", I190, FIND(",", I190, FIND(",", I190, FIND(",", I190, FIND(",", I190, FIND(",", I190, FIND(",", I190) + 1) + 1) + 1) + 1) + 1) + 1) - FIND(",", I190, FIND(",", I190, FIND(",", I190, FIND(",", I190, FIND(",", I190, FIND(",", I190) + 1) + 1) + 1) + 1) + 1) - 1, LEN(I190)))), "") | X190: =IFERROR(TRIM(MID(I190, FIND(",", I190, FIND(",", I190, FIND(",", I190, FIND(",", I190, FIND(",", I190, FIND(",", I190, FIND(",", I190, FIND(",", I190) + 1) + 1) + 1) + 1) + 1) + 1) + 1) + 1, IFERROR(FIND(",", I190, FIND(",", I190, FIND(",", I190, FIND(",", I190, FIND(",", I190, FIND(",", I190, FIND(",", I190, FIND(",", I190) + 1) + 1) + 1) + 1) + 1) + 1) + 1) - FIND(",", I190, FIND(",", I190, FIND(",", I190, FIND(",", I190, FIND(",", I190, FIND(",", I190, FIND(",", I190) + 1) + 1) + 1) + 1) + 1) + 1) - 1, LEN(I190)))), "") | Z190: =IFERROR(TRIM(MID(I190, FIND(",", I190, FIND(",", I190, FIND(",", I190, FIND(",", I190, FIND(",", I190, FIND(",", I190, FIND(",", I190, FIND(",", I190, FIND(",", I190) + 1) + 1) + 1) + 1) + 1) + 1) + 1) + 1) + 1, IFERROR(FIND(",", I190, FIND(",", I190, FIND(",", I190, FIND(",", I190, FIND(",", I190, FIND(",", I190, FIND(",", I190, FIND(",", I190, FIND(",", I190) + 1) + 1) + 1) + 1) + 1) + 1) + 1) + 1) - FIND(",", I190, FIND(",", I190, FIND(",", I190, FIND(",", I190, FIND(",", I190, FIND(",", I190, FIND(",", I190, FIND(",", I190) + 1) + 1) + 1) + 1) + 1) + 1) + 1) - 1, LEN(I190)))), "")
